Workbook

Sheet Lectura
A1: ¿El negocio da o no da? Lectura con los números a la vista
A2: Cota optimista: los costos sin dato (alquiler de la casa, luz, gas y agua, contador, pileta, cabinas) están en 0 o en un piso. Precios: lista de la zona cercana (Ambrela). USD constantes sin IVA.
A4: Indicador | B4: Conservador | C4: Base | D4: Favorable | E4: Cómo se lee
A5: Precio neto promedio por miembro flex (USD por mes, sin IVA) | B5: =Equilibrio!B5 -> 40.911952 | C5: =Equilibrio!C5 -> 46.972982 | D5: =Equilibrio!D5 -> 50.382311 | E5: Mezcla de planes con el precio de la zona, menos descuento, sin IVA.
A6: Miembros flex necesarios para cubrir los costos | B6: =Equilibrio!B11 -> 204.61133 | C6: =Equilibrio!C11 -> 77.930628 | D6: =Equilibrio!D11 -> 31.457124 | E6: En régimen (mes 36).
A7: Tope de miembros flex que entran en los puestos | B7: =Equilibrio!B12 -> 45.561793 | C7: =Equilibrio!C12 -> 60.325567 | D7: =Equilibrio!D12 -> 78.074689 | E7: Puestos simultáneos, con el pico de martes a jueves.
A8: El equilibrio necesita este % del tope | B8: =Equilibrio!B13 -> 4.4908534 | C8: =Equilibrio!C13 -> 1.2918342 | D8: =Equilibrio!D13 -> 0.40291065 | E8: Más de 100 %: no alcanza ni con todos los puestos llenos.
A9: Resultado operativo mensual con todos los puestos llenos (mejor caso) | B9: =Equilibrio!B12*Equilibrio!B8+Equilibrio!B10-Equilibrio!B9 -> -3604.4912 | C9: =Equilibrio!C12*Equilibrio!C8+Equilibrio!C10-Equilibrio!C9 -> -618.15699 | D9: =Equilibrio!D12*Equilibrio!D8+Equilibrio!D10-Equilibrio!D9 -> 2054.3494 | E9: Si es negativo, el negocio pierde plata aunque se llene.
A10: Resultado operativo mensual en el mes 36 (con las altas supuestas) | B10: =Resumen!B11 -> -4343.6254 | C10: =Resumen!C11 -> -1603.6953 | D10: =Resumen!D11 -> 1078.5811 | E10: Antes de Ganancias y sin alquilar la casa.
A11: Inversión inicial (sin capital de trabajo) | B11: =Resumen!B5 -> 275790.19 | C11: =Resumen!C5 -> 197524.94 | D11: =Resumen!D5 -> 135685.4 | E11: Obra, equipamiento, honorarios, trámites y contingencias.
A12: Años para recuperar la inversión con todos los puestos llenos | B12: =IF(B9>0,B11/(B9*12),"no la recupera") -> no la recupera | C12: =IF(C9>0,C11/(C9*12),"no la recupera") -> no la recupera | D12: =IF(D9>0,D11/(D9*12),"no la recupera") -> 5.5039893 | E12: Inversión / (mejor caso × 12).
A13: Precio necesario para equilibrar con el 80 % del tope (veces el precio del escenario) | B13: =(Equilibrio!B9+0.8*Equilibrio!B12*(Equilibrio!B7-Equilibrio!B5*((1+Supuestos!$D$7*Supuestos!$D$8)*(Supuestos!$D$54+Supuestos!$D$56)+Supuestos!$D$55)))/(0.8*Equilibrio!B12*Equilibrio!B5*(1-((1+Supuestos!$D$7*Supuestos!$D$8)*(Supuestos!$D$54+Supuestos!$D$56)+Supuestos!$D$55))+Equilibrio!B10) -> 3.1829985 | C13: =(Equilibrio!C9+0.8*Equilibrio!C12*(Equilibrio!C7-Equilibrio!C5*((1+Supuestos!$E$7*Supuestos!$E$8)*(Supuestos!$E$54+Supuestos!$E$56)+Supuestos!$E$55)))/(0.8*Equilibrio!C12*Equilibrio!C5*(1-((1+Supuestos!$E$7*Supuestos!$E$8)*(Supuestos!$E$54+Supuestos!$E$56)+Supuestos!$E$55))+Equilibrio!C10) -> 1.3382453 | D13: =(Equilibrio!D9+0.8*Equilibrio!D12*(Equilibrio!D7-Equilibrio!D5*((1+Supuestos!$F$7*Supuestos!$F$8)*(Supuestos!$F$54+Supuestos!$F$56)+Supuestos!$F$55)))/(0.8*Equilibrio!D12*Equilibrio!D5*(1-((1+Supuestos!$F$7*Supuestos!$F$8)*(Supuestos!$F$54+Supuestos!$F$56)+Supuestos!$F$55))+Equilibrio!D10) -> 0.71522535 | E13: 1,00 = los precios de hoy; 2,00 = el doble.
A14: Plan de 12 días por mes necesario para equilibrar al 80 % (ARS con IVA) | B14: =B13*Supuestos!$D$27*Supuestos!$D$37 -> 295063.96 | C14: =C13*Supuestos!$E$27*Supuestos!$E$37 -> 137839.27 | D14: =D13*Supuestos!$F$27*Supuestos!$F$37 -> 77351.622 | E14: Comparar con Ambrela 3 días/sem (103.000) y HUERTA 12 días (302.500 con IVA), ver hoja Mercado_verificado.
A15: Mejor caso si el dueño atiende y no hay personal pago (USD por mes) | B15: =B9+Modelo_Conservador!AM30*(1+Supuestos!$D$69) -> -1725.9392 | C15: =C9+Modelo_Base!AM30*(1+Supuestos!$E$69) -> 1121.903 | D15: =D9+Modelo_Favorable!AM30*(1+Supuestos!$F$69) -> 3707.9419 | E15: Suma el sueldo y las cargas que se ahorran (con el % de imprevistos). El tiempo del dueño no está valorado.
A16: Años para recuperar la inversión en ese caso | B16: =IF(B15>0,B11/(B15*12),"no la recupera") -> no la recupera | C16: =IF(C15>0,C11/(C15*12),"no la recupera") -> 14.671867 | D16: =IF(D15>0,D11/(D15*12),"no la recupera") -> 3.0494321 | E16: Inversión / (resultado × 12), con todos los puestos llenos.
A17: VEREDICTO (cota optimista) | B17: =IF(B9<0,"NO DA",IF(B8>0.8,"AJUSTADO",IF(B12>5,"SOLO OPERATIVO","DA"))) -> NO DA | C17: =IF(C9<0,"NO DA",IF(C8>0.8,"AJUSTADO",IF(C12>5,"SOLO OPERATIVO","DA"))) -> NO DA | D17: =IF(D9<0,"NO DA",IF(D8>0.8,"AJUSTADO",IF(D12>5,"SOLO OPERATIVO","DA"))) -> SOLO OPERATIVO | E17: NO DA = aun lleno no cubre los costos · AJUSTADO = necesita más del 80 % del tope · SOLO OPERATIVO = cubre los costos pero la inversión tarda más de 5 años en volver · DA = cubre y recupera en 5 años o menos.
A19: Aparte, NO verificado y fuera del modelo: elburó (Villa Urquiza, ficha probable) publica Flex 'desde' ARS 115.000 y puesto fijo ARS 257.000 a 300.000, sin fecha ni IVA (datos/sedes_G3.json, G3-01). Si se confirmara, sugiere precios cerca de 30 % más altos que Ambrela en planes flex.

Sheet Resumen
A1: Resumen por escenario
A2: Todo se recalcula al cambiar Supuestos. USD constantes; resultado antes del impuesto a las Ganancias.
A4: Indicador | B4: Conservador | C4: Base | D4: Favorable | E4: Cómo se lee
A5: Inversión inicial (sin capital de trabajo) | B5: =Inversion!D21 -> 275790.19 | C5: =Inversion!E21 -> 197524.94 | D5: =Inversion!F21 -> 135685.4 | E5: Obra, equipamiento, honorarios, trámites, apertura y contingencias.
A6: Necesidad máxima de caja (inversión + pérdidas de arranque) | B6: =-MIN(Modelo_Conservador!C45:AM45) -> 434690.54 | C6: =-MIN(Modelo_Base!C45:AM45) -> 265076 | D6: =-MIN(Modelo_Favorable!C45:AM45) -> 141419.64 | E6: Lo que hay que tener disponible en el peor momento del flujo acumulado.
A7: Miembros flex en el mes 12 | B7: =Modelo_Conservador!O7 -> 15.80834 | C7: =Modelo_Base!O7 -> 28.583586 | D7: =Modelo_Favorable!O7 -> 46.06943
A8: Miembros flex en el mes 36 | B8: =Modelo_Conservador!AM7 -> 12.947217 | C8: =Modelo_Base!AM7 -> 32.257515 | D8: =Modelo_Favorable!AM7 -> 55.932426 | E8: Limitado por el tope de puestos en el pico.
A9: Ocupación promedio de puestos flex, mes 36 | B9: =Modelo_Conservador!AM12 -> 0.21049503 | C9: =Modelo_Base!AM12 -> 0.41132598 | D9: =Modelo_Favorable!AM12 -> 0.57311712 | E9: Puestos-día usados / puestos-día disponibles en días hábiles.
A10: Ingresos del mes 36 (USD sin IVA) | B10: =Modelo_Conservador!AM21 -> 1336.8161 | C10: =Modelo_Base!AM21 -> 2828.8044 | D10: =Modelo_Favorable!AM21 -> 4875.8085
A11: Resultado operativo del mes 36 | B11: =Modelo_Conservador!AM42 -> -4343.6254 | C11: =Modelo_Base!AM42 -> -1603.6953 | D11: =Modelo_Favorable!AM42 -> 1078.5811
A12: Resultado operativo acumulado de los 36 meses | B12: =SUM(Modelo_Conservador!D42:AM42) -> -158900.36 | C12: =SUM(Modelo_Base!D42:AM42) -> -67551.058 | D12: =SUM(Modelo_Favorable!D42:AM42) -> 18897.552
A13: Margen operativo del año 3 | B13: =IFERROR(SUM(Modelo_Conservador!AB42:AM42)/SUM(Modelo_Conservador!AB21:AM21),0) -> -3.2157883 | C13: =IFERROR(SUM(Modelo_Base!AB42:AM42)/SUM(Modelo_Base!AB21:AM21),0) -> -0.57727416 | D13: =IFERROR(SUM(Modelo_Favorable!AB42:AM42)/SUM(Modelo_Favorable!AB21:AM21),0) -> 0.21154443 | E13: Resultado operativo / ingresos, meses 25 a 36.
A14: Mes de recupero de la inversión (caja, casa propia) | B14: =IFERROR(MATCH(TRUE(),INDEX(Modelo_Conservador!C45:AM45>=0,0),0)-1,"no recupera en 36 meses") -> no recupera en 36 meses | C14: =IFERROR(MATCH(TRUE(),INDEX(Modelo_Base!C45:AM45>=0,0),0)-1,"no recupera en 36 meses") -> no recupera en 36 meses | D14: =IFERROR(MATCH(TRUE(),INDEX(Modelo_Favorable!C45:AM45>=0,0),0)-1,"no recupera en 36 meses") -> no recupera en 36 meses | E14: Primer mes con flujo acumulado ≥ 0.
A15: Mes de recupero frente a alquilar la casa | B15: =IFERROR(MATCH(TRUE(),INDEX(Modelo_Conservador!C48:AM48>=0,0),0)-1,"no recupera en 36 meses") -> no recupera en 36 meses | C15: =IFERROR(MATCH(TRUE(),INDEX(Modelo_Base!C48:AM48>=0,0),0)-1,"no recupera en 36 meses") -> no recupera en 36 meses | D15: =IFERROR(MATCH(TRUE(),INDEX(Modelo_Favorable!C48:AM48>=0,0),0)-1,"no recupera en 36 meses") -> no recupera en 36 meses | E15: Igual, restando cada mes el alquiler que se deja de cobrar.
A16: TIR anual a 36 meses, sin valor residual (caja) | B16: =IFERROR((1+IRR(Modelo_Conservador!C44:AM44))^12-1,"no calculable") -> no calculable | C16: =IFERROR((1+IRR(Modelo_Base!C44:AM44))^12-1,"no calculable") -> no calculable | D16: =IFERROR((1+IRR(Modelo_Favorable!C44:AM44))^12-1,"no calculable") -> no calculable | E16: Conservadora: no suma lo que vale el negocio ni el equipamiento al mes 36.
A17: VAN a 36 meses con la tasa de Supuestos (caja) | B17: =NPV((1+Supuestos!$D$92)^(1/12)-1,Modelo_Conservador!D44:AM44)+Modelo_Conservador!C44+Supuestos!$D$93/(1+Supuestos!$D$92)^3 -> -410246.25 | C17: =NPV((1+Supuestos!$E$92)^(1/12)-1,Modelo_Base!D44:AM44)+Modelo_Base!C44+Supuestos!$E$93/(1+Supuestos!$E$92)^3 -> -255543.63 | D17: =NPV((1+Supuestos!$F$92)^(1/12)-1,Modelo_Favorable!D44:AM44)+Modelo_Favorable!C44+Supuestos!$F$93/(1+Supuestos!$F$92)^3 -> -121557.68 | E17: La tasa la define el inversor; el valor que viene es un supuesto.
A18: Alquiler de mercado de la casa que se deja de cobrar (por mes) | B18: =Supuestos!$D$91 -> 0 | C18: =Supuestos!$E$91 -> 0 | D18: =Supuestos!$F$91 -> 0 | E18: Costo de oportunidad de usar la casa propia.
A19: Resultado operativo del año 3 menos el alquiler que se deja de cobrar (por mes) | B19: =AVERAGE(Modelo_Conservador!AB42:AM42)-Supuestos!$D$91 -> -4337.0558 | C19: =AVERAGE(Modelo_Base!AB42:AM42)-Supuestos!$E$91 -> -1620.228 | D19: =AVERAGE(Modelo_Favorable!AB42:AM42)-Supuestos!$F$91 -> 1016.415 | E19: Si es negativo, alquilar la casa rinde más que el coworking (antes de impuestos).

Sheet Supuestos
A1: Supuestos del modelo (celdas azules = entradas editables)
A2: Marco monetario: USD constantes al 27/10/2026. TC de conversión de precios en pesos: ver fila 'tc'. Sin previsiones de inflación ni devaluación. Cada valor tiene su fuente o se marca como supuesto a validar.
A4: Clave | B4: Supuesto | C4: Unidad | D4: Conservador | E4: Base | F4: Favorable | G4: Fuente / justificación | H4: Tipo
A5: GENERALES
A6: tc | B6: Tipo de cambio para pasar pesos a dólares | C6: ARS por USD | D6: 1560 | E6: 1560 | F6: 1560 | G6: dolarapi.com, dólar oficial BNA venta, 27/10/2026 (datos/alquiler_oficinas.json). | H6: dato
A7: iva | B7: Alícuota de IVA | C7: % | D7: 0.21 | E7: 0.21 | F7: 0.21 | G7: Ley de IVA, alícuota general. | H7: dato
A8: ri | B8: ¿Responsable inscripto? (1 = sí, 0 = monotributo) | C8: 1/0 | D8: 1 | E8: 1 | F8: 1 | G8: Monotributo no alcanza: tope de 200 m² para locaciones/servicios (LEEME); se asume Responsable Inscripto. A confirmar con contador. | H8: supuesto
A9: dias_habiles | B9: Días hábiles por mes | C9: días | D9: 21 | E9: 21 | F9: 21 | G9: Promedio de lunes a viernes sin feriados nacionales (aprox.). | H9: supuesto
A10: meses_obra | B10: Meses de obra y habilitación antes de abrir | C10: meses | D10: 6 | E10: 4 | F10: 3 | G10: Supuesto a validar con el arquitecto y el gestor. | H10: a validar
A11: CAPACIDAD (casa de 450 m²: subsuelo, planta baja + patio, planta alta; distribución sin plano)
A12: puestos_flex | B12: Puestos flexibles (simultáneos) | C12: puestos | D12: 30 | E12: 36 | F12: 42 | G12: SUPUESTO sin plano ni dato en el repo: 7,5 a 11 m² totales por puesto (incluye baños, cocina, salas, circulación y escalera). El coeficiente de ocupación del Código (Art. 3.4.7.2) no se pudo verificar (entorno_y_normativa.md, 2.3). | H12: a validar
A13: puestos_fijos | B13: Puestos fijos (escritorio asignado) | C13: puestos | D13: 4 | E13: 6 | F13: 8 | G13: SUPUESTO sin plano ni dato en el repo: 7,5 a 11 m² totales por puesto (incluye baños, cocina, salas, circulación y escalera). El coeficiente de ocupación del Código (Art. 3.4.7.2) no se pudo verificar (entorno_y_normativa.md, 2.3). | H13: a validar
A14: oficinas_priv | B14: Oficinas privadas chicas (complemento) | C14: oficinas | D14: 2 | E14: 2 | F14: 3 | G14: SUPUESTO sin plano ni dato en el repo: 7,5 a 11 m² totales por puesto (incluye baños, cocina, salas, circulación y escalera). El coeficiente de ocupación del Código (Art. 3.4.7.2) no se pudo verificar (entorno_y_normativa.md, 2.3). | H14: a validar
A15: puestos_por_oficina | B15: Puestos por oficina privada | C15: puestos | D15: 3 | E15: 3 | F15: 3 | G15: Oficina de 3 personas (aprox. 12–15 m²). | H15: supuesto
A16: USO DE LOS PUESTOS
A17: uso_flex | B17: Uso real de los días incluidos (flex) | C17: % | D17: 0.85 | E17: 0.8 | F17: 0.75 | G17: Mayor uso = menos membresías por puesto (por eso el conservador usa el más alto). Supuesto a medir en la preventa. | H17: a validar
A18: factor_pico | B18: Pico de asistencia sobre el promedio (mar-jue) | C18: veces | D18: 1.35 | E18: 1.3 | F18: 1.25 | G18: Los coworkings se llenan martes a jueves; supuesto a medir. | H18: a validar
A19: uso_fijo | B19: Uso de los puestos fijos y oficinas (para consumo) | C19: % | D19: 0.8 | E19: 0.8 | F19: 0.8 | G19: Supuesto. | H19: supuesto
A20: PLANES Y PRECIOS (ARS por mes, con IVA, como se publican)
A21: dias_p1 | B21: Plan 4 días por mes: días incluidos | C21: días/mes | D21: 4 | E21: 4 | F21: 4 | G21: Diseño de la oferta propuesta. | H21: supuesto
A22: dias_p2 | B22: Plan 8 días por mes (≈2 por semana): días incluidos | C22: días/mes | D22: 8 | E22: 8 | F22: 8 | G22: Diseño de la oferta propuesta. | H22: supuesto
A23: dias_p3 | B23: Plan 12 días por mes (≈3 por semana): días incluidos | C23: días/mes | D23: 12 | E23: 12 | F23: 12 | G23: Diseño de la oferta propuesta. | H23: supuesto
A24: dias_p4 | B24: Plan ilimitado flex (lunes a viernes): días incluidos | C24: días/mes | D24: 21 | E24: 21 | F24: 21 | G24: Diseño de la oferta propuesta. | H24: supuesto
A25: precio_p1 | B25: Precio plan 1 | C25: ARS/mes | D25: 54900 | E25: 54900 | F25: 54900 | G25: DERIVADO, no publicado: Ambrela no vende plan de 4 días. Precio del plan 2 días/sem (89.000) × proporción 4D/8D de HUERTA (135.000/219.000). | H25: mercado
A26: precio_p2 | B26: Precio plan 2 | C26: ARS/mes | D26: 89000 | E26: 89000 | F26: 89000 | G26: Ambrela (Devoto, 3,6 km; único competidor directo), datos/sedes_G1A.json G1A-01: precio publicado sin fecha ni IVA aclarado y sin moneda explícita (se asume ARS por magnitud, sin confirmar); se toma como precio final. Plan 'Start Point 2 Días' (≈ 8-9 días por mes). | H26: mercado
A27: precio_p3 | B27: Precio plan 3 | C27: ARS/mes | D27: 103000 | E27: 103000 | F27: 103000 | G27: Ambrela (Devoto, 3,6 km; único competidor directo), datos/sedes_G1A.json G1A-01: precio publicado sin fecha ni IVA aclarado y sin moneda explícita (se asume ARS por magnitud, sin confirmar); se toma como precio final. Plan 'Start Point 3 Días' (≈ 13 días por mes). | H27: mercado
A28: precio_p4 | B28: Precio plan 4 | C28: ARS/mes | D28: 111200 | E28: 111200 | F28: 111200 | G28: DERIVADO, no publicado: Ambrela no vende ilimitado flex. Precio 3 días/sem (103.000) × proporción FLEX/12D de HUERTA (270.000/250.000); queda bajo el puesto fijo de Ambrela (118.000). | H28: mercado
A29: mix_p1 | B29: Peso del plan 1 en los miembros flex | C29: % | D29: 0.1 | E29: 0.1 | F29: 0.1 | G29: SUPUESTO sin dato: en la zona solo Ambrela publica planes (2 y 3 días por semana y puesto fijo). Medir en la preventa. | H29: a validar
A30: mix_p2 | B30: Peso del plan 2 en los miembros flex | C30: % | D30: 0.35 | E30: 0.35 | F30: 0.35 | G30: SUPUESTO sin dato: en la zona solo Ambrela publica planes (2 y 3 días por semana y puesto fijo). Medir en la preventa. | H30: a validar
A31: mix_p3 | B31: Peso del plan 3 en los miembros flex | C31: % | D31: 0.3 | E31: 0.3 | F31: 0.3 | G31: SUPUESTO sin dato: en la zona solo Ambrela publica planes (2 y 3 días por semana y puesto fijo). Medir en la preventa. | H31: a validar
A32: mix_p4 | B32: Peso del plan 4 en los miembros flex | C32: % | D32: 0.25 | E32: 0.25 | F32: 0.25 | G32: SUPUESTO sin dato: en la zona solo Ambrela publica planes (2 y 3 días por semana y puesto fijo). Medir en la preventa. | H32: a validar
... A43: ramp_of | B43: Meses hasta ocupar las oficinas privadas | C43: meses | D43: 10 | E43: 6 | F43: 4 | G43: Supuesto. | H43: a validar
A44: ALTAS Y BAJAS DE MIEMBROS FLEX
A45: miembros_ini | B45: Miembros al abrir (preventa / lista de espera) | C45: miembros | D45: 0 | E45: 5 | F45: 10 | G45: Depende de la preventa (ver plan de validación). | H45: a validar
A46: altas_f1 | B46: Altas por mes, meses 1 a 6 | C46: miembros/mes | D46: 2 | E46: 3 | F46: 5 | G46: SUPUESTO sin dato de demanda: ningún archivo del repo mide cuántos profesionales de la zona usarían un coworking (entorno_y_normativa.md, 4). Medir con preventa y lista de espera. | H46: a validar
A47: altas_f2 | B47: Altas por mes, meses 7 a 12 | C47: miembros/mes | D47: 2 | E47: 3 | F47: 4 | G47: SUPUESTO sin dato de demanda: ningún archivo del repo mide cuántos profesionales de la zona usarían un coworking (entorno_y_normativa.md, 4). Medir con preventa y lista de espera. | H47: a validar
A48: altas_f3 | B48: Altas por mes, meses 13 a 36 | C48: miembros/mes | D48: 1 | E48: 2 | F48: 3 | G48: SUPUESTO sin dato de demanda: ningún archivo del repo mide cuántos profesionales de la zona usarían un coworking (entorno_y_normativa.md, 4). Medir con preventa y lista de espera. | H48: a validar
A49: churn | B49: Bajas mensuales de miembros flex | C49: % | D49: 0.08 | E49: 0.06 | F49: 0.05 | G49: SUPUESTO sin dato local. | H49: a validar
A50: altas_fijo | B50: Altas de puestos fijos por mes | C50: puestos/mes | D50: 0.5 | E50: 1 | F50: 1.5 | G50: Supuesto. | H50: a validar
A51: churn_fijo | B51: Bajas mensuales de puestos fijos | C51: % | D51: 0.05 | E51: 0.04 | F51: 0.03 | G51: Supuesto (los fijos rotan menos). | H51: a validar
A52: COSTOS VARIABLES
A53: costo_puesto_dia_usd | B53: Café, té, agua y consumibles por puesto-día | C53: USD | D53: 1.22 | E53: 0.81 | F53: 0.41 | G53: Solo café: kg tostado ARS 63.540 (costos_referencia #53) × 10 g por taza × 3 / 2 / 1 tazas por día (el gramaje y las tazas son SUPUESTOS). Té, azúcar, agua y papel: SIN DATO. | H53: estimación
A54: comision_pct | B54: Comisión de cobro (tarjeta / billetera) | C54: % de lo cobrado | D54: 0.0629 | E54: 0.0345 | F54: 0.006 | G54: Mercado Pago: tarjeta de crédito con acreditación inmediata hasta 6,29 %; QR con saldo o débito 0,6 % (costos_referencia #17-18, fuente secundaria, + IVA). Base = mitad y mitad (SUPUESTO). | H54: dato
A55: iibb_pct | B55: Ingresos Brutos CABA | C55: % de ventas sin IVA | D55: 0.05 | E55: 0.03 | F55: 0.03 | G55: 3 % servicios inmobiliarios y de alquiler (costos_referencia #15); 5 % si encuadra como locación de inmuebles comerciales (#16). El encuadre del coworking NO está confirmado. | H55: dato
A56: idc_pct | B56: Impuesto a los débitos y créditos bancarios (aprox.) | C56: % de lo cobrado | D56: 0.012 | E56: 0.012 | F56: 0.012 | G56: Ley 25.413: 0,6 % sobre créditos + 0,6 % sobre débitos; aproximado sobre lo cobrado. | H56: dato
A57: COSTOS FIJOS (USD por mes)
A58: personal_fte | B58: Personal de recepción y comunidad (jornadas completas) | C58: personas | D58: 1.5 | E58: 1.5 | F58: 1.5 | G58: Lunes a viernes 8 a 20 h: una jornada completa + media. | H58: supuesto
A59: costo_fte_usd | B59: Costo laboral por persona (sueldo + cargas) | C59: USD/mes | D59: 1159.6 | E59: 1104.8 | F59: 1049.9 | G59: Comercio CCT 130/75 Administrativo A, ARS 1.316.632 con suma fija (costos_referencia #6) × cargas 37,4 % / 30,9 % / 24,4 % (#54, calculadora de un marketplace, no norma). Verificar el acuerdo. | H59: dato
A60: limpieza_usd | B60: Limpieza | C60: USD/mes | D60: 673.1 | E60: 376.9 | F60: 269.2 | G60: Conservador: jornada mediana ARS 50.000 × 21 días (costos_referencia #56). Base y favorable: ARS 7.000 / 5.000 por hora (rango 5.000 a 9.000, #57, sin verificar) × 4 h por día (SUPUESTO) × 21 días. | H60: estimación
A61: internet_usd | B61: Internet principal + respaldo | C61: USD/mes | D61: 115.4 | E61: 55.8 | F61: 43 | G61: Fibra Movistar combo ARS 22.018 + respaldo Starlink: Priority 500 GB ARS 158.000 / Residencial Estándar 65.000 / Lite 45.000 (costos_referencia #67, #34-35). Son planes residenciales o de combo: la fibra empresarial simétrica requiere cotización (#66). | H61: dato
A62: servicios_usd | B62: Electricidad, gas y agua | C62: USD/mes | D62: 27.1 | E62: 27.1 | F62: 27.1 | G62: SIN DATO de consumo. Solo los cargos fijos mensuales: Edenor T1 ARS 18.268 + Metrogas P1-P2 ARS 24.017 (costos_referencia #76, #31); agua AySA no disponible (#83). Falta la factura real de la casa. | H62: SIN DATO
A63: seguros_usd | B63: Seguros (integral y responsabilidad civil) | C63: USD/mes | D63: 192.3 | E63: 112.2 | F63: 32.1 | G63: Comparador comercial, no cotización: oficina y servicios profesionales ARS 50.000 a 300.000 por mes (costos_referencia #62, mayo 2026, valores inconsistentes). Base = punto medio. Un coworking con terceros necesita RC. | H63: estimación
A64: software_usd | B64: Software de gestión y reservas | C64: USD/mes | D64: 177 | E64: 129 | F64: 99 | G64: Spacebring Business USD 177; OfficeRnD Essentials USD 129 mensual / 99 anual (costos_referencia #19-20). | H64: dato
A65: admin_usd | B65: Contador y administración | C65: USD/mes | D65: 0 | E65: 0 | F65: 0 | G65: SIN DATO: ningún archivo tiene honorarios de contador para un Responsable Inscripto. Cargado en 0. | H65: SIN DATO
A66: mant_pct_anual | B66: Mantenimiento y reposición (anual, sobre la inversión) | C66: % | D66: 0.05 | E66: 0.04 | F66: 0.04 | G66: Supuesto. | H66: supuesto
A67: marketing_usd | B67: Publicidad digital | C67: USD/mes | D67: 500 | E67: 400 | F67: 400 | G67: SUPUESTO de diseño. Referencia: CPC mediano Meta Ads en Argentina USD 0,63 (julio 2026, costos_referencia #63) → USD 400 a 500 por mes ≈ 640 a 800 clics. | H67: supuesto
A68: comunidad_usd | B68: Actividades de comunidad (desayunos, charlas) | C68: USD/mes | D68: 150 | E68: 150 | F68: 150 | G68: Un desayuno de miembros y una charla por mes; supuesto. | H68: supuesto
A69: otros_pct | B69: Otros e imprevistos (sobre los fijos) | C69: % | D69: 0.08 | E69: 0.05 | F69: 0.05 | G69: Supuesto. | H69: supuesto
A70: INVERSIÓN INICIAL (USD)
A71: m2_obra | B71: m² a intervenir (sin el patio) | C71: m² | D71: 390 | E71: 390 | F71: 390 | G71: 450 m² totales menos el patio estimado; sin plano. | H71: a validar
A72: usd_m2_obra | B72: Adecuación por m² (pintura, pisos, iluminación, baños, terminaciones) | C72: USD/m² | D72: 406.4 | E72: 304.8 | F72: 203.2 | G72: ANCLADO en el costo de construir nuevo en CABA, ARS 1.584.840 por m² (julio 2026, costos_referencia #0). El 40 % / 30 % / 20 % para una refacción de casa usada es SUPUESTO mío: validar con presupuesto de arquitecto. | H72: estimación
A73: m2_patio | B73: m² de patio a techar | C73: m² | D73: 60 | E73: 60 | F73: 60 | G73: Sin plano: supuesto a medir. | H73: a validar
A74: usd_m2_patio | B74: Techado de patio por m² | C74: USD/m² | D74: 64.1 | E74: 47.4 | F74: 30.8 | G74: Techado con policarbonato, material y mano de obra, ARS 48.000 a 100.000 por m² (costos_referencia #36). Sin estructura nueva, piso ni instalaciones. Techar puede estar prohibido (entorno_y_normativa.md, 1.3). | H74: estimación
A75: pileta_usd | B75: Anulación / relleno de pileta | C75: USD | D75: 0 | E75: 0 | F75: 0 | G75: SIN DATO: costos_referencia #44 'no disponible'. Cargado en 0. | H75: SIN DATO
A76: bano_acc_usd | B76: Baño accesible | C76: USD | D76: 5769.2 | E76: 4487.2 | F76: 3205.1 | G76: PROXY: reforma de baño 'media', ARS 5.000.000 a 9.000.000 (costos_referencia #80). No hay precio de baño accesible; el rango es de otro tipo de obra. | H76: estimación
A77: electrica_datos_usd | B77: Instalación eléctrica y red de datos | C77: USD | D77: 7219.2 | E77: 5437.2 | F77: 3655.1 | G77: Solo mano de obra: tablero ARS 333.000 a 602.000 + puesta a tierra 169.000 a 260.000 + 100 bocas a 52.000 a 104.000 (costos_referencia #37-38). Las 100 bocas son SUPUESTO (2 por puesto + áreas comunes). Materiales y cableado: SIN DATO. | H77: estimación
A78: clima_n | B78: Equipos de aire acondicionado | C78: equipos | D78: 8 | E78: 8 | F78: 8 | G78: Supuesto: un equipo cada 40–50 m² cubiertos. | H78: supuesto
A79: clima_usd | B79: Aire acondicionado instalado (por equipo) | C79: USD | D79: 1292.8 | E79: 981.9 | F79: 906.8 | G79: Split inverter frío/calor de 4.300 a 5.590 frigorías, solo el equipo: ARS 1.414.550 / 1.531.827 / 2.016.845 (costos_referencia #27). Instalación: SIN DATO. | H79: dato
A80: mueble_puesto_usd | B80: Escritorio + silla ergonómica por puesto | C80: USD | D80: 384.6 | E80: 173.1 | F80: 142 | G80: Puesto: silla (70.000 económica / 340.000 media-alta) + escritorio (151.499 a 259.919) (costos_referencia #23-25). Común: lockers de 12 puertas, sillones de 3 cuerpos y Smart TV (#50, #51, #48); las cantidades son SUPUESTO. Mesa de reuniones y sillas de sala: SIN DATO (#75). | H80: dato
A81: mueble_comun_usd | B81: Mobiliario común (salas, living, lockers) | C81: USD | D81: 3982.6 | E81: 2876.5 | F81: 1434.3 | G81: Puesto: silla (70.000 económica / 340.000 media-alta) + escritorio (151.499 a 259.919) (costos_referencia #23-25). Común: lockers de 12 puertas, sillones de 3 cuerpos y Smart TV (#50, #51, #48); las cantidades son SUPUESTO. Mesa de reuniones y sillas de sala: SIN DATO (#75). | H81: estimación
A82: cabinas_n | B82: Cabinas para llamadas | C82: cabinas | D82: 2 | E82: 3 | F82: 3 | G82: Supuesto. | H82: supuesto
... A89: contingencia_pct | B89: Contingencias | C89: % | D89: 0.15 | E89: 0.12 | F89: 0.1 | G89: Práctica habitual en refacciones de casas usadas; supuesto. | H89: supuesto
A90: COSTO DE OPORTUNIDAD Y FINANZAS
A91: alquiler_casa_usd | B91: Alquiler de mercado de la casa que se deja de cobrar | C91: USD/mes | D91: 0 | E91: 0 | F91: 0 | G91: SIN DATO: datos/casa_costo_oportunidad.json está pendiente (0 avisos). Cargado en 0; el Resumen muestra cuánto resultado operativo queda para pagar ese alquiler. | H91: SIN DATO
A92: tasa_desc_anual | B92: Tasa de descuento anual en USD (la define el inversor) | C92: % | D92: 0.12 | E92: 0.12 | F92: 0.12 | G92: Supuesto ilustrativo: el inversor tiene que poner su propia tasa. | H92: a definir
A93: valor_residual_usd | B93: Valor residual al mes 36 (negocio y equipamiento) | C93: USD | D93: 0 | E93: 0 | F93: 0 | G93: Se deja en 0 para no inflar el retorno. | H93: supuesto

Sheet Inversion
A1: Inversión inicial (USD, mes 0)
A2: Se calcula desde Supuestos. El capital de trabajo no se suma acá: es la necesidad máxima de caja de cada escenario (ver Resumen).
A4: Rubro | B4: Cómo se calcula | D4: Conservador | E4: Base | F4: Favorable
A5: Obra de adecuación general | B5: m² intervenidos × USD/m² | D5: =Supuestos!$D$71*Supuestos!$D$72 -> 158496 | E5: =Supuestos!$E$71*Supuestos!$E$72 -> 118872 | F5: =Supuestos!$F$71*Supuestos!$F$72 -> 79248
A6: Techado del patio | B6: m² de patio × USD/m² | D6: =Supuestos!$D$73*Supuestos!$D$74 -> 3846 | E6: =Supuestos!$E$73*Supuestos!$E$74 -> 2844 | F6: =Supuestos!$F$73*Supuestos!$F$74 -> 1848
A7: Anulación / relleno de pileta | B7: suma fija | D7: =Supuestos!$D$75 -> 0 | E7: =Supuestos!$E$75 -> 0 | F7: =Supuestos!$F$75 -> 0
A8: Baño accesible | B8: suma fija | D8: =Supuestos!$D$76 -> 5769.2 | E8: =Supuestos!$E$76 -> 4487.2 | F8: =Supuestos!$F$76 -> 3205.1
A9: Instalación eléctrica y red de datos | B9: suma fija | D9: =Supuestos!$D$77 -> 7219.2 | E9: =Supuestos!$E$77 -> 5437.2 | F9: =Supuestos!$F$77 -> 3655.1
A10: Climatización | B10: equipos × USD por equipo instalado | D10: =Supuestos!$D$78*Supuestos!$D$79 -> 10342.4 | E10: =Supuestos!$E$78*Supuestos!$E$79 -> 7855.2 | F10: =Supuestos!$F$78*Supuestos!$F$79 -> 7254.4
A11: Mobiliario de puestos | B11: (puestos flex + fijos + oficinas) × USD por puesto | D11: =(Supuestos!$D$12+Supuestos!$D$13+Supuestos!$D$14*Supuestos!$D$15)*Supuestos!$D$80 -> 15384 | E11: =(Supuestos!$E$12+Supuestos!$E$13+Supuestos!$E$14*Supuestos!$E$15)*Supuestos!$E$80 -> 8308.8 | F11: =(Supuestos!$F$12+Supuestos!$F$13+Supuestos!$F$14*Supuestos!$F$15)*Supuestos!$F$80 -> 8378
A12: Mobiliario común (salas, living, lockers) | B12: suma fija | D12: =Supuestos!$D$81 -> 3982.6 | E12: =Supuestos!$E$81 -> 2876.5 | F12: =Supuestos!$F$81 -> 1434.3
A13: Cabinas para llamadas | B13: cabinas × USD | D13: =Supuestos!$D$82*Supuestos!$D$83 -> 0 | E13: =Supuestos!$E$82*Supuestos!$E$83 -> 0 | F13: =Supuestos!$F$82*Supuestos!$F$83 -> 0
A14: Café y cocina (equipamiento) | B14: suma fija | D14: =Supuestos!$D$84 -> 3509.3 | E14: =Supuestos!$E$84 -> 2145.7 | F14: =Supuestos!$F$84 -> 2120.7
A15: Conectividad, control de acceso y cámaras | B15: suma fija | D15: =Supuestos!$D$85 -> 2735.4 | E15: =Supuestos!$E$85 -> 1701.5 | F15: =Supuestos!$F$85 -> 1166.9
A16: Subtotal obra y equipamiento | D16: =SUM(D5:D15) -> 211284.1 | E16: =SUM(E5:E15) -> 154528.1 | F16: =SUM(F5:F15) -> 108310.5
A17: Honorarios profesionales (proyecto, dirección, planos) | B17: % sobre obra (filas de obra e instalaciones) | D17: =SUM(D5:D9)*Supuestos!$D$86 -> 24546.256 | E17: =SUM(E5:E9)*Supuestos!$E$86 -> 18429.656 | F17: =SUM(F5:F9)*Supuestos!$F$86 -> 12313.868
A18: Habilitación, planos de uso, incendio y trámites | B18: suma fija | D18: =Supuestos!$D$87 -> 1987.2 | E18: =Supuestos!$E$87 -> 1403.8 | F18: =Supuestos!$F$87 -> 726
A19: Marketing de apertura y preventa | B19: suma fija | D19: =Supuestos!$D$88 -> 2000 | E19: =Supuestos!$E$88 -> 2000 | F19: =Supuestos!$F$88 -> 2000
A20: Contingencias | B20: % sobre todo lo anterior | D20: =SUM(D16:D19)*Supuestos!$D$89 -> 35972.633 | E20: =SUM(E16:E19)*Supuestos!$E$89 -> 21163.387 | F20: =SUM(F16:F19)*Supuestos!$F$89 -> 12335.037
A21: INVERSIÓN INICIAL TOTAL (sin capital de trabajo) | D21: =SUM(D16:D20) -> 275790.19 | E21: =SUM(E16:E20) -> 197524.94 | F21: =SUM(F16:F20) -> 135685.4

Sheet Equilibrio
A1: Punto de equilibrio en régimen (mes tipo, con los supuestos de cada escenario)
A2: ¿Cuántos miembros flex hacen falta para cubrir los costos fijos, con los puestos fijos, oficinas y extras del mes 36? Comparado con el tope de puestos.
A4: Concepto | B4: Conservador | C4: Base | D4: Favorable | E4: Fórmula
A5: Precio neto promedio por miembro flex (USD/mes, sin IVA) | B5: =((Supuestos!$D$29*Supuestos!$D$25+Supuestos!$D$30*Supuestos!$D$26+Supuestos!$D$31*Supuestos!$D$27+Supuestos!$D$32*Supuestos!$D$28)*Supuestos!$D$37*(1-Supuestos!$D$38)/(1+Supuestos!$D$7*Supuestos!$D$8)/Supuestos!$D$6) -> 40.911952 | C5: =((Supuestos!$E$29*Supuestos!$E$25+Supuestos!$E$30*Supuestos!$E$26+Supuestos!$E$31*Supuestos!$E$27+Supuestos!$E$32*Supuestos!$E$28)*Supuestos!$E$37*(1-Supuestos!$E$38)/(1+Supuestos!$E$7*Supuestos!$E$8)/Supuestos!$E$6) -> 46.972982 | D5: =((Supuestos!$F$29*Supuestos!$F$25+Supuestos!$F$30*Supuestos!$F$26+Supuestos!$F$31*Supuestos!$F$27+Supuestos!$F$32*Supuestos!$F$28)*Supuestos!$F$37*(1-Supuestos!$F$38)/(1+Supuestos!$F$7*Supuestos!$F$8)/Supuestos!$F$6) -> 50.382311 | E5: mezcla de planes × precio × (1 − descuento) / IVA / TC
A6: Días promedio incluidos por miembro flex | B6: =(Supuestos!$D$29*Supuestos!$D$21+Supuestos!$D$30*Supuestos!$D$22+Supuestos!$D$31*Supuestos!$D$23+Supuestos!$D$32*Supuestos!$D$24) -> 12.05 | C6: =(Supuestos!$E$29*Supuestos!$E$21+Supuestos!$E$30*Supuestos!$E$22+Supuestos!$E$31*Supuestos!$E$23+Supuestos!$E$32*Supuestos!$E$24) -> 12.05 | D6: =(Supuestos!$F$29*Supuestos!$F$21+Supuestos!$F$30*Supuestos!$F$22+Supuestos!$F$31*Supuestos!$F$23+Supuestos!$F$32*Supuestos!$F$24) -> 12.05 | E6: mezcla × días de cada plan
A7: Costo variable por miembro flex (USD/mes) | B7: =(Supuestos!$D$29*Supuestos!$D$21+Supuestos!$D$30*Supuestos!$D$22+Supuestos!$D$31*Supuestos!$D$23+Supuestos!$D$32*Supuestos!$D$24)*Supuestos!$D$17*Supuestos!$D$53+((Supuestos!$D$29*Supuestos!$D$25+Supuestos!$D$30*Supuestos!$D$26+Supuestos!$D$31*Supuestos!$D$27+Supuestos!$D$32*Supuestos!$D$28)*Supuestos!$D$37*(1-Supuestos!$D$38)/(1+Supuestos!$D$7*Supuestos!$D$8)/Supuestos!$D$6)*((1+Supuestos!$D$7*Supuestos!$D$8)*(Supuestos!$D$54+Supuestos!$D$56)+Supuestos!$D$55) -> 18.249257 | C7: =(Supuestos!$E$29*Supuestos!$E$21+Supuestos!$E$30*Supuestos!$E$22+Supuestos!$E$31*Supuestos!$E$23+Supuestos!$E$32*Supuestos!$E$24)*Supuestos!$E$17*Supuestos!$E$53+((Supuestos!$E$29*Supuestos!$E$25+Supuestos!$E$30*Supuestos!$E$26+Supuestos!$E$31*Supuestos!$E$27+Supuestos!$E$32*Supuestos!$E$28)*Supuestos!$E$37*(1-Supuestos!$E$38)/(1+Supuestos!$E$7*Supuestos!$E$8)/Supuestos!$E$6)*((1+Supuestos!$E$7*Supuestos!$E$8)*(Supuestos!$E$54+Supuestos!$E$56)+Supuestos!$E$55) -> 11.860524 | D7: =(Supuestos!$F$29*Supuestos!$F$21+Supuestos!$F$30*Supuestos!$F$22+Supuestos!$F$31*Supuestos!$F$23+Supuestos!$F$32*Supuestos!$F$24)*Supuestos!$F$17*Supuestos!$F$53+((Supuestos!$F$29*Supuestos!$F$25+Supuestos!$F$30*Supuestos!$F$26+Supuestos!$F$31*Supuestos!$F$27+Supuestos!$F$32*Supuestos!$F$28)*Supuestos!$F$37*(1-Supuestos!$F$38)/(1+Supuestos!$F$7*Supuestos!$F$8)/Supuestos!$F$6)*((1+Supuestos!$F$7*Supuestos!$F$8)*(Supuestos!$F$54+Supuestos!$F$56)+Supuestos!$F$55) -> 6.3141711 | E7: consumo + comisiones + impuestos sobre ventas
A8: Contribución por miembro flex (USD/mes) | B8: =B5-B7 -> 22.662695 | C8: =C5-C7 -> 35.112457 | D8: =D5-D7 -> 44.06814 | E8: precio neto − costo variable
A9: Costos fijos del mes 36 | B9: =Modelo_Conservador!AM40 -> 5101.2999 | C9: =Modelo_Base!AM40 -> 3744.9473 | D9: =Modelo_Favorable!AM40 -> 3199.9114
A10: Contribución de fijos, oficinas y extras del mes 36 | B10: =Modelo_Conservador!AM28-Modelo_Conservador!AM7*B8 -> 464.25565 | C10: =Modelo_Base!AM28-Modelo_Base!AM7*C8 -> 1008.6114 | D10: =Modelo_Favorable!AM28-Modelo_Favorable!AM7*D8 -> 1813.6545 | E10: margen de contribución total − el de los miembros flex
A11: MIEMBROS FLEX NECESARIOS PARA EL EQUILIBRIO | B11: =MAX(0,(B9-B10)/B8) -> 204.61133 | C11: =MAX(0,(C9-C10)/C8) -> 77.930628 | D11: =MAX(0,(D9-D10)/D8) -> 31.457124 | E11: (fijos − otras contribuciones) / contribución por miembro
A12: Tope de miembros flex (puestos en el pico) | B12: =Modelo_Conservador!AM5 -> 45.561793 | C12: =Modelo_Base!AM5 -> 60.325567 | D12: =Modelo_Favorable!AM5 -> 78.074689
A13: Equilibrio como % del tope | B13: =B11/B12 -> 4.4908534 | C13: =C11/C12 -> 1.2918342 | D13: =D11/D12 -> 0.40291065 | E13: más de 80 %: el negocio depende de estar casi lleno

Sheet Sensibilidad
A1: Sensibilidad del resultado operativo mensual en régimen · escenario Base
A2: Miembros flex = % del tope de puestos. Precio = variación sobre los precios de Supuestos. Fijos, oficinas y extras como en el mes 36 del escenario Base. USD por mes, antes de Ganancias.
A4: Miembros flex (% del tope) ↓ / Precio → | B4: -0.2 | C4: -0.1 | D4: 0 | E4: 0.1 | F4: 0.2
A5: 0.4 | B5: =$A5*Equilibrio!C12*(Equilibrio!C5*(1+B$4)*(1-((1+Supuestos!$E$7*Supuestos!$E$8)*(Supuestos!$E$54+Supuestos!$E$56)+Supuestos!$E$55))-(Equilibrio!C7-Equilibrio!C5*((1+Supuestos!$E$7*Supuestos!$E$8)*(Supuestos!$E$54+Supuestos!$E$56)+Supuestos!$E$55)))+Equilibrio!C10*(1+B$4)-Equilibrio!C9 -> -2297.9246 | C5: =$A5*Equilibrio!C12*(Equilibrio!C5*(1+C$4)*(1-((1+Supuestos!$E$7*Supuestos!$E$8)*(Supuestos!$E$54+Supuestos!$E$56)+Supuestos!$E$55))-(Equilibrio!C7-Equilibrio!C5*((1+Supuestos!$E$7*Supuestos!$E$8)*(Supuestos!$E$54+Supuestos!$E$56)+Supuestos!$E$55)))+Equilibrio!C10*(1+C$4)-Equilibrio!C9 -> -2093.4945 | D5: =$A5*Equilibrio!C12*(Equilibrio!C5*(1+D$4)*(1-((1+Supuestos!$E$7*Supuestos!$E$8)*(Supuestos!$E$54+Supuestos!$E$56)+Supuestos!$E$55))-(Equilibrio!C7-Equilibrio!C5*((1+Supuestos!$E$7*Supuestos!$E$8)*(Supuestos!$E$54+Supuestos!$E$56)+Supuestos!$E$55)))+Equilibrio!C10*(1+D$4)-Equilibrio!C9 -> -1889.0643 | E5: =$A5*Equilibrio!C12*(Equilibrio!C5*(1+E$4)*(1-((1+Supuestos!$E$7*Supuestos!$E$8)*(Supuestos!$E$54+Supuestos!$E$56)+Supuestos!$E$55))-(Equilibrio!C7-Equilibrio!C5*((1+Supuestos!$E$7*Supuestos!$E$8)*(Supuestos!$E$54+Supuestos!$E$56)+Supuestos!$E$55)))+Equilibrio!C10*(1+E$4)-Equilibrio!C9 -> -1684.6342 | F5: =$A5*Equilibrio!C12*(Equilibrio!C5*(1+F$4)*(1-((1+Supuestos!$E$7*Supuestos!$E$8)*(Supuestos!$E$54+Supuestos!$E$56)+Supuestos!$E$55))-(Equilibrio!C7-Equilibrio!C5*((1+Supuestos!$E$7*Supuestos!$E$8)*(Supuestos!$E$54+Supuestos!$E$56)+Supuestos!$E$55)))+Equilibrio!C10*(1+F$4)-Equilibrio!C9 -> -1480.204
A6: 0.5 | B6: =$A6*Equilibrio!C12*(Equilibrio!C5*(1+B$4)*(1-((1+Supuestos!$E$7*Supuestos!$E$8)*(Supuestos!$E$54+Supuestos!$E$56)+Supuestos!$E$55))-(Equilibrio!C7-Equilibrio!C5*((1+Supuestos!$E$7*Supuestos!$E$8)*(Supuestos!$E$54+Supuestos!$E$56)+Supuestos!$E$55)))+Equilibrio!C10*(1+B$4)-Equilibrio!C9 -> -2137.8912 | C6: =$A6*Equilibrio!C12*(Equilibrio!C5*(1+C$4)*(1-((1+Supuestos!$E$7*Supuestos!$E$8)*(Supuestos!$E$54+Supuestos!$E$56)+Supuestos!$E$55))-(Equilibrio!C7-Equilibrio!C5*((1+Supuestos!$E$7*Supuestos!$E$8)*(Supuestos!$E$54+Supuestos!$E$56)+Supuestos!$E$55)))+Equilibrio!C10*(1+C$4)-Equilibrio!C9 -> -1907.5688 | D6: =$A6*Equilibrio!C12*(Equilibrio!C5*(1+D$4)*(1-((1+Supuestos!$E$7*Supuestos!$E$8)*(Supuestos!$E$54+Supuestos!$E$56)+Supuestos!$E$55))-(Equilibrio!C7-Equilibrio!C5*((1+Supuestos!$E$7*Supuestos!$E$8)*(Supuestos!$E$54+Supuestos!$E$56)+Supuestos!$E$55)))+Equilibrio!C10*(1+D$4)-Equilibrio!C9 -> -1677.2464 | E6: =$A6*Equilibrio!C12*(Equilibrio!C5*(1+E$4)*(1-((1+Supuestos!$E$7*Supuestos!$E$8)*(Supuestos!$E$54+Supuestos!$E$56)+Supuestos!$E$55))-(Equilibrio!C7-Equilibrio!C5*((1+Supuestos!$E$7*Supuestos!$E$8)*(Supuestos!$E$54+Supuestos!$E$56)+Supuestos!$E$55)))+Equilibrio!C10*(1+E$4)-Equilibrio!C9 -> -1446.924 | F6: =$A6*Equilibrio!C12*(Equilibrio!C5*(1+F$4)*(1-((1+Supuestos!$E$7*Supuestos!$E$8)*(Supuestos!$E$54+Supuestos!$E$56)+Supuestos!$E$55))-(Equilibrio!C7-Equilibrio!C5*((1+Supuestos!$E$7*Supuestos!$E$8)*(Supuestos!$E$54+Supuestos!$E$56)+Supuestos!$E$55)))+Equilibrio!C10*(1+F$4)-Equilibrio!C9 -> -1216.6016
A7: 0.6 | B7: =$A7*Equilibrio!C12*(Equilibrio!C5*(1+B$4)*(1-((1+Supuestos!$E$7*Supuestos!$E$8)*(Supuestos!$E$54+Supuestos!$E$56)+Supuestos!$E$55))-(Equilibrio!C7-Equilibrio!C5*((1+Supuestos!$E$7*Supuestos!$E$8)*(Supuestos!$E$54+Supuestos!$E$56)+Supuestos!$E$55)))+Equilibrio!C10*(1+B$4)-Equilibrio!C9 -> -1977.8578 | C7: =$A7*Equilibrio!C12*(Equilibrio!C5*(1+C$4)*(1-((1+Supuestos!$E$7*Supuestos!$E$8)*(Supuestos!$E$54+Supuestos!$E$56)+Supuestos!$E$55))-(Equilibrio!C7-Equilibrio!C5*((1+Supuestos!$E$7*Supuestos!$E$8)*(Supuestos!$E$54+Supuestos!$E$56)+Supuestos!$E$55)))+Equilibrio!C10*(1+C$4)-Equilibrio!C9 -> -1721.6432 | D7: =$A7*Equilibrio!C12*(Equilibrio!C5*(1+D$4)*(1-((1+Supuestos!$E$7*Supuestos!$E$8)*(Supuestos!$E$54+Supuestos!$E$56)+Supuestos!$E$55))-(Equilibrio!C7-Equilibrio!C5*((1+Supuestos!$E$7*Supuestos!$E$8)*(Supuestos!$E$54+Supuestos!$E$56)+Supuestos!$E$55)))+Equilibrio!C10*(1+D$4)-Equilibrio!C9 -> -1465.4285 | E7: =$A7*Equilibrio!C12*(Equilibrio!C5*(1+E$4)*(1-((1+Supuestos!$E$7*Supuestos!$E$8)*(Supuestos!$E$54+Supuestos!$E$56)+Supuestos!$E$55))-(Equilibrio!C7-Equilibrio!C5*((1+Supuestos!$E$7*Supuestos!$E$8)*(Supuestos!$E$54+Supuestos!$E$56)+Supuestos!$E$55)))+Equilibrio!C10*(1+E$4)-Equilibrio!C9 -> -1209.2139 | F7: =$A7*Equilibrio!C12*(Equilibrio!C5*(1+F$4)*(1-((1+Supuestos!$E$7*Supuestos!$E$8)*(Supuestos!$E$54+Supuestos!$E$56)+Supuestos!$E$55))-(Equilibrio!C7-Equilibrio!C5*((1+Supuestos!$E$7*Supuestos!$E$8)*(Supuestos!$E$54+Supuestos!$E$56)+Supuestos!$E$55)))+Equilibrio!C10*(1+F$4)-Equilibrio!C9 -> -952.99925
A8: 0.7 | B8: =$A8*Equilibrio!C12*(Equilibrio!C5*(1+B$4)*(1-((1+Supuestos!$E$7*Supuestos!$E$8)*(Supuestos!$E$54+Supuestos!$E$56)+Supuestos!$E$55))-(Equilibrio!C7-Equilibrio!C5*((1+Supuestos!$E$7*Supuestos!$E$8)*(Supuestos!$E$54+Supuestos!$E$56)+Supuestos!$E$55)))+Equilibrio!C10*(1+B$4)-Equilibrio!C9 -> -1817.8244 | C8: =$A8*Equilibrio!C12*(Equilibrio!C5*(1+C$4)*(1-((1+Supuestos!$E$7*Supuestos!$E$8)*(Supuestos!$E$54+Supuestos!$E$56)+Supuestos!$E$55))-(Equilibrio!C7-Equilibrio!C5*((1+Supuestos!$E$7*Supuestos!$E$8)*(Supuestos!$E$54+Supuestos!$E$56)+Supuestos!$E$55)))+Equilibrio!C10*(1+C$4)-Equilibrio!C9 -> -1535.7175 | D8: =$A8*Equilibrio!C12*(Equilibrio!C5*(1+D$4)*(1-((1+Supuestos!$E$7*Supuestos!$E$8)*(Supuestos!$E$54+Supuestos!$E$56)+Supuestos!$E$55))-(Equilibrio!C7-Equilibrio!C5*((1+Supuestos!$E$7*Supuestos!$E$8)*(Supuestos!$E$54+Supuestos!$E$56)+Supuestos!$E$55)))+Equilibrio!C10*(1+D$4)-Equilibrio!C9 -> -1253.6106 | E8: =$A8*Equilibrio!C12*(Equilibrio!C5*(1+E$4)*(1-((1+Supuestos!$E$7*Supuestos!$E$8)*(Supuestos!$E$54+Supuestos!$E$56)+Supuestos!$E$55))-(Equilibrio!C7-Equilibrio!C5*((1+Supuestos!$E$7*Supuestos!$E$8)*(Supuestos!$E$54+Supuestos!$E$56)+Supuestos!$E$55)))+Equilibrio!C10*(1+E$4)-Equilibrio!C9 -> -971.50375 | F8: =$A8*Equilibrio!C12*(Equilibrio!C5*(1+F$4)*(1-((1+Supuestos!$E$7*Supuestos!$E$8)*(Supuestos!$E$54+Supuestos!$E$56)+Supuestos!$E$55))-(Equilibrio!C7-Equilibrio!C5*((1+Supuestos!$E$7*Supuestos!$E$8)*(Supuestos!$E$54+Supuestos!$E$56)+Supuestos!$E$55)))+Equilibrio!C10*(1+F$4)-Equilibrio!C9 -> -689.39686
A9: 0.8 | B9: =$A9*Equilibrio!C12*(Equilibrio!C5*(1+B$4)*(1-((1+Supuestos!$E$7*Supuestos!$E$8)*(Supuestos!$E$54+Supuestos!$E$56)+Supuestos!$E$55))-(Equilibrio!C7-Equilibrio!C5*((1+Supuestos!$E$7*Supuestos!$E$8)*(Supuestos!$E$54+Supuestos!$E$56)+Supuestos!$E$55)))+Equilibrio!C10*(1+B$4)-Equilibrio!C9 -> -1657.7911 | C9: =$A9*Equilibrio!C12*(Equilibrio!C5*(1+C$4)*(1-((1+Supuestos!$E$7*Supuestos!$E$8)*(Supuestos!$E$54+Supuestos!$E$56)+Supuestos!$E$55))-(Equilibrio!C7-Equilibrio!C5*((1+Supuestos!$E$7*Supuestos!$E$8)*(Supuestos!$E$54+Supuestos!$E$56)+Supuestos!$E$55)))+Equilibrio!C10*(1+C$4)-Equilibrio!C9 -> -1349.7919 | D9: =$A9*Equilibrio!C12*(Equilibrio!C5*(1+D$4)*(1-((1+Supuestos!$E$7*Supuestos!$E$8)*(Supuestos!$E$54+Supuestos!$E$56)+Supuestos!$E$55))-(Equilibrio!C7-Equilibrio!C5*((1+Supuestos!$E$7*Supuestos!$E$8)*(Supuestos!$E$54+Supuestos!$E$56)+Supuestos!$E$55)))+Equilibrio!C10*(1+D$4)-Equilibrio!C9 -> -1041.7928 | E9: =$A9*Equilibrio!C12*(Equilibrio!C5*(1+E$4)*(1-((1+Supuestos!$E$7*Supuestos!$E$8)*(Supuestos!$E$54+Supuestos!$E$56)+Supuestos!$E$55))-(Equilibrio!C7-Equilibrio!C5*((1+Supuestos!$E$7*Supuestos!$E$8)*(Supuestos!$E$54+Supuestos!$E$56)+Supuestos!$E$55)))+Equilibrio!C10*(1+E$4)-Equilibrio!C9 -> -733.79362 | F9: =$A9*Equilibrio!C12*(Equilibrio!C5*(1+F$4)*(1-((1+Supuestos!$E$7*Supuestos!$E$8)*(Supuestos!$E$54+Supuestos!$E$56)+Supuestos!$E$55))-(Equilibrio!C7-Equilibrio!C5*((1+Supuestos!$E$7*Supuestos!$E$8)*(Supuestos!$E$54+Supuestos!$E$56)+Supuestos!$E$55)))+Equilibrio!C10*(1+F$4)-Equilibrio!C9 -> -425.79447
A10: 0.9 | B10: =$A10*Equilibrio!C12*(Equilibrio!C5*(1+B$4)*(1-((1+Supuestos!$E$7*Supuestos!$E$8)*(Supuestos!$E$54+Supuestos!$E$56)+Supuestos!$E$55))-(Equilibrio!C7-Equilibrio!C5*((1+Supuestos!$E$7*Supuestos!$E$8)*(Supuestos!$E$54+Supuestos!$E$56)+Supuestos!$E$55)))+Equilibrio!C10*(1+B$4)-Equilibrio!C9 -> -1497.7577 | C10: =$A10*Equilibrio!C12*(Equilibrio!C5*(1+C$4)*(1-((1+Supuestos!$E$7*Supuestos!$E$8)*(Supuestos!$E$54+Supuestos!$E$56)+Supuestos!$E$55))-(Equilibrio!C7-Equilibrio!C5*((1+Supuestos!$E$7*Supuestos!$E$8)*(Supuestos!$E$54+Supuestos!$E$56)+Supuestos!$E$55)))+Equilibrio!C10*(1+C$4)-Equilibrio!C9 -> -1163.8663 | D10: =$A10*Equilibrio!C12*(Equilibrio!C5*(1+D$4)*(1-((1+Supuestos!$E$7*Supuestos!$E$8)*(Supuestos!$E$54+Supuestos!$E$56)+Supuestos!$E$55))-(Equilibrio!C7-Equilibrio!C5*((1+Supuestos!$E$7*Supuestos!$E$8)*(Supuestos!$E$54+Supuestos!$E$56)+Supuestos!$E$55)))+Equilibrio!C10*(1+D$4)-Equilibrio!C9 -> -829.97487 | E10: =$A10*Equilibrio!C12*(Equilibrio!C5*(1+E$4)*(1-((1+Supuestos!$E$7*Supuestos!$E$8)*(Supuestos!$E$54+Supuestos!$E$56)+Supuestos!$E$55))-(Equilibrio!C7-Equilibrio!C5*((1+Supuestos!$E$7*Supuestos!$E$8)*(Supuestos!$E$54+Supuestos!$E$56)+Supuestos!$E$55)))+Equilibrio!C10*(1+E$4)-Equilibrio!C9 -> -496.08348 | F10: =$A10*Equilibrio!C12*(Equilibrio!C5*(1+F$4)*(1-((1+Supuestos!$E$7*Supuestos!$E$8)*(Supuestos!$E$54+Supuestos!$E$56)+Supuestos!$E$55))-(Equilibrio!C7-Equilibrio!C5*((1+Supuestos!$E$7*Supuestos!$E$8)*(Supuestos!$E$54+Supuestos!$E$56)+Supuestos!$E$55)))+Equilibrio!C10*(1+F$4)-Equilibrio!C9 -> -162.19208
A11: 1 | B11: =$A11*Equilibrio!C12*(Equilibrio!C5*(1+B$4)*(1-((1+Supuestos!$E$7*Supuestos!$E$8)*(Supuestos!$E$54+Supuestos!$E$56)+Supuestos!$E$55))-(Equilibrio!C7-Equilibrio!C5*((1+Supuestos!$E$7*Supuestos!$E$8)*(Supuestos!$E$54+Supuestos!$E$56)+Supuestos!$E$55)))+Equilibrio!C10*(1+B$4)-Equilibrio!C9 -> -1337.7243 | C11: =$A11*Equilibrio!C12*(Equilibrio!C5*(1+C$4)*(1-((1+Supuestos!$E$7*Supuestos!$E$8)*(Supuestos!$E$54+Supuestos!$E$56)+Supuestos!$E$55))-(Equilibrio!C7-Equilibrio!C5*((1+Supuestos!$E$7*Supuestos!$E$8)*(Supuestos!$E$54+Supuestos!$E$56)+Supuestos!$E$55)))+Equilibrio!C10*(1+C$4)-Equilibrio!C9 -> -977.94063 | D11: =$A11*Equilibrio!C12*(Equilibrio!C5*(1+D$4)*(1-((1+Supuestos!$E$7*Supuestos!$E$8)*(Supuestos!$E$54+Supuestos!$E$56)+Supuestos!$E$55))-(Equilibrio!C7-Equilibrio!C5*((1+Supuestos!$E$7*Supuestos!$E$8)*(Supuestos!$E$54+Supuestos!$E$56)+Supuestos!$E$55)))+Equilibrio!C10*(1+D$4)-Equilibrio!C9 -> -618.15699 | E11: =$A11*Equilibrio!C12*(Equilibrio!C5*(1+E$4)*(1-((1+Supuestos!$E$7*Supuestos!$E$8)*(Supuestos!$E$54+Supuestos!$E$56)+Supuestos!$E$55))-(Equilibrio!C7-Equilibrio!C5*((1+Supuestos!$E$7*Supuestos!$E$8)*(Supuestos!$E$54+Supuestos!$E$56)+Supuestos!$E$55)))+Equilibrio!C10*(1+E$4)-Equilibrio!C9 -> -258.37334 | F11: =$A11*Equilibrio!C12*(Equilibrio!C5*(1+F$4)*(1-((1+Supuestos!$E$7*Supuestos!$E$8)*(Supuestos!$E$54+Supuestos!$E$56)+Supuestos!$E$55))-(Equilibrio!C7-Equilibrio!C5*((1+Supuestos!$E$7*Supuestos!$E$8)*(Supuestos!$E$54+Supuestos!$E$56)+Supuestos!$E$55)))+Equilibrio!C10*(1+F$4)-Equilibrio!C9 -> 101.41031
A13: Lectura: en rojo, el mes da pérdida. La celda de 0 % de precio y la ocupación que alcanza el escenario Base es la del Resumen.
A15: Qué mueve más el resultado (mes en régimen, escenario Base, ±20 %)
A16: Variable | B16: −20 % | C16: +20 % | D16: Rango
A17: Precio de las membresías | B17: =Modelo_Base!AM7*Equilibrio!C8+Equilibrio!C10-Equilibrio!C9+Modelo_Base!AM7*Equilibrio!C5*(1-((1+Supuestos!$E$7*Supuestos!$E$8)*(Supuestos!$E$54+Supuestos!$E$56)+Supuestos!$E$55))*(-0.2) -> -1880.5993 | C17: =Modelo_Base!AM7*Equilibrio!C8+Equilibrio!C10-Equilibrio!C9+Modelo_Base!AM7*Equilibrio!C5*(1-((1+Supuestos!$E$7*Supuestos!$E$8)*(Supuestos!$E$54+Supuestos!$E$56)+Supuestos!$E$55))*(0.2) -> -1326.7912 | D17: =ABS(C17-B17) -> 553.80808
A18: Cantidad de miembros flex | B18: =Modelo_Base!AM7*0.8*Equilibrio!C8+Equilibrio!C10-Equilibrio!C9 -> -1830.2234 | C18: =MIN(Modelo_Base!AM7*1.2,Equilibrio!C12)*Equilibrio!C8+Equilibrio!C10-Equilibrio!C9 -> -1377.1671 | D18: =ABS(C18-B18) -> 453.05624
A19: Costos fijos | B19: =Modelo_Base!AM7*Equilibrio!C8+Equilibrio!C10-Equilibrio!C9*0.8 -> -854.70579 | C19: =Modelo_Base!AM7*Equilibrio!C8+Equilibrio!C10-Equilibrio!C9*1.2 -> -2352.6847 | D19: =ABS(C19-B19) -> 1497.9789
A20: Personal (sueldos y cargas) | B20: =Modelo_Base!AM7*Equilibrio!C8+Equilibrio!C10-Equilibrio!C9+Modelo_Base!AM30*0.2 -> -1272.2553 | C20: =Modelo_Base!AM7*Equilibrio!C8+Equilibrio!C10-Equilibrio!C9-Modelo_Base!AM30*0.2 -> -1935.1353 | D20: =ABS(C20-B20) -> 662.88
A22: Referencia: resultado del mes 36, escenario Base | B22: =Modelo_Base!AM42 -> -1603.6953

Sheet Modelo_Conservador
A1: Modelo mensual a 36 meses · escenario Conservador (USD constantes)
A2: Miembros = fin de mes. Ingresos sin IVA. Flujo de caja con la casa propia (sin alquiler pagado); abajo, el resultado económico restando el alquiler que se deja de cobrar.
B3: Mes | C3: 0 | D3: 1 | E3: 2 | F3: 3 | G3: 4 | H3: 5 | I3: 6 | J3: 7 | K3: 8 | L3: 9 | M3: 10 | N3: 11 | O3: 12 | P3: 13 | Q3: 14 | R3: 15 | S3: 16 | T3: 17 | U3: 18 | V3: 19 | W3: 20 | X3: 21 | Y3: 22 | Z3: 23 | AA3: 24 | AB3: 25 | AC3: 26 | AD3: 27 | AE3: 28 | AF3: 29 | AG3: 30 | AH3: 31 | AI3: 32 | AJ3: 33 | AK3: 34 | AL3: 35 | AM3: 36
B4: MIEMBROS Y OCUPACIÓN
B5: Tope de miembros flex que entran en los puestos (pico) | D5: =(Supuestos!$D$12*Supuestos!$D$9/((Supuestos!$D$29*Supuestos!$D$21+Supuestos!$D$30*Supuestos!$D$22+Supuestos!$D$31*Supuestos!$D$23+Supuestos!$D$32*Supuestos!$D$24)*Supuestos!$D$17*Supuestos!$D$18)) -> 45.561793 | E5: =(Supuestos!$D$12*Supuestos!$D$9/((Supuestos!$D$29*Supuestos!$D$21+Supuestos!$D$30*Supuestos!$D$22+Supuestos!$D$31*Supuestos!$D$23+Supuestos!$D$32*Supuestos!$D$24)*Supuestos!$D$17*Supuestos!$D$18)) -> 45.561793 | F5: =(Supuestos!$D$12*Supuestos!$D$9/((Supuestos!$D$29*Supuestos!$D$21+Supuestos!$D$30*Supuestos!$D$22+Supuestos!$D$31*Supuestos!$D$23+Supuestos!$D$32*Supuestos!$D$24)*Supuestos!$D$17*Supuestos!$D$18)) -> 45.561793 | G5: =(Supuestos!$D$12*Supuestos!$D$9/((Supuestos!$D$29*Supuestos!$D$21+Supuestos!$D$30*Supuestos!$D$22+Supuestos!$D$31*Supuestos!$D$23+Supuestos!$D$32*Supuestos!$D$24)*Supuestos!$D$17*Supuestos!$D$18)) -> 45.561793 | H5: =(Supuestos!$D$12*Supuestos!$D$9/((Supuestos!$D$29*Supuestos!$D$21+Supuestos!$D$30*Supuestos!$D$22+Supuestos!$D$31*Supuestos!$D$23+Supuestos!$D$32*Supuestos!$D$24)*Supuestos!$D$17*Supuestos!$D$18)) -> 45.561793 | I5: =(Supuestos!$D$12*Supuestos!$D$9/((Supuestos!$D$29*Supuestos!$D$21+Supuestos!$D$30*Supuestos!$D$22+Supuestos!$D$31*Supuestos!$D$23+Supuestos!$D$32*Supuestos!$D$24)*Supuestos!$D$17*Supuestos!$D$18)) -> 45.561793 | J5: =(Supuestos!$D$12*Supuestos!$D$9/((Supuestos!$D$29*Supuestos!$D$21+Supuestos!$D$30*Supuestos!$D$22+Supuestos!$D$31*Supuestos!$D$23+Supuestos!$D$32*Supuestos!$D$24)*Supuestos!$D$17*Supuestos!$D$18)) -> 45.561793 | K5: =(Supuestos!$D$12*Supuestos!$D$9/((Supuestos!$D$29*Supuestos!$D$21+Supuestos!$D$30*Supuestos!$D$22+Supuestos!$D$31*Supuestos!$D$23+Supuestos!$D$32*Supuestos!$D$24)*Supuestos!$D$17*Supuestos!$D$18)) -> 45.561793 | ... AM5: =(Supuestos!$D$12*Supuestos!$D$9/((Supuestos!$D$29*Supuestos!$D$21+Supuestos!$D$30*Supuestos!$D$22+Supuestos!$D$31*Supuestos!$D$23+Supuestos!$D$32*Supuestos!$D$24)*Supuestos!$D$17*Supuestos!$D$18)) -> 45.561793
B6: Altas de miembros flex en el mes | D6: =IF(D$3<=6,Supuestos!$D$46,IF(D$3<=12,Supuestos!$D$47,Supuestos!$D$48)) -> 2 | E6: =IF(E$3<=6,Supuestos!$D$46,IF(E$3<=12,Supuestos!$D$47,Supuestos!$D$48)) -> 2 | F6: =IF(F$3<=6,Supuestos!$D$46,IF(F$3<=12,Supuestos!$D$47,Supuestos!$D$48)) -> 2 | G6: =IF(G$3<=6,Supuestos!$D$46,IF(G$3<=12,Supuestos!$D$47,Supuestos!$D$48)) -> 2 | H6: =IF(H$3<=6,Supuestos!$D$46,IF(H$3<=12,Supuestos!$D$47,Supuestos!$D$48)) -> 2 | I6: =IF(I$3<=6,Supuestos!$D$46,IF(I$3<=12,Supuestos!$D$47,Supuestos!$D$48)) -> 2 | J6: =IF(J$3<=6,Supuestos!$D$46,IF(J$3<=12,Supuestos!$D$47,Supuestos!$D$48)) -> 2 | K6: =IF(K$3<=6,Supuestos!$D$46,IF(K$3<=12,Supuestos!$D$47,Supuestos!$D$48)) -> 2 | ... AM6: =IF(AM$3<=6,Supuestos!$D$46,IF(AM$3<=12,Supuestos!$D$47,Supuestos!$D$48)) -> 1
B7: Miembros flex (fin de mes) | D7: =MIN(D5,Supuestos!$D$45*(1-Supuestos!$D$49)+D6) -> 2 | E7: =MIN(E5,D7*(1-Supuestos!$D$49)+E6) -> 3.84 | F7: =MIN(F5,E7*(1-Supuestos!$D$49)+F6) -> 5.5328 | G7: =MIN(G5,F7*(1-Supuestos!$D$49)+G6) -> 7.090176 | H7: =MIN(H5,G7*(1-Supuestos!$D$49)+H6) -> 8.5229619 | I7: =MIN(I5,H7*(1-Supuestos!$D$49)+I6) -> 9.841125 | J7: =MIN(J5,I7*(1-Supuestos!$D$49)+J6) -> 11.053835 | K7: =MIN(K5,J7*(1-Supuestos!$D$49)+K6) -> 12.169528 | L7: =MIN(L5,K7*(1-Supuestos!$D$49)+L6) -> 13.195966 | ... AM7: =MIN(AM5,AL7*(1-Supuestos!$D$49)+AM6) -> 12.947217
B8: Bajas estimadas de flex en el mes | D8: =Supuestos!$D$45*Supuestos!$D$49 -> 0 | E8: =D7*Supuestos!$D$49 -> 0.16 | F8: =E7*Supuestos!$D$49 -> 0.3072 | G8: =F7*Supuestos!$D$49 -> 0.442624 | H8: =G7*Supuestos!$D$49 -> 0.56721408 | I8: =H7*Supuestos!$D$49 -> 0.68183695 | J8: =I7*Supuestos!$D$49 -> 0.78729 | K8: =J7*Supuestos!$D$49 -> 0.8843068 | L8: =K7*Supuestos!$D$49 -> 0.97356225 | ... AM8: =AL7*Supuestos!$D$49 -> 1.0388884
B9: Puestos fijos ocupados | D9: =MIN(Supuestos!$D$13,Supuestos!$D$50) -> 0.5 | E9: =MIN(Supuestos!$D$13,D9*(1-Supuestos!$D$51)+Supuestos!$D$50) -> 0.975 | F9: =MIN(Supuestos!$D$13,E9*(1-Supuestos!$D$51)+Supuestos!$D$50) -> 1.42625 | G9: =MIN(Supuestos!$D$13,F9*(1-Supuestos!$D$51)+Supuestos!$D$50) -> 1.8549375 | H9: =MIN(Supuestos!$D$13,G9*(1-Supuestos!$D$51)+Supuestos!$D$50) -> 2.2621906 | I9: =MIN(Supuestos!$D$13,H9*(1-Supuestos!$D$51)+Supuestos!$D$50) -> 2.6490811 | J9: =MIN(Supuestos!$D$13,I9*(1-Supuestos!$D$51)+Supuestos!$D$50) -> 3.016627 | K9: =MIN(Supuestos!$D$13,J9*(1-Supuestos!$D$51)+Supuestos!$D$50) -> 3.3657957 | L9: =MIN(Supuestos!$D$13,K9*(1-Supuestos!$D$51)+Supuestos!$D$50) -> 3.6975059 | ... AM9: =MIN(Supuestos!$D$13,AL9*(1-Supuestos!$D$51)+Supuestos!$D$50) -> 4
B10: Oficinas privadas ocupadas | D10: =Supuestos!$D$14*MIN(1,D$3/Supuestos!$D$43) -> 0.2 | E10: =Supuestos!$D$14*MIN(1,E$3/Supuestos!$D$43) -> 0.4 | F10: =Supuestos!$D$14*MIN(1,F$3/Supuestos!$D$43) -> 0.6 | G10: =Supuestos!$D$14*MIN(1,G$3/Supuestos!$D$43) -> 0.8 | H10: =Supuestos!$D$14*MIN(1,H$3/Supuestos!$D$43) -> 1 | I10: =Supuestos!$D$14*MIN(1,I$3/Supuestos!$D$43) -> 1.2 | J10: =Supuestos!$D$14*MIN(1,J$3/Supuestos!$D$43) -> 1.4 | K10: =Supuestos!$D$14*MIN(1,K$3/Supuestos!$D$43) -> 1.6 | ... AM10: =Supuestos!$D$14*MIN(1,AM$3/Supuestos!$D$43) -> 2
B11: Puestos-día usados por miembros flex | D11: =D7*(Supuestos!$D$29*Supuestos!$D$21+Supuestos!$D$30*Supuestos!$D$22+Supuestos!$D$31*Supuestos!$D$23+Supuestos!$D$32*Supuestos!$D$24)*Supuestos!$D$17 -> 20.485 | E11: =E7*(Supuestos!$D$29*Supuestos!$D$21+Supuestos!$D$30*Supuestos!$D$22+Supuestos!$D$31*Supuestos!$D$23+Supuestos!$D$32*Supuestos!$D$24)*Supuestos!$D$17 -> 39.3312 | F11: =F7*(Supuestos!$D$29*Supuestos!$D$21+Supuestos!$D$30*Supuestos!$D$22+Supuestos!$D$31*Supuestos!$D$23+Supuestos!$D$32*Supuestos!$D$24)*Supuestos!$D$17 -> 56.669704 | G11: =G7*(Supuestos!$D$29*Supuestos!$D$21+Supuestos!$D$30*Supuestos!$D$22+Supuestos!$D$31*Supuestos!$D$23+Supuestos!$D$32*Supuestos!$D$24)*Supuestos!$D$17 -> 72.621128 | H11: =H7*(Supuestos!$D$29*Supuestos!$D$21+Supuestos!$D$30*Supuestos!$D$22+Supuestos!$D$31*Supuestos!$D$23+Supuestos!$D$32*Supuestos!$D$24)*Supuestos!$D$17 -> 87.296437 | I11: =I7*(Supuestos!$D$29*Supuestos!$D$21+Supuestos!$D$30*Supuestos!$D$22+Supuestos!$D$31*Supuestos!$D$23+Supuestos!$D$32*Supuestos!$D$24)*Supuestos!$D$17 -> 100.79772 | J11: =J7*(Supuestos!$D$29*Supuestos!$D$21+Supuestos!$D$30*Supuestos!$D$22+Supuestos!$D$31*Supuestos!$D$23+Supuestos!$D$32*Supuestos!$D$24)*Supuestos!$D$17 -> 113.2189 | K11: =K7*(Supuestos!$D$29*Supuestos!$D$21+Supuestos!$D$30*Supuestos!$D$22+Supuestos!$D$31*Supuestos!$D$23+Supuestos!$D$32*Supuestos!$D$24)*Supuestos!$D$17 -> 124.64639 | ... AM11: =AM7*(Supuestos!$D$29*Supuestos!$D$21+Supuestos!$D$30*Supuestos!$D$22+Supuestos!$D$31*Supuestos!$D$23+Supuestos!$D$32*Supuestos!$D$24)*Supuestos!$D$17 -> 132.61187
B12: Ocupación promedio de puestos flex (días hábiles) | D12: =D11/(Supuestos!$D$12*Supuestos!$D$9) -> 0.032515873 | E12: =E11/(Supuestos!$D$12*Supuestos!$D$9) -> 0.062430476 | F12: =F11/(Supuestos!$D$12*Supuestos!$D$9) -> 0.089951911 | G12: =G11/(Supuestos!$D$12*Supuestos!$D$9) -> 0.11527163 | H12: =H11/(Supuestos!$D$12*Supuestos!$D$9) -> 0.13856577 | I12: =I11/(Supuestos!$D$12*Supuestos!$D$9) -> 0.15999638 | J12: =J11/(Supuestos!$D$12*Supuestos!$D$9) -> 0.17971255 | K12: =K11/(Supuestos!$D$12*Supuestos!$D$9) -> 0.19785142 | ... AM12: =AM11/(Supuestos!$D$12*Supuestos!$D$9) -> 0.21049503
B13: Puestos flex simultáneos en el pico (estimado) | D13: =D11/Supuestos!$D$9*Supuestos!$D$18 -> 1.3168929 | E13: =E11/Supuestos!$D$9*Supuestos!$D$18 -> 2.5284343 | F13: =F11/Supuestos!$D$9*Supuestos!$D$18 -> 3.6430524 | G13: =G11/Supuestos!$D$9*Supuestos!$D$18 -> 4.6685011 | H13: =H11/Supuestos!$D$9*Supuestos!$D$18 -> 5.6119138 | I13: =I11/Supuestos!$D$9*Supuestos!$D$18 -> 6.4798536 | J13: =J11/Supuestos!$D$9*Supuestos!$D$18 -> 7.2783582 | K13: =K11/Supuestos!$D$9*Supuestos!$D$18 -> 8.0129824 | ... AM13: =AM11/Supuestos!$D$9*Supuestos!$D$18 -> 8.5250486
B14: INGRESOS (USD sin IVA)
B15: Membresías flex (días por mes / ilimitado) | D15: =D7*((Supuestos!$D$29*Supuestos!$D$25+Supuestos!$D$30*Supuestos!$D$26+Supuestos!$D$31*Supuestos!$D$27+Supuestos!$D$32*Supuestos!$D$28)*Supuestos!$D$37)*(1-Supuestos!$D$38)/(1+Supuestos!$D$7*Supuestos!$D$8)/Supuestos!$D$6 -> 81.823903 | E15: =E7*((Supuestos!$D$29*Supuestos!$D$25+Supuestos!$D$30*Supuestos!$D$26+Supuestos!$D$31*Supuestos!$D$27+Supuestos!$D$32*Supuestos!$D$28)*Supuestos!$D$37)*(1-Supuestos!$D$38)/(1+Supuestos!$D$7*Supuestos!$D$8)/Supuestos!$D$6 -> 157.10189 | F15: =F7*((Supuestos!$D$29*Supuestos!$D$25+Supuestos!$D$30*Supuestos!$D$26+Supuestos!$D$31*Supuestos!$D$27+Supuestos!$D$32*Supuestos!$D$28)*Supuestos!$D$37)*(1-Supuestos!$D$38)/(1+Supuestos!$D$7*Supuestos!$D$8)/Supuestos!$D$6 -> 226.35765 | G15: =G7*((Supuestos!$D$29*Supuestos!$D$25+Supuestos!$D$30*Supuestos!$D$26+Supuestos!$D$31*Supuestos!$D$27+Supuestos!$D$32*Supuestos!$D$28)*Supuestos!$D$37)*(1-Supuestos!$D$38)/(1+Supuestos!$D$7*Supuestos!$D$8)/Supuestos!$D$6 -> 290.07294 | H15: =H7*((Supuestos!$D$29*Supuestos!$D$25+Supuestos!$D$30*Supuestos!$D$26+Supuestos!$D$31*Supuestos!$D$27+Supuestos!$D$32*Supuestos!$D$28)*Supuestos!$D$37)*(1-Supuestos!$D$38)/(1+Supuestos!$D$7*Supuestos!$D$8)/Supuestos!$D$6 -> 348.69101 | I15: =I7*((Supuestos!$D$29*Supuestos!$D$25+Supuestos!$D$30*Supuestos!$D$26+Supuestos!$D$31*Supuestos!$D$27+Supuestos!$D$32*Supuestos!$D$28)*Supuestos!$D$37)*(1-Supuestos!$D$38)/(1+Supuestos!$D$7*Supuestos!$D$8)/Supuestos!$D$6 -> 402.61963 | J15: =J7*((Supuestos!$D$29*Supuestos!$D$25+Supuestos!$D$30*Supuestos!$D$26+Supuestos!$D$31*Supuestos!$D$27+Supuestos!$D$32*Supuestos!$D$28)*Supuestos!$D$37)*(1-Supuestos!$D$38)/(1+Supuestos!$D$7*Supuestos!$D$8)/Supuestos!$D$6 -> 452.23396 | K15: =K7*((Supuestos!$D$29*Supuestos!$D$25+Supuestos!$D$30*Supuestos!$D$26+Supuestos!$D$31*Supuestos!$D$27+Supuestos!$D$32*Supuestos!$D$28)*Supuestos!$D$37)*(1-Supuestos!$D$38)/(1+Supuestos!$D$7*Supuestos!$D$8)/Supuestos!$D$6 -> 497.87915 | ... AM15: =AM7*((Supuestos!$D$29*Supuestos!$D$25+Supuestos!$D$30*Supuestos!$D$26+Supuestos!$D$31*Supuestos!$D$27+Supuestos!$D$32*Supuestos!$D$28)*Supuestos!$D$37)*(1-Supuestos!$D$38)/(1+Supuestos!$D$7*Supuestos!$D$8)/Supuestos!$D$6 -> 529.6959
B16: Puestos fijos | D16: =D9*Supuestos!$D$33*Supuestos!$D$37*(1-Supuestos!$D$38)/(1+Supuestos!$D$7*Supuestos!$D$8)/Supuestos!$D$6 -> 25.317864 | E16: =E9*Supuestos!$D$33*Supuestos!$D$37*(1-Supuestos!$D$38)/(1+Supuestos!$D$7*Supuestos!$D$8)/Supuestos!$D$6 -> 49.369835 | F16: =F9*Supuestos!$D$33*Supuestos!$D$37*(1-Supuestos!$D$38)/(1+Supuestos!$D$7*Supuestos!$D$8)/Supuestos!$D$6 -> 72.219207 | G16: =G9*Supuestos!$D$33*Supuestos!$D$37*(1-Supuestos!$D$38)/(1+Supuestos!$D$7*Supuestos!$D$8)/Supuestos!$D$6 -> 93.926111 | H16: =H9*Supuestos!$D$33*Supuestos!$D$37*(1-Supuestos!$D$38)/(1+Supuestos!$D$7*Supuestos!$D$8)/Supuestos!$D$6 -> 114.54767 | I16: =I9*Supuestos!$D$33*Supuestos!$D$37*(1-Supuestos!$D$38)/(1+Supuestos!$D$7*Supuestos!$D$8)/Supuestos!$D$6 -> 134.13815 | J16: =J9*Supuestos!$D$33*Supuestos!$D$37*(1-Supuestos!$D$38)/(1+Supuestos!$D$7*Supuestos!$D$8)/Supuestos!$D$6 -> 152.74911 | K16: =K9*Supuestos!$D$33*Supuestos!$D$37*(1-Supuestos!$D$38)/(1+Supuestos!$D$7*Supuestos!$D$8)/Supuestos!$D$6 -> 170.42951 | ... AM16: =AM9*Supuestos!$D$33*Supuestos!$D$37*(1-Supuestos!$D$38)/(1+Supuestos!$D$7*Supuestos!$D$8)/Supuestos!$D$6 -> 202.54291
B17: Oficinas privadas (complemento) | D17: =D10*Supuestos!$D$34*Supuestos!$D$37*(1-Supuestos!$D$38)/(1+Supuestos!$D$7*Supuestos!$D$8)/Supuestos!$D$6 -> 41.195168 | E17: =E10*Supuestos!$D$34*Supuestos!$D$37*(1-Supuestos!$D$38)/(1+Supuestos!$D$7*Supuestos!$D$8)/Supuestos!$D$6 -> 82.390337 | F17: =F10*Supuestos!$D$34*Supuestos!$D$37*(1-Supuestos!$D$38)/(1+Supuestos!$D$7*Supuestos!$D$8)/Supuestos!$D$6 -> 123.58551 | G17: =G10*Supuestos!$D$34*Supuestos!$D$37*(1-Supuestos!$D$38)/(1+Supuestos!$D$7*Supuestos!$D$8)/Supuestos!$D$6 -> 164.78067 | H17: =H10*Supuestos!$D$34*Supuestos!$D$37*(1-Supuestos!$D$38)/(1+Supuestos!$D$7*Supuestos!$D$8)/Supuestos!$D$6 -> 205.97584 | I17: =I10*Supuestos!$D$34*Supuestos!$D$37*(1-Supuestos!$D$38)/(1+Supuestos!$D$7*Supuestos!$D$8)/Supuestos!$D$6 -> 247.17101 | J17: =J10*Supuestos!$D$34*Supuestos!$D$37*(1-Supuestos!$D$38)/(1+Supuestos!$D$7*Supuestos!$D$8)/Supuestos!$D$6 -> 288.36618 | K17: =K10*Supuestos!$D$34*Supuestos!$D$37*(1-Supuestos!$D$38)/(1+Supuestos!$D$7*Supuestos!$D$8)/Supuestos!$D$6 -> 329.56135 | ... AM17: =AM10*Supuestos!$D$34*Supuestos!$D$37*(1-Supuestos!$D$38)/(1+Supuestos!$D$7*Supuestos!$D$8)/Supuestos!$D$6 -> 411.95168
B18: Pases diarios | D18: =Supuestos!$D$39*MIN(1,D$3/Supuestos!$D$42)*Supuestos!$D$35*Supuestos!$D$37/(1+Supuestos!$D$7*Supuestos!$D$8)/Supuestos!$D$6 -> 10.88684 | E18: =Supuestos!$D$39*MIN(1,E$3/Supuestos!$D$42)*Supuestos!$D$35*Supuestos!$D$37/(1+Supuestos!$D$7*Supuestos!$D$8)/Supuestos!$D$6 -> 21.773681 | F18: =Supuestos!$D$39*MIN(1,F$3/Supuestos!$D$42)*Supuestos!$D$35*Supuestos!$D$37/(1+Supuestos!$D$7*Supuestos!$D$8)/Supuestos!$D$6 -> 32.660521 | G18: =Supuestos!$D$39*MIN(1,G$3/Supuestos!$D$42)*Supuestos!$D$35*Supuestos!$D$37/(1+Supuestos!$D$7*Supuestos!$D$8)/Supuestos!$D$6 -> 43.547362 | H18: =Supuestos!$D$39*MIN(1,H$3/Supuestos!$D$42)*Supuestos!$D$35*Supuestos!$D$37/(1+Supuestos!$D$7*Supuestos!$D$8)/Supuestos!$D$6 -> 54.434202 | I18: =Supuestos!$D$39*MIN(1,I$3/Supuestos!$D$42)*Supuestos!$D$35*Supuestos!$D$37/(1+Supuestos!$D$7*Supuestos!$D$8)/Supuestos!$D$6 -> 65.321043 | J18: =Supuestos!$D$39*MIN(1,J$3/Supuestos!$D$42)*Supuestos!$D$35*Supuestos!$D$37/(1+Supuestos!$D$7*Supuestos!$D$8)/Supuestos!$D$6 -> 76.207883 | K18: =Supuestos!$D$39*MIN(1,K$3/Supuestos!$D$42)*Supuestos!$D$35*Supuestos!$D$37/(1+Supuestos!$D$7*Supuestos!$D$8)/Supuestos!$D$6 -> 87.094723 | ... AM18: =Supuestos!$D$39*MIN(1,AM$3/Supuestos!$D$42)*Supuestos!$D$35*Supuestos!$D$37/(1+Supuestos!$D$7*Supuestos!$D$8)/Supuestos!$D$6 -> 130.64209
B19: Salas por hora a externos | D19: =Supuestos!$D$40*MIN(1,D$3/Supuestos!$D$42)*Supuestos!$D$36*Supuestos!$D$37/(1+Supuestos!$D$7*Supuestos!$D$8)/Supuestos!$D$6 -> 5.1652893 | E19: =Supuestos!$D$40*MIN(1,E$3/Supuestos!$D$42)*Supuestos!$D$36*Supuestos!$D$37/(1+Supuestos!$D$7*Supuestos!$D$8)/Supuestos!$D$6 -> 10.330579 | F19: =Supuestos!$D$40*MIN(1,F$3/Supuestos!$D$42)*Supuestos!$D$36*Supuestos!$D$37/(1+Supuestos!$D$7*Supuestos!$D$8)/Supuestos!$D$6 -> 15.495868 | G19: =Supuestos!$D$40*MIN(1,G$3/Supuestos!$D$42)*Supuestos!$D$36*Supuestos!$D$37/(1+Supuestos!$D$7*Supuestos!$D$8)/Supuestos!$D$6 -> 20.661157 | H19: =Supuestos!$D$40*MIN(1,H$3/Supuestos!$D$42)*Supuestos!$D$36*Supuestos!$D$37/(1+Supuestos!$D$7*Supuestos!$D$8)/Supuestos!$D$6 -> 25.826446 | I19: =Supuestos!$D$40*MIN(1,I$3/Supuestos!$D$42)*Supuestos!$D$36*Supuestos!$D$37/(1+Supuestos!$D$7*Supuestos!$D$8)/Supuestos!$D$6 -> 30.991736 | J19: =Supuestos!$D$40*MIN(1,J$3/Supuestos!$D$42)*Supuestos!$D$36*Supuestos!$D$37/(1+Supuestos!$D$7*Supuestos!$D$8)/Supuestos!$D$6 -> 36.157025 | K19: =Supuestos!$D$40*MIN(1,K$3/Supuestos!$D$42)*Supuestos!$D$36*Supuestos!$D$37/(1+Supuestos!$D$7*Supuestos!$D$8)/Supuestos!$D$6 -> 41.322314 | ... AM19: =Supuestos!$D$40*MIN(1,AM$3/Supuestos!$D$42)*Supuestos!$D$36*Supuestos!$D$37/(1+Supuestos!$D$7*Supuestos!$D$8)/Supuestos!$D$6 -> 61.983471
B20: Otros (domicilio comercial, eventos) | D20: =Supuestos!$D$41*MIN(1,D$3/Supuestos!$D$42) -> 0 | E20: =Supuestos!$D$41*MIN(1,E$3/Supuestos!$D$42) -> 0 | F20: =Supuestos!$D$41*MIN(1,F$3/Supuestos!$D$42) -> 0 | G20: =Supuestos!$D$41*MIN(1,G$3/Supuestos!$D$42) -> 0 | H20: =Supuestos!$D$41*MIN(1,H$3/Supuestos!$D$42) -> 0 | I20: =Supuestos!$D$41*MIN(1,I$3/Supuestos!$D$42) -> 0 | J20: =Supuestos!$D$41*MIN(1,J$3/Supuestos!$D$42) -> 0 | K20: =Supuestos!$D$41*MIN(1,K$3/Supuestos!$D$42) -> 0 | ... AM20: =Supuestos!$D$41*MIN(1,AM$3/Supuestos!$D$42) -> 0
B21: INGRESOS TOTALES | D21: =SUM(D15:D20) -> 164.38907 | E21: =SUM(E15:E20) -> 320.96633 | F21: =SUM(F15:F20) -> 470.31875 | G21: =SUM(G15:G20) -> 612.98824 | H21: =SUM(H15:H20) -> 749.47517 | I21: =SUM(I15:I20) -> 880.24157 | J21: =SUM(J15:J20) -> 1005.7142 | K21: =SUM(K15:K20) -> 1126.287 | ... AM21: =SUM(AM15:AM20) -> 1336.8161
B22: COSTOS VARIABLES
B23: Café, té, agua y consumibles | D23: =(D11+D9*Supuestos!$D$9*Supuestos!$D$19+(D10*Supuestos!$D$15*Supuestos!$D$9*Supuestos!$D$19)+Supuestos!$D$39*MIN(1,D$3/Supuestos!$D$42))*Supuestos!$D$53 -> 49.570633 | E23: =(E11+E9*Supuestos!$D$9*Supuestos!$D$19+(E10*Supuestos!$D$15*Supuestos!$D$9*Supuestos!$D$19)+Supuestos!$D$39*MIN(1,E$3/Supuestos!$D$42))*Supuestos!$D$53 -> 96.629531 | F23: =(F11+F9*Supuestos!$D$9*Supuestos!$D$19+(F10*Supuestos!$D$15*Supuestos!$D$9*Supuestos!$D$19)+Supuestos!$D$39*MIN(1,F$3/Supuestos!$D$42))*Supuestos!$D$53 -> 141.36226 | G23: =(G11+G9*Supuestos!$D$9*Supuestos!$D$19+(G10*Supuestos!$D$15*Supuestos!$D$9*Supuestos!$D$19)+Supuestos!$D$39*MIN(1,G$3/Supuestos!$D$42))*Supuestos!$D$53 -> 183.94031 | H23: =(H11+H9*Supuestos!$D$9*Supuestos!$D$19+(H10*Supuestos!$D$15*Supuestos!$D$9*Supuestos!$D$19)+Supuestos!$D$39*MIN(1,H$3/Supuestos!$D$42))*Supuestos!$D$53 -> 224.52218 | I23: =(I11+I9*Supuestos!$D$9*Supuestos!$D$19+(I10*Supuestos!$D$15*Supuestos!$D$9*Supuestos!$D$19)+Supuestos!$D$39*MIN(1,I$3/Supuestos!$D$42))*Supuestos!$D$53 -> 263.25439 | J23: =(J11+J9*Supuestos!$D$9*Supuestos!$D$19+(J10*Supuestos!$D$15*Supuestos!$D$9*Supuestos!$D$19)+Supuestos!$D$39*MIN(1,J$3/Supuestos!$D$42))*Supuestos!$D$53 -> 300.27238 | K23: =(K11+K9*Supuestos!$D$9*Supuestos!$D$19+(K10*Supuestos!$D$15*Supuestos!$D$9*Supuestos!$D$19)+Supuestos!$D$39*MIN(1,K$3/Supuestos!$D$42))*Supuestos!$D$53 -> 335.70141 | ... AM23: =(AM11+AM9*Supuestos!$D$9*Supuestos!$D$19+(AM10*Supuestos!$D$15*Supuestos!$D$9*Supuestos!$D$19)+Supuestos!$D$39*MIN(1,AM$3/Supuestos!$D$42))*Supuestos!$D$53 -> 391.14648
B24: Comisiones de cobro | D24: =D21*(1+Supuestos!$D$7*Supuestos!$D$8)*Supuestos!$D$54 -> 12.511487 | E24: =E21*(1+Supuestos!$D$7*Supuestos!$D$8)*Supuestos!$D$54 -> 24.428426 | F24: =F21*(1+Supuestos!$D$7*Supuestos!$D$8)*Supuestos!$D$54 -> 35.79549 | G24: =G21*(1+Supuestos!$D$7*Supuestos!$D$8)*Supuestos!$D$54 -> 46.653922 | H24: =H21*(1+Supuestos!$D$7*Supuestos!$D$8)*Supuestos!$D$54 -> 57.041805 | I24: =I21*(1+Supuestos!$D$7*Supuestos!$D$8)*Supuestos!$D$54 -> 66.994305 | J24: =J21*(1+Supuestos!$D$7*Supuestos!$D$8)*Supuestos!$D$54 -> 76.543899 | K24: =K21*(1+Supuestos!$D$7*Supuestos!$D$8)*Supuestos!$D$54 -> 85.720581 | ... AM24: =AM21*(1+Supuestos!$D$7*Supuestos!$D$8)*Supuestos!$D$54 -> 101.74373
B25: Ingresos Brutos | D25: =D21*Supuestos!$D$55 -> 8.2194533 | E25: =E21*Supuestos!$D$55 -> 16.048316 | F25: =F21*Supuestos!$D$55 -> 23.515937 | G25: =G21*Supuestos!$D$55 -> 30.649412 | H25: =H21*Supuestos!$D$55 -> 37.473758 | I25: =I21*Supuestos!$D$55 -> 44.012078 | J25: =J21*Supuestos!$D$55 -> 50.285708 | K25: =K21*Supuestos!$D$55 -> 56.314352 | ... AM25: =AM21*Supuestos!$D$55 -> 66.840803
B26: Impuesto a los débitos y créditos (aprox.) | D26: =D21*(1+Supuestos!$D$7*Supuestos!$D$8)*Supuestos!$D$56 -> 2.3869292 | E26: =E21*(1+Supuestos!$D$7*Supuestos!$D$8)*Supuestos!$D$56 -> 4.660431 | F26: =F21*(1+Supuestos!$D$7*Supuestos!$D$8)*Supuestos!$D$56 -> 6.8290282 | G26: =G21*(1+Supuestos!$D$7*Supuestos!$D$8)*Supuestos!$D$56 -> 8.9005893 | H26: =H21*(1+Supuestos!$D$7*Supuestos!$D$8)*Supuestos!$D$56 -> 10.882379 | I26: =I21*(1+Supuestos!$D$7*Supuestos!$D$8)*Supuestos!$D$56 -> 12.781108 | J26: =J21*(1+Supuestos!$D$7*Supuestos!$D$8)*Supuestos!$D$56 -> 14.60297 | K26: =K21*(1+Supuestos!$D$7*Supuestos!$D$8)*Supuestos!$D$56 -> 16.353688 | ... AM26: =AM21*(1+Supuestos!$D$7*Supuestos!$D$8)*Supuestos!$D$56 -> 19.410569
B27: Total costos variables | D27: =SUM(D23:D26) -> 72.688503 | E27: =SUM(E23:E26) -> 141.7667 | F27: =SUM(F23:F26) -> 207.50271 | G27: =SUM(G23:G26) -> 270.14423 | H27: =SUM(H23:H26) -> 329.92012 | I27: =SUM(I23:I26) -> 387.04188 | J27: =SUM(J23:J26) -> 441.70496 | K27: =SUM(K23:K26) -> 494.09004 | ... AM27: =SUM(AM23:AM26) -> 579.14158
B28: MARGEN DE CONTRIBUCIÓN | D28: =D21-D27 -> 91.700562 | E28: =E21-E27 -> 179.19962 | F28: =F21-F27 -> 262.81603 | G28: =G21-G27 -> 342.84401 | H28: =H21-H27 -> 419.55504 | I28: =I21-I27 -> 493.19969 | J28: =J21-J27 -> 564.00919 | K28: =K21-K27 -> 632.19701 | ... AM28: =AM21-AM27 -> 757.67447
B29: COSTOS FIJOS MENSUALES
B30: Personal (recepción / comunidad), con cargas | D30: =Supuestos!$D$58*Supuestos!$D$59 -> 1739.4 | E30: =Supuestos!$D$58*Supuestos!$D$59 -> 1739.4 | F30: =Supuestos!$D$58*Supuestos!$D$59 -> 1739.4 | G30: =Supuestos!$D$58*Supuestos!$D$59 -> 1739.4 | H30: =Supuestos!$D$58*Supuestos!$D$59 -> 1739.4 | I30: =Supuestos!$D$58*Supuestos!$D$59 -> 1739.4 | J30: =Supuestos!$D$58*Supuestos!$D$59 -> 1739.4 | K30: =Supuestos!$D$58*Supuestos!$D$59 -> 1739.4 | ... AM30: =Supuestos!$D$58*Supuestos!$D$59 -> 1739.4
B31: Limpieza | D31: =Supuestos!$D$60 -> 673.1 | E31: =Supuestos!$D$60 -> 673.1 | F31: =Supuestos!$D$60 -> 673.1 | G31: =Supuestos!$D$60 -> 673.1 | H31: =Supuestos!$D$60 -> 673.1 | I31: =Supuestos!$D$60 -> 673.1 | J31: =Supuestos!$D$60 -> 673.1 | K31: =Supuestos!$D$60 -> 673.1 | ... AM31: =Supuestos!$D$60 -> 673.1
B32: Internet principal + respaldo | D32: =Supuestos!$D$61 -> 115.4 | E32: =Supuestos!$D$61 -> 115.4 | F32: =Supuestos!$D$61 -> 115.4 | G32: =Supuestos!$D$61 -> 115.4 | H32: =Supuestos!$D$61 -> 115.4 | I32: =Supuestos!$D$61 -> 115.4 | J32: =Supuestos!$D$61 -> 115.4 | K32: =Supuestos!$D$61 -> 115.4 | ... AM32: =Supuestos!$D$61 -> 115.4
B33: Electricidad, gas y agua | D33: =Supuestos!$D$62 -> 27.1 | E33: =Supuestos!$D$62 -> 27.1 | F33: =Supuestos!$D$62 -> 27.1 | G33: =Supuestos!$D$62 -> 27.1 | H33: =Supuestos!$D$62 -> 27.1 | I33: =Supuestos!$D$62 -> 27.1 | J33: =Supuestos!$D$62 -> 27.1 | K33: =Supuestos!$D$62 -> 27.1 | ... AM33: =Supuestos!$D$62 -> 27.1
B34: Seguros | D34: =Supuestos!$D$63 -> 192.3 | E34: =Supuestos!$D$63 -> 192.3 | F34: =Supuestos!$D$63 -> 192.3 | G34: =Supuestos!$D$63 -> 192.3 | H34: =Supuestos!$D$63 -> 192.3 | I34: =Supuestos!$D$63 -> 192.3 | J34: =Supuestos!$D$63 -> 192.3 | K34: =Supuestos!$D$63 -> 192.3 | ... AM34: =Supuestos!$D$63 -> 192.3
B35: Software de gestión y reservas | D35: =Supuestos!$D$64 -> 177 | E35: =Supuestos!$D$64 -> 177 | F35: =Supuestos!$D$64 -> 177 | G35: =Supuestos!$D$64 -> 177 | H35: =Supuestos!$D$64 -> 177 | I35: =Supuestos!$D$64 -> 177 | J35: =Supuestos!$D$64 -> 177 | K35: =Supuestos!$D$64 -> 177 | ... AM35: =Supuestos!$D$64 -> 177
B36: Contador y administración | D36: =Supuestos!$D$65 -> 0 | E36: =Supuestos!$D$65 -> 0 | F36: =Supuestos!$D$65 -> 0 | G36: =Supuestos!$D$65 -> 0 | H36: =Supuestos!$D$65 -> 0 | I36: =Supuestos!$D$65 -> 0 | J36: =Supuestos!$D$65 -> 0 | K36: =Supuestos!$D$65 -> 0 | ... AM36: =Supuestos!$D$65 -> 0
B37: Mantenimiento y reposición | D37: =Inversion!D21*Supuestos!$D$66/12 -> 1149.1258 | E37: =Inversion!D21*Supuestos!$D$66/12 -> 1149.1258 | F37: =Inversion!D21*Supuestos!$D$66/12 -> 1149.1258 | G37: =Inversion!D21*Supuestos!$D$66/12 -> 1149.1258 | H37: =Inversion!D21*Supuestos!$D$66/12 -> 1149.1258 | I37: =Inversion!D21*Supuestos!$D$66/12 -> 1149.1258 | J37: =Inversion!D21*Supuestos!$D$66/12 -> 1149.1258 | K37: =Inversion!D21*Supuestos!$D$66/12 -> 1149.1258 | L37: =Inversion!D21*Supuestos!$D$66/12 -> 1149.1258 | M37: =Inversion!D21*Supuestos!$D$66/12 -> 1149.1258 | N37: =Inversion!D21*Supuestos!$D$66/12 -> 1149.1258 | O37: =Inversion!D21*Supuestos!$D$66/12 -> 1149.1258 | P37: =Inversion!D21*Supuestos!$D$66/12 -> 1149.1258 | Q37: =Inversion!D21*Supuestos!$D$66/12 -> 1149.1258 | R37: =Inversion!D21*Supuestos!$D$66/12 -> 1149.1258 | S37: =Inversion!D21*Supuestos!$D$66/12 -> 1149.1258 | T37: =Inversion!D21*Supuestos!$D$66/12 -> 1149.1258 | U37: =Inversion!D21*Supuestos!$D$66/12 -> 1149.1258 | V37: =Inversion!D21*Supuestos!$D$66/12 -> 1149.1258 | W37: =Inversion!D21*Supuestos!$D$66/12 -> 1149.1258 | X37: =Inversion!D21*Supuestos!$D$66/12 -> 1149.1258 | Y37: =Inversion!D21*Supuestos!$D$66/12 -> 1149.1258 | Z37: =Inversion!D21*Supuestos!$D$66/12 -> 1149.1258 | AA37: =Inversion!D21*Supuestos!$D$66/12 -> 1149.1258 | AB37: =Inversion!D21*Supuestos!$D$66/12 -> 1149.1258 | AC37: =Inversion!D21*Supuestos!$D$66/12 -> 1149.1258 | AD37: =Inversion!D21*Supuestos!$D$66/12 -> 1149.1258 | AE37: =Inversion!D21*Supuestos!$D$66/12 -> 1149.1258 | AF37: =Inversion!D21*Supuestos!$D$66/12 -> 1149.1258 | AG37: =Inversion!D21*Supuestos!$D$66/12 -> 1149.1258 | AH37: =Inversion!D21*Supuestos!$D$66/12 -> 1149.1258 | AI37: =Inversion!D21*Supuestos!$D$66/12 -> 1149.1258 | AJ37: =Inversion!D21*Supuestos!$D$66/12 -> 1149.1258 | AK37: =Inversion!D21*Supuestos!$D$66/12 -> 1149.1258 | AL37: =Inversion!D21*Supuestos!$D$66/12 -> 1149.1258 | AM37: =Inversion!D21*Supuestos!$D$66/12 -> 1149.1258
B38: Publicidad y comunidad (eventos, desayunos) | D38: =Supuestos!$D$67+Supuestos!$D$68 -> 650 | E38: =Supuestos!$D$67+Supuestos!$D$68 -> 650 | F38: =Supuestos!$D$67+Supuestos!$D$68 -> 650 | G38: =Supuestos!$D$67+Supuestos!$D$68 -> 650 | H38: =Supuestos!$D$67+Supuestos!$D$68 -> 650 | I38: =Supuestos!$D$67+Supuestos!$D$68 -> 650 | J38: =Supuestos!$D$67+Supuestos!$D$68 -> 650 | K38: =Supuestos!$D$67+Supuestos!$D$68 -> 650 | ... AM38: =Supuestos!$D$67+Supuestos!$D$68 -> 650
B39: Otros e imprevistos | D39: =SUM(D30:D38)*Supuestos!$D$69 -> 377.87406 | E39: =SUM(E30:E38)*Supuestos!$D$69 -> 377.87406 | F39: =SUM(F30:F38)*Supuestos!$D$69 -> 377.87406 | G39: =SUM(G30:G38)*Supuestos!$D$69 -> 377.87406 | H39: =SUM(H30:H38)*Supuestos!$D$69 -> 377.87406 | I39: =SUM(I30:I38)*Supuestos!$D$69 -> 377.87406 | J39: =SUM(J30:J38)*Supuestos!$D$69 -> 377.87406 | K39: =SUM(K30:K38)*Supuestos!$D$69 -> 377.87406 | ... AM39: =SUM(AM30:AM38)*Supuestos!$D$69 -> 377.87406
B40: Total costos fijos | D40: =SUM(D30:D39) -> 5101.2999 | E40: =SUM(E30:E39) -> 5101.2999 | F40: =SUM(F30:F39) -> 5101.2999 | G40: =SUM(G30:G39) -> 5101.2999 | H40: =SUM(H30:H39) -> 5101.2999 | I40: =SUM(I30:I39) -> 5101.2999 | J40: =SUM(J30:J39) -> 5101.2999 | K40: =SUM(K30:K39) -> 5101.2999 | ... AM40: =SUM(AM30:AM39) -> 5101.2999
B41: RESULTADO Y CAJA
B42: RESULTADO OPERATIVO (antes de Ganancias) | D42: =D28-D40 -> -5009.5993 | E42: =E28-E40 -> -4922.1002 | F42: =F28-F40 -> -4838.4838 | G42: =G28-G40 -> -4758.4558 | H42: =H28-H40 -> -4681.7448 | I42: =I28-I40 -> -4608.1002 | J42: =J28-J40 -> -4537.2907 | K42: =K28-K40 -> -4469.1028 | ... AM42: =AM28-AM40 -> -4343.6254
B43: Inversión inicial | C43: =-Inversion!D21 -> -275790.19 | D43: 0 | E43: 0 | F43: 0 | G43: 0 | H43: 0 | I43: 0 | J43: 0 | K43: 0 | L43: 0 | M43: 0 | N43: 0 | O43: 0 | P43: 0 | Q43: 0 | R43: 0 | S43: 0 | T43: 0 | U43: 0 | V43: 0 | W43: 0 | X43: 0 | Y43: 0 | Z43: 0 | AA43: 0 | AB43: 0 | AC43: 0 | AD43: 0 | AE43: 0 | AF43: 0 | AG43: 0 | AH43: 0 | AI43: 0 | AJ43: 0 | AK43: 0 | AL43: 0 | AM43: 0
B44: Flujo de caja del proyecto (casa propia, sin alquiler pagado) | C44: =C43 -> -275790.19 | D44: =D42+D43 -> -5009.5993 | E44: =E42+E43 -> -4922.1002 | F44: =F42+F43 -> -4838.4838 | G44: =G42+G43 -> -4758.4558 | H44: =H42+H43 -> -4681.7448 | I44: =I42+I43 -> -4608.1002 | J44: =J42+J43 -> -4537.2907 | K44: =K42+K43 -> -4469.1028 | ... AM44: =AM42+AM43 -> -4343.6254
B45: Flujo acumulado | C45: =C44 -> -275790.19 | D45: =C45+D44 -> -280799.79 | E45: =D45+E44 -> -285721.89 | F45: =E45+F44 -> -290560.37 | G45: =F45+G44 -> -295318.83 | H45: =G45+H44 -> -300000.57 | I45: =H45+I44 -> -304608.67 | J45: =I45+J44 -> -309145.96 | K45: =J45+K44 -> -313615.07 | ... AM45: =AL45+AM44 -> -434690.54
B46: Alquiler de la casa que se deja de cobrar (costo de oportunidad) | C46: =-Supuestos!$D$91*Supuestos!$D$10 -> 0 | D46: =-Supuestos!$D$91 -> 0 | E46: =-Supuestos!$D$91 -> 0 | F46: =-Supuestos!$D$91 -> 0 | G46: =-Supuestos!$D$91 -> 0 | H46: =-Supuestos!$D$91 -> 0 | I46: =-Supuestos!$D$91 -> 0 | J46: =-Supuestos!$D$91 -> 0 | K46: =-Supuestos!$D$91 -> 0 | ... AM46: =-Supuestos!$D$91 -> 0
B47: Resultado económico frente a alquilar la casa | C47: =C44+C46 -> -275790.19 | D47: =D44+D46 -> -5009.5993 | E47: =E44+E46 -> -4922.1002 | F47: =F44+F46 -> -4838.4838 | G47: =G44+G46 -> -4758.4558 | H47: =H44+H46 -> -4681.7448 | I47: =I44+I46 -> -4608.1002 | J47: =J44+J46 -> -4537.2907 | ... AM47: =AM44+AM46 -> -4343.6254
B48: Resultado económico acumulado | C48: =C47 -> -275790.19 | D48: =C48+D47 -> -280799.79 | E48: =D48+E47 -> -285721.89 | F48: =E48+F47 -> -290560.37 | G48: =F48+G47 -> -295318.83 | H48: =G48+H47 -> -300000.57 | I48: =H48+I47 -> -304608.67 | J48: =I48+J47 -> -309145.96 | K48: =J48+K47 -> -313615.07 | ... AM48: =AL48+AM47 -> -434690.54

Sheet Modelo_Base
A1: Modelo mensual a 36 meses · escenario Base (USD constantes)
A2: Miembros = fin de mes. Ingresos sin IVA. Flujo de caja con la casa propia (sin alquiler pagado); abajo, el resultado económico restando el alquiler que se deja de cobrar.
B3: Mes | C3: 0 | D3: 1 | E3: 2 | F3: 3 | G3: 4 | H3: 5 | I3: 6 | J3: 7 | K3: 8 | L3: 9 | M3: 10 | N3: 11 | O3: 12 | P3: 13 | Q3: 14 | R3: 15 | S3: 16 | T3: 17 | U3: 18 | V3: 19 | W3: 20 | X3: 21 | Y3: 22 | Z3: 23 | AA3: 24 | AB3: 25 | AC3: 26 | AD3: 27 | AE3: 28 | AF3: 29 | AG3: 30 | AH3: 31 | AI3: 32 | AJ3: 33 | AK3: 34 | AL3: 35 | AM3: 36
B4: MIEMBROS Y OCUPACIÓN
B5: Tope de miembros flex que entran en los puestos (pico) | D5: =(Supuestos!$E$12*Supuestos!$E$9/((Supuestos!$E$29*Supuestos!$E$21+Supuestos!$E$30*Supuestos!$E$22+Supuestos!$E$31*Supuestos!$E$23+Supuestos!$E$32*Supuestos!$E$24)*Supuestos!$E$17*Supuestos!$E$18)) -> 60.325567 | E5: =(Supuestos!$E$12*Supuestos!$E$9/((Supuestos!$E$29*Supuestos!$E$21+Supuestos!$E$30*Supuestos!$E$22+Supuestos!$E$31*Supuestos!$E$23+Supuestos!$E$32*Supuestos!$E$24)*Supuestos!$E$17*Supuestos!$E$18)) -> 60.325567 | F5: =(Supuestos!$E$12*Supuestos!$E$9/((Supuestos!$E$29*Supuestos!$E$21+Supuestos!$E$30*Supuestos!$E$22+Supuestos!$E$31*Supuestos!$E$23+Supuestos!$E$32*Supuestos!$E$24)*Supuestos!$E$17*Supuestos!$E$18)) -> 60.325567 | G5: =(Supuestos!$E$12*Supuestos!$E$9/((Supuestos!$E$29*Supuestos!$E$21+Supuestos!$E$30*Supuestos!$E$22+Supuestos!$E$31*Supuestos!$E$23+Supuestos!$E$32*Supuestos!$E$24)*Supuestos!$E$17*Supuestos!$E$18)) -> 60.325567 | H5: =(Supuestos!$E$12*Supuestos!$E$9/((Supuestos!$E$29*Supuestos!$E$21+Supuestos!$E$30*Supuestos!$E$22+Supuestos!$E$31*Supuestos!$E$23+Supuestos!$E$32*Supuestos!$E$24)*Supuestos!$E$17*Supuestos!$E$18)) -> 60.325567 | I5: =(Supuestos!$E$12*Supuestos!$E$9/((Supuestos!$E$29*Supuestos!$E$21+Supuestos!$E$30*Supuestos!$E$22+Supuestos!$E$31*Supuestos!$E$23+Supuestos!$E$32*Supuestos!$E$24)*Supuestos!$E$17*Supuestos!$E$18)) -> 60.325567 | J5: =(Supuestos!$E$12*Supuestos!$E$9/((Supuestos!$E$29*Supuestos!$E$21+Supuestos!$E$30*Supuestos!$E$22+Supuestos!$E$31*Supuestos!$E$23+Supuestos!$E$32*Supuestos!$E$24)*Supuestos!$E$17*Supuestos!$E$18)) -> 60.325567 | K5: =(Supuestos!$E$12*Supuestos!$E$9/((Supuestos!$E$29*Supuestos!$E$21+Supuestos!$E$30*Supuestos!$E$22+Supuestos!$E$31*Supuestos!$E$23+Supuestos!$E$32*Supuestos!$E$24)*Supuestos!$E$17*Supuestos!$E$18)) -> 60.325567 | ... AM5: =(Supuestos!$E$12*Supuestos!$E$9/((Supuestos!$E$29*Supuestos!$E$21+Supuestos!$E$30*Supuestos!$E$22+Supuestos!$E$31*Supuestos!$E$23+Supuestos!$E$32*Supuestos!$E$24)*Supuestos!$E$17*Supuestos!$E$18)) -> 60.325567
B6: Altas de miembros flex en el mes | D6: =IF(D$3<=6,Supuestos!$E$46,IF(D$3<=12,Supuestos!$E$47,Supuestos!$E$48)) -> 3 | E6: =IF(E$3<=6,Supuestos!$E$46,IF(E$3<=12,Supuestos!$E$47,Supuestos!$E$48)) -> 3 | F6: =IF(F$3<=6,Supuestos!$E$46,IF(F$3<=12,Supuestos!$E$47,Supuestos!$E$48)) -> 3 | G6: =IF(G$3<=6,Supuestos!$E$46,IF(G$3<=12,Supuestos!$E$47,Supuestos!$E$48)) -> 3 | H6: =IF(H$3<=6,Supuestos!$E$46,IF(H$3<=12,Supuestos!$E$47,Supuestos!$E$48)) -> 3 | I6: =IF(I$3<=6,Supuestos!$E$46,IF(I$3<=12,Supuestos!$E$47,Supuestos!$E$48)) -> 3 | J6: =IF(J$3<=6,Supuestos!$E$46,IF(J$3<=12,Supuestos!$E$47,Supuestos!$E$48)) -> 3 | K6: =IF(K$3<=6,Supuestos!$E$46,IF(K$3<=12,Supuestos!$E$47,Supuestos!$E$48)) -> 3 | ... AM6: =IF(AM$3<=6,Supuestos!$E$46,IF(AM$3<=12,Supuestos!$E$47,Supuestos!$E$48)) -> 2
B7: Miembros flex (fin de mes) | D7: =MIN(D5,Supuestos!$E$45*(1-Supuestos!$E$49)+D6) -> 7.7 | E7: =MIN(E5,D7*(1-Supuestos!$E$49)+E6) -> 10.238 | F7: =MIN(F5,E7*(1-Supuestos!$E$49)+F6) -> 12.62372 | G7: =MIN(G5,F7*(1-Supuestos!$E$49)+G6) -> 14.866297 | H7: =MIN(H5,G7*(1-Supuestos!$E$49)+H6) -> 16.974319 | I7: =MIN(I5,H7*(1-Supuestos!$E$49)+I6) -> 18.95586 | J7: =MIN(J5,I7*(1-Supuestos!$E$49)+J6) -> 20.818508 | K7: =MIN(K5,J7*(1-Supuestos!$E$49)+K6) -> 22.569398 | L7: =MIN(L5,K7*(1-Supuestos!$E$49)+L6) -> 24.215234 | ... AM7: =MIN(AM5,AL7*(1-Supuestos!$E$49)+AM6) -> 32.257515
B8: Bajas estimadas de flex en el mes | D8: =Supuestos!$E$45*Supuestos!$E$49 -> 0.3 | E8: =D7*Supuestos!$E$49 -> 0.462 | F8: =E7*Supuestos!$E$49 -> 0.61428 | G8: =F7*Supuestos!$E$49 -> 0.7574232 | H8: =G7*Supuestos!$E$49 -> 0.89197781 | I8: =H7*Supuestos!$E$49 -> 1.0184591 | J8: =I7*Supuestos!$E$49 -> 1.1373516 | K8: =J7*Supuestos!$E$49 -> 1.2491105 | L8: =K7*Supuestos!$E$49 -> 1.3541639 | ... AM8: =AL7*Supuestos!$E$49 -> 1.9313307
B9: Puestos fijos ocupados | D9: =MIN(Supuestos!$E$13,Supuestos!$E$50) -> 1 | E9: =MIN(Supuestos!$E$13,D9*(1-Supuestos!$E$51)+Supuestos!$E$50) -> 1.96 | F9: =MIN(Supuestos!$E$13,E9*(1-Supuestos!$E$51)+Supuestos!$E$50) -> 2.8816 | G9: =MIN(Supuestos!$E$13,F9*(1-Supuestos!$E$51)+Supuestos!$E$50) -> 3.766336 | H9: =MIN(Supuestos!$E$13,G9*(1-Supuestos!$E$51)+Supuestos!$E$50) -> 4.6156826 | I9: =MIN(Supuestos!$E$13,H9*(1-Supuestos!$E$51)+Supuestos!$E$50) -> 5.4310553 | J9: =MIN(Supuestos!$E$13,I9*(1-Supuestos!$E$51)+Supuestos!$E$50) -> 6 | K9: =MIN(Supuestos!$E$13,J9*(1-Supuestos!$E$51)+Supuestos!$E$50) -> 6 | L9: =MIN(Supuestos!$E$13,K9*(1-Supuestos!$E$51)+Supuestos!$E$50) -> 6 | ... AM9: =MIN(Supuestos!$E$13,AL9*(1-Supuestos!$E$51)+Supuestos!$E$50) -> 6
B10: Oficinas privadas ocupadas | D10: =Supuestos!$E$14*MIN(1,D$3/Supuestos!$E$43) -> 0.33333333 | E10: =Supuestos!$E$14*MIN(1,E$3/Supuestos!$E$43) -> 0.66666667 | F10: =Supuestos!$E$14*MIN(1,F$3/Supuestos!$E$43) -> 1 | G10: =Supuestos!$E$14*MIN(1,G$3/Supuestos!$E$43) -> 1.3333333 | H10: =Supuestos!$E$14*MIN(1,H$3/Supuestos!$E$43) -> 1.6666667 | I10: =Supuestos!$E$14*MIN(1,I$3/Supuestos!$E$43) -> 2 | J10: =Supuestos!$E$14*MIN(1,J$3/Supuestos!$E$43) -> 2 | K10: =Supuestos!$E$14*MIN(1,K$3/Supuestos!$E$43) -> 2 | ... AM10: =Supuestos!$E$14*MIN(1,AM$3/Supuestos!$E$43) -> 2
B11: Puestos-día usados por miembros flex | D11: =D7*(Supuestos!$E$29*Supuestos!$E$21+Supuestos!$E$30*Supuestos!$E$22+Supuestos!$E$31*Supuestos!$E$23+Supuestos!$E$32*Supuestos!$E$24)*Supuestos!$E$17 -> 74.228 | E11: =E7*(Supuestos!$E$29*Supuestos!$E$21+Supuestos!$E$30*Supuestos!$E$22+Supuestos!$E$31*Supuestos!$E$23+Supuestos!$E$32*Supuestos!$E$24)*Supuestos!$E$17 -> 98.69432 | F11: =F7*(Supuestos!$E$29*Supuestos!$E$21+Supuestos!$E$30*Supuestos!$E$22+Supuestos!$E$31*Supuestos!$E$23+Supuestos!$E$32*Supuestos!$E$24)*Supuestos!$E$17 -> 121.69266 | G11: =G7*(Supuestos!$E$29*Supuestos!$E$21+Supuestos!$E$30*Supuestos!$E$22+Supuestos!$E$31*Supuestos!$E$23+Supuestos!$E$32*Supuestos!$E$24)*Supuestos!$E$17 -> 143.3111 | H11: =H7*(Supuestos!$E$29*Supuestos!$E$21+Supuestos!$E$30*Supuestos!$E$22+Supuestos!$E$31*Supuestos!$E$23+Supuestos!$E$32*Supuestos!$E$24)*Supuestos!$E$17 -> 163.63244 | I11: =I7*(Supuestos!$E$29*Supuestos!$E$21+Supuestos!$E$30*Supuestos!$E$22+Supuestos!$E$31*Supuestos!$E$23+Supuestos!$E$32*Supuestos!$E$24)*Supuestos!$E$17 -> 182.73449 | J11: =J7*(Supuestos!$E$29*Supuestos!$E$21+Supuestos!$E$30*Supuestos!$E$22+Supuestos!$E$31*Supuestos!$E$23+Supuestos!$E$32*Supuestos!$E$24)*Supuestos!$E$17 -> 200.69042 | K11: =K7*(Supuestos!$E$29*Supuestos!$E$21+Supuestos!$E$30*Supuestos!$E$22+Supuestos!$E$31*Supuestos!$E$23+Supuestos!$E$32*Supuestos!$E$24)*Supuestos!$E$17 -> 217.56899 | ... AM11: =AM7*(Supuestos!$E$29*Supuestos!$E$21+Supuestos!$E$30*Supuestos!$E$22+Supuestos!$E$31*Supuestos!$E$23+Supuestos!$E$32*Supuestos!$E$24)*Supuestos!$E$17 -> 310.96244
B12: Ocupación promedio de puestos flex (días hábiles) | D12: =D11/(Supuestos!$E$12*Supuestos!$E$9) -> 0.098185185 | E12: =E11/(Supuestos!$E$12*Supuestos!$E$9) -> 0.13054804 | F12: =F11/(Supuestos!$E$12*Supuestos!$E$9) -> 0.16096913 | G12: =G11/(Supuestos!$E$12*Supuestos!$E$9) -> 0.18956495 | H12: =H11/(Supuestos!$E$12*Supuestos!$E$9) -> 0.21644502 | I12: =I11/(Supuestos!$E$12*Supuestos!$E$9) -> 0.24171229 | J12: =J11/(Supuestos!$E$12*Supuestos!$E$9) -> 0.26546352 | K12: =K11/(Supuestos!$E$12*Supuestos!$E$9) -> 0.28778968 | ... AM12: =AM11/(Supuestos!$E$12*Supuestos!$E$9) -> 0.41132598
B13: Puestos flex simultáneos en el pico (estimado) | D13: =D11/Supuestos!$E$9*Supuestos!$E$18 -> 4.5950667 | E13: =E11/Supuestos!$E$9*Supuestos!$E$18 -> 6.1096484 | F13: =F11/Supuestos!$E$9*Supuestos!$E$18 -> 7.5333552 | G13: =G11/Supuestos!$E$9*Supuestos!$E$18 -> 8.8716396 | H13: =H11/Supuestos!$E$9*Supuestos!$E$18 -> 10.129627 | I13: =I11/Supuestos!$E$9*Supuestos!$E$18 -> 11.312135 | J13: =J11/Supuestos!$E$9*Supuestos!$E$18 -> 12.423693 | K13: =K11/Supuestos!$E$9*Supuestos!$E$18 -> 13.468557 | ... AM13: =AM11/Supuestos!$E$9*Supuestos!$E$18 -> 19.250056
B14: INGRESOS (USD sin IVA)
B15: Membresías flex (días por mes / ilimitado) | D15: =D7*((Supuestos!$E$29*Supuestos!$E$25+Supuestos!$E$30*Supuestos!$E$26+Supuestos!$E$31*Supuestos!$E$27+Supuestos!$E$32*Supuestos!$E$28)*Supuestos!$E$37)*(1-Supuestos!$E$38)/(1+Supuestos!$E$7*Supuestos!$E$8)/Supuestos!$E$6 -> 361.69196 | E15: =E7*((Supuestos!$E$29*Supuestos!$E$25+Supuestos!$E$30*Supuestos!$E$26+Supuestos!$E$31*Supuestos!$E$27+Supuestos!$E$32*Supuestos!$E$28)*Supuestos!$E$37)*(1-Supuestos!$E$38)/(1+Supuestos!$E$7*Supuestos!$E$8)/Supuestos!$E$6 -> 480.90939 | F15: =F7*((Supuestos!$E$29*Supuestos!$E$25+Supuestos!$E$30*Supuestos!$E$26+Supuestos!$E$31*Supuestos!$E$27+Supuestos!$E$32*Supuestos!$E$28)*Supuestos!$E$37)*(1-Supuestos!$E$38)/(1+Supuestos!$E$7*Supuestos!$E$8)/Supuestos!$E$6 -> 592.97377 | G15: =G7*((Supuestos!$E$29*Supuestos!$E$25+Supuestos!$E$30*Supuestos!$E$26+Supuestos!$E$31*Supuestos!$E$27+Supuestos!$E$32*Supuestos!$E$28)*Supuestos!$E$37)*(1-Supuestos!$E$38)/(1+Supuestos!$E$7*Supuestos!$E$8)/Supuestos!$E$6 -> 698.31429 | H15: =H7*((Supuestos!$E$29*Supuestos!$E$25+Supuestos!$E$30*Supuestos!$E$26+Supuestos!$E$31*Supuestos!$E$27+Supuestos!$E$32*Supuestos!$E$28)*Supuestos!$E$37)*(1-Supuestos!$E$38)/(1+Supuestos!$E$7*Supuestos!$E$8)/Supuestos!$E$6 -> 797.33437 | I15: =I7*((Supuestos!$E$29*Supuestos!$E$25+Supuestos!$E$30*Supuestos!$E$26+Supuestos!$E$31*Supuestos!$E$27+Supuestos!$E$32*Supuestos!$E$28)*Supuestos!$E$37)*(1-Supuestos!$E$38)/(1+Supuestos!$E$7*Supuestos!$E$8)/Supuestos!$E$6 -> 890.41326 | J15: =J7*((Supuestos!$E$29*Supuestos!$E$25+Supuestos!$E$30*Supuestos!$E$26+Supuestos!$E$31*Supuestos!$E$27+Supuestos!$E$32*Supuestos!$E$28)*Supuestos!$E$37)*(1-Supuestos!$E$38)/(1+Supuestos!$E$7*Supuestos!$E$8)/Supuestos!$E$6 -> 977.9074 | K15: =K7*((Supuestos!$E$29*Supuestos!$E$25+Supuestos!$E$30*Supuestos!$E$26+Supuestos!$E$31*Supuestos!$E$27+Supuestos!$E$32*Supuestos!$E$28)*Supuestos!$E$37)*(1-Supuestos!$E$38)/(1+Supuestos!$E$7*Supuestos!$E$8)/Supuestos!$E$6 -> 1060.1519 | ... AM15: =AM7*((Supuestos!$E$29*Supuestos!$E$25+Supuestos!$E$30*Supuestos!$E$26+Supuestos!$E$31*Supuestos!$E$27+Supuestos!$E$32*Supuestos!$E$28)*Supuestos!$E$37)*(1-Supuestos!$E$38)/(1+Supuestos!$E$7*Supuestos!$E$8)/Supuestos!$E$6 -> 1515.2316
B16: Puestos fijos | D16: =D9*Supuestos!$E$33*Supuestos!$E$37*(1-Supuestos!$E$38)/(1+Supuestos!$E$7*Supuestos!$E$8)/Supuestos!$E$6 -> 58.137317 | E16: =E9*Supuestos!$E$33*Supuestos!$E$37*(1-Supuestos!$E$38)/(1+Supuestos!$E$7*Supuestos!$E$8)/Supuestos!$E$6 -> 113.94914 | F16: =F9*Supuestos!$E$33*Supuestos!$E$37*(1-Supuestos!$E$38)/(1+Supuestos!$E$7*Supuestos!$E$8)/Supuestos!$E$6 -> 167.52849 | G16: =G9*Supuestos!$E$33*Supuestos!$E$37*(1-Supuestos!$E$38)/(1+Supuestos!$E$7*Supuestos!$E$8)/Supuestos!$E$6 -> 218.96467 | H16: =H9*Supuestos!$E$33*Supuestos!$E$37*(1-Supuestos!$E$38)/(1+Supuestos!$E$7*Supuestos!$E$8)/Supuestos!$E$6 -> 268.3434 | I16: =I9*Supuestos!$E$33*Supuestos!$E$37*(1-Supuestos!$E$38)/(1+Supuestos!$E$7*Supuestos!$E$8)/Supuestos!$E$6 -> 315.74698 | J16: =J9*Supuestos!$E$33*Supuestos!$E$37*(1-Supuestos!$E$38)/(1+Supuestos!$E$7*Supuestos!$E$8)/Supuestos!$E$6 -> 348.8239 | K16: =K9*Supuestos!$E$33*Supuestos!$E$37*(1-Supuestos!$E$38)/(1+Supuestos!$E$7*Supuestos!$E$8)/Supuestos!$E$6 -> 348.8239 | ... AM16: =AM9*Supuestos!$E$33*Supuestos!$E$37*(1-Supuestos!$E$38)/(1+Supuestos!$E$7*Supuestos!$E$8)/Supuestos!$E$6 -> 348.8239
B17: Oficinas privadas (complemento) | D17: =D10*Supuestos!$E$34*Supuestos!$E$37*(1-Supuestos!$E$38)/(1+Supuestos!$E$7*Supuestos!$E$8)/Supuestos!$E$6 -> 78.830261 | E17: =E10*Supuestos!$E$34*Supuestos!$E$37*(1-Supuestos!$E$38)/(1+Supuestos!$E$7*Supuestos!$E$8)/Supuestos!$E$6 -> 157.66052 | F17: =F10*Supuestos!$E$34*Supuestos!$E$37*(1-Supuestos!$E$38)/(1+Supuestos!$E$7*Supuestos!$E$8)/Supuestos!$E$6 -> 236.49078 | G17: =G10*Supuestos!$E$34*Supuestos!$E$37*(1-Supuestos!$E$38)/(1+Supuestos!$E$7*Supuestos!$E$8)/Supuestos!$E$6 -> 315.32104 | H17: =H10*Supuestos!$E$34*Supuestos!$E$37*(1-Supuestos!$E$38)/(1+Supuestos!$E$7*Supuestos!$E$8)/Supuestos!$E$6 -> 394.1513 | I17: =I10*Supuestos!$E$34*Supuestos!$E$37*(1-Supuestos!$E$38)/(1+Supuestos!$E$7*Supuestos!$E$8)/Supuestos!$E$6 -> 472.98156 | J17: =J10*Supuestos!$E$34*Supuestos!$E$37*(1-Supuestos!$E$38)/(1+Supuestos!$E$7*Supuestos!$E$8)/Supuestos!$E$6 -> 472.98156 | K17: =K10*Supuestos!$E$34*Supuestos!$E$37*(1-Supuestos!$E$38)/(1+Supuestos!$E$7*Supuestos!$E$8)/Supuestos!$E$6 -> 472.98156 | ... AM17: =AM10*Supuestos!$E$34*Supuestos!$E$37*(1-Supuestos!$E$38)/(1+Supuestos!$E$7*Supuestos!$E$8)/Supuestos!$E$6 -> 472.98156
B18: Pases diarios | D18: =Supuestos!$E$39*MIN(1,D$3/Supuestos!$E$42)*Supuestos!$E$35*Supuestos!$E$37/(1+Supuestos!$E$7*Supuestos!$E$8)/Supuestos!$E$6 -> 28.225142 | E18: =Supuestos!$E$39*MIN(1,E$3/Supuestos!$E$42)*Supuestos!$E$35*Supuestos!$E$37/(1+Supuestos!$E$7*Supuestos!$E$8)/Supuestos!$E$6 -> 56.450284 | F18: =Supuestos!$E$39*MIN(1,F$3/Supuestos!$E$42)*Supuestos!$E$35*Supuestos!$E$37/(1+Supuestos!$E$7*Supuestos!$E$8)/Supuestos!$E$6 -> 84.675426 | G18: =Supuestos!$E$39*MIN(1,G$3/Supuestos!$E$42)*Supuestos!$E$35*Supuestos!$E$37/(1+Supuestos!$E$7*Supuestos!$E$8)/Supuestos!$E$6 -> 112.90057 | H18: =Supuestos!$E$39*MIN(1,H$3/Supuestos!$E$42)*Supuestos!$E$35*Supuestos!$E$37/(1+Supuestos!$E$7*Supuestos!$E$8)/Supuestos!$E$6 -> 141.12571 | I18: =Supuestos!$E$39*MIN(1,I$3/Supuestos!$E$42)*Supuestos!$E$35*Supuestos!$E$37/(1+Supuestos!$E$7*Supuestos!$E$8)/Supuestos!$E$6 -> 169.35085 | J18: =Supuestos!$E$39*MIN(1,J$3/Supuestos!$E$42)*Supuestos!$E$35*Supuestos!$E$37/(1+Supuestos!$E$7*Supuestos!$E$8)/Supuestos!$E$6 -> 197.57599 | K18: =Supuestos!$E$39*MIN(1,K$3/Supuestos!$E$42)*Supuestos!$E$35*Supuestos!$E$37/(1+Supuestos!$E$7*Supuestos!$E$8)/Supuestos!$E$6 -> 225.80113 | ... AM18: =Supuestos!$E$39*MIN(1,AM$3/Supuestos!$E$42)*Supuestos!$E$35*Supuestos!$E$37/(1+Supuestos!$E$7*Supuestos!$E$8)/Supuestos!$E$6 -> 254.02628
B19: Salas por hora a externos | D19: =Supuestos!$E$40*MIN(1,D$3/Supuestos!$E$42)*Supuestos!$E$36*Supuestos!$E$37/(1+Supuestos!$E$7*Supuestos!$E$8)/Supuestos!$E$6 -> 15.304561 | E19: =Supuestos!$E$40*MIN(1,E$3/Supuestos!$E$42)*Supuestos!$E$36*Supuestos!$E$37/(1+Supuestos!$E$7*Supuestos!$E$8)/Supuestos!$E$6 -> 30.609122 | F19: =Supuestos!$E$40*MIN(1,F$3/Supuestos!$E$42)*Supuestos!$E$36*Supuestos!$E$37/(1+Supuestos!$E$7*Supuestos!$E$8)/Supuestos!$E$6 -> 45.913682 | G19: =Supuestos!$E$40*MIN(1,G$3/Supuestos!$E$42)*Supuestos!$E$36*Supuestos!$E$37/(1+Supuestos!$E$7*Supuestos!$E$8)/Supuestos!$E$6 -> 61.218243 | H19: =Supuestos!$E$40*MIN(1,H$3/Supuestos!$E$42)*Supuestos!$E$36*Supuestos!$E$37/(1+Supuestos!$E$7*Supuestos!$E$8)/Supuestos!$E$6 -> 76.522804 | I19: =Supuestos!$E$40*MIN(1,I$3/Supuestos!$E$42)*Supuestos!$E$36*Supuestos!$E$37/(1+Supuestos!$E$7*Supuestos!$E$8)/Supuestos!$E$6 -> 91.827365 | J19: =Supuestos!$E$40*MIN(1,J$3/Supuestos!$E$42)*Supuestos!$E$36*Supuestos!$E$37/(1+Supuestos!$E$7*Supuestos!$E$8)/Supuestos!$E$6 -> 107.13193 | K19: =Supuestos!$E$40*MIN(1,K$3/Supuestos!$E$42)*Supuestos!$E$36*Supuestos!$E$37/(1+Supuestos!$E$7*Supuestos!$E$8)/Supuestos!$E$6 -> 122.43649 | ... AM19: =Supuestos!$E$40*MIN(1,AM$3/Supuestos!$E$42)*Supuestos!$E$36*Supuestos!$E$37/(1+Supuestos!$E$7*Supuestos!$E$8)/Supuestos!$E$6 -> 137.74105
B20: Otros (domicilio comercial, eventos) | D20: =Supuestos!$E$41*MIN(1,D$3/Supuestos!$E$42) -> 11.111111 | E20: =Supuestos!$E$41*MIN(1,E$3/Supuestos!$E$42) -> 22.222222 | F20: =Supuestos!$E$41*MIN(1,F$3/Supuestos!$E$42) -> 33.333333 | G20: =Supuestos!$E$41*MIN(1,G$3/Supuestos!$E$42) -> 44.444444 | H20: =Supuestos!$E$41*MIN(1,H$3/Supuestos!$E$42) -> 55.555556 | I20: =Supuestos!$E$41*MIN(1,I$3/Supuestos!$E$42) -> 66.666667 | J20: =Supuestos!$E$41*MIN(1,J$3/Supuestos!$E$42) -> 77.777778 | K20: =Supuestos!$E$41*MIN(1,K$3/Supuestos!$E$42) -> 88.888889 | ... AM20: =Supuestos!$E$41*MIN(1,AM$3/Supuestos!$E$42) -> 100
B21: INGRESOS TOTALES | D21: =SUM(D15:D20) -> 553.30035 | E21: =SUM(E15:E20) -> 861.80068 | F21: =SUM(F15:F20) -> 1160.9155 | G21: =SUM(G15:G20) -> 1451.1633 | H21: =SUM(H15:H20) -> 1733.0331 | I21: =SUM(I15:I20) -> 2006.9867 | J21: =SUM(J15:J20) -> 2182.1986 | K21: =SUM(K15:K20) -> 2319.0839 | ... AM21: =SUM(AM15:AM20) -> 2828.8044
B22: COSTOS VARIABLES
B23: Café, té, agua y consumibles | D23: =(D11+D9*Supuestos!$E$9*Supuestos!$E$19+(D10*Supuestos!$E$15*Supuestos!$E$9*Supuestos!$E$19)+Supuestos!$E$39*MIN(1,D$3/Supuestos!$E$42))*Supuestos!$E$53 -> 90.49068 | E23: =(E11+E9*Supuestos!$E$9*Supuestos!$E$19+(E10*Supuestos!$E$15*Supuestos!$E$9*Supuestos!$E$19)+Supuestos!$E$39*MIN(1,E$3/Supuestos!$E$42))*Supuestos!$E$53 -> 140.13008 | F23: =(F11+F9*Supuestos!$E$9*Supuestos!$E$19+(F10*Supuestos!$E$15*Supuestos!$E$9*Supuestos!$E$19)+Supuestos!$E$39*MIN(1,F$3/Supuestos!$E$42))*Supuestos!$E$53 -> 188.05787 | G23: =(G11+G9*Supuestos!$E$9*Supuestos!$E$19+(G10*Supuestos!$E$15*Supuestos!$E$9*Supuestos!$E$19)+Supuestos!$E$39*MIN(1,G$3/Supuestos!$E$42))*Supuestos!$E$53 -> 234.36629 | H23: =(H11+H9*Supuestos!$E$9*Supuestos!$E$19+(H10*Supuestos!$E$15*Supuestos!$E$9*Supuestos!$E$19)+Supuestos!$E$39*MIN(1,H$3/Supuestos!$E$42))*Supuestos!$E$53 -> 279.14248 | I23: =(I11+I9*Supuestos!$E$9*Supuestos!$E$19+(I10*Supuestos!$E$15*Supuestos!$E$9*Supuestos!$E$19)+Supuestos!$E$39*MIN(1,I$3/Supuestos!$E$42))*Supuestos!$E$53 -> 322.46874 | J23: =(J11+J9*Supuestos!$E$9*Supuestos!$E$19+(J10*Supuestos!$E$15*Supuestos!$E$9*Supuestos!$E$19)+Supuestos!$E$39*MIN(1,J$3/Supuestos!$E$42))*Supuestos!$E$53 -> 347.90524 | K23: =(K11+K9*Supuestos!$E$9*Supuestos!$E$19+(K10*Supuestos!$E$15*Supuestos!$E$9*Supuestos!$E$19)+Supuestos!$E$39*MIN(1,K$3/Supuestos!$E$42))*Supuestos!$E$53 -> 364.72689 | ... AM23: =(AM11+AM9*Supuestos!$E$9*Supuestos!$E$19+(AM10*Supuestos!$E$15*Supuestos!$E$9*Supuestos!$E$19)+Supuestos!$E$39*MIN(1,AM$3/Supuestos!$E$42))*Supuestos!$E$53 -> 443.52558
B24: Comisiones de cobro | D24: =D21*(1+Supuestos!$E$7*Supuestos!$E$8)*Supuestos!$E$54 -> 23.097523 | E24: =E21*(1+Supuestos!$E$7*Supuestos!$E$8)*Supuestos!$E$54 -> 35.975869 | F24: =F21*(1+Supuestos!$E$7*Supuestos!$E$8)*Supuestos!$E$54 -> 48.462417 | G24: =G21*(1+Supuestos!$E$7*Supuestos!$E$8)*Supuestos!$E$54 -> 60.57881 | H24: =H21*(1+Supuestos!$E$7*Supuestos!$E$8)*Supuestos!$E$54 -> 72.345469 | I24: =I21*(1+Supuestos!$E$7*Supuestos!$E$8)*Supuestos!$E$54 -> 83.781659 | J24: =J21*(1+Supuestos!$E$7*Supuestos!$E$8)*Supuestos!$E$54 -> 91.095879 | K24: =K21*(1+Supuestos!$E$7*Supuestos!$E$8)*Supuestos!$E$54 -> 96.810157 | ... AM24: =AM21*(1+Supuestos!$E$7*Supuestos!$E$8)*Supuestos!$E$54 -> 118.08844
B25: Ingresos Brutos | D25: =D21*Supuestos!$E$55 -> 16.59901 | E25: =E21*Supuestos!$E$55 -> 25.85402 | F25: =F21*Supuestos!$E$55 -> 34.827464 | G25: =G21*Supuestos!$E$55 -> 43.534898 | H25: =H21*Supuestos!$E$55 -> 51.990994 | I25: =I21*Supuestos!$E$55 -> 60.209601 | J25: =J21*Supuestos!$E$55 -> 65.465957 | K25: =K21*Supuestos!$E$55 -> 69.572516 | ... AM25: =AM21*Supuestos!$E$55 -> 84.864133
B26: Impuesto a los débitos y créditos (aprox.) | D26: =D21*(1+Supuestos!$E$7*Supuestos!$E$8)*Supuestos!$E$56 -> 8.0339211 | E26: =E21*(1+Supuestos!$E$7*Supuestos!$E$8)*Supuestos!$E$56 -> 12.513346 | F26: =F21*(1+Supuestos!$E$7*Supuestos!$E$8)*Supuestos!$E$56 -> 16.856493 | G26: =G21*(1+Supuestos!$E$7*Supuestos!$E$8)*Supuestos!$E$56 -> 21.07089 | H26: =H21*(1+Supuestos!$E$7*Supuestos!$E$8)*Supuestos!$E$56 -> 25.163641 | I26: =I21*(1+Supuestos!$E$7*Supuestos!$E$8)*Supuestos!$E$56 -> 29.141447 | J26: =J21*(1+Supuestos!$E$7*Supuestos!$E$8)*Supuestos!$E$56 -> 31.685523 | K26: =K21*(1+Supuestos!$E$7*Supuestos!$E$8)*Supuestos!$E$56 -> 33.673098 | ... AM26: =AM21*(1+Supuestos!$E$7*Supuestos!$E$8)*Supuestos!$E$56 -> 41.07424
B27: Total costos variables | D27: =SUM(D23:D26) -> 138.22113 | E27: =SUM(E23:E26) -> 214.47331 | F27: =SUM(F23:F26) -> 288.20424 | G27: =SUM(G23:G26) -> 359.55089 | H27: =SUM(H23:H26) -> 428.64259 | I27: =SUM(I23:I26) -> 495.60144 | J27: =SUM(J23:J26) -> 536.1526 | K27: =SUM(K23:K26) -> 564.78266 | ... AM27: =SUM(AM23:AM26) -> 687.55239
B28: MARGEN DE CONTRIBUCIÓN | D28: =D21-D27 -> 415.07921 | E28: =E21-E27 -> 647.32736 | F28: =F21-F27 -> 872.71124 | G28: =G21-G27 -> 1091.6124 | H28: =H21-H27 -> 1304.3906 | I28: =I21-I27 -> 1511.3852 | J28: =J21-J27 -> 1646.046 | K28: =K21-K27 -> 1754.3012 | ... AM28: =AM21-AM27 -> 2141.252
B29: COSTOS FIJOS MENSUALES
B30: Personal (recepción / comunidad), con cargas | D30: =Supuestos!$E$58*Supuestos!$E$59 -> 1657.2 | E30: =Supuestos!$E$58*Supuestos!$E$59 -> 1657.2 | F30: =Supuestos!$E$58*Supuestos!$E$59 -> 1657.2 | G30: =Supuestos!$E$58*Supuestos!$E$59 -> 1657.2 | H30: =Supuestos!$E$58*Supuestos!$E$59 -> 1657.2 | I30: =Supuestos!$E$58*Supuestos!$E$59 -> 1657.2 | J30: =Supuestos!$E$58*Supuestos!$E$59 -> 1657.2 | K30: =Supuestos!$E$58*Supuestos!$E$59 -> 1657.2 | ... AM30: =Supuestos!$E$58*Supuestos!$E$59 -> 1657.2
B31: Limpieza | D31: =Supuestos!$E$60 -> 376.9 | E31: =Supuestos!$E$60 -> 376.9 | F31: =Supuestos!$E$60 -> 376.9 | G31: =Supuestos!$E$60 -> 376.9 | H31: =Supuestos!$E$60 -> 376.9 | I31: =Supuestos!$E$60 -> 376.9 | J31: =Supuestos!$E$60 -> 376.9 | K31: =Supuestos!$E$60 -> 376.9 | ... AM31: =Supuestos!$E$60 -> 376.9
B32: Internet principal + respaldo | D32: =Supuestos!$E$61 -> 55.8 | E32: =Supuestos!$E$61 -> 55.8 | F32: =Supuestos!$E$61 -> 55.8 | G32: =Supuestos!$E$61 -> 55.8 | H32: =Supuestos!$E$61 -> 55.8 | I32: =Supuestos!$E$61 -> 55.8 | J32: =Supuestos!$E$61 -> 55.8 | K32: =Supuestos!$E$61 -> 55.8 | ... AM32: =Supuestos!$E$61 -> 55.8
B33: Electricidad, gas y agua | D33: =Supuestos!$E$62 -> 27.1 | E33: =Supuestos!$E$62 -> 27.1 | F33: =Supuestos!$E$62 -> 27.1 | G33: =Supuestos!$E$62 -> 27.1 | H33: =Supuestos!$E$62 -> 27.1 | I33: =Supuestos!$E$62 -> 27.1 | J33: =Supuestos!$E$62 -> 27.1 | K33: =Supuestos!$E$62 -> 27.1 | ... AM33: =Supuestos!$E$62 -> 27.1
B34: Seguros | D34: =Supuestos!$E$63 -> 112.2 | E34: =Supuestos!$E$63 -> 112.2 | F34: =Supuestos!$E$63 -> 112.2 | G34: =Supuestos!$E$63 -> 112.2 | H34: =Supuestos!$E$63 -> 112.2 | I34: =Supuestos!$E$63 -> 112.2 | J34: =Supuestos!$E$63 -> 112.2 | K34: =Supuestos!$E$63 -> 112.2 | ... AM34: =Supuestos!$E$63 -> 112.2
B35: Software de gestión y reservas | D35: =Supuestos!$E$64 -> 129 | E35: =Supuestos!$E$64 -> 129 | F35: =Supuestos!$E$64 -> 129 | G35: =Supuestos!$E$64 -> 129 | H35: =Supuestos!$E$64 -> 129 | I35: =Supuestos!$E$64 -> 129 | J35: =Supuestos!$E$64 -> 129 | K35: =Supuestos!$E$64 -> 129 | ... AM35: =Supuestos!$E$64 -> 129
B36: Contador y administración | D36: =Supuestos!$E$65 -> 0 | E36: =Supuestos!$E$65 -> 0 | F36: =Supuestos!$E$65 -> 0 | G36: =Supuestos!$E$65 -> 0 | H36: =Supuestos!$E$65 -> 0 | I36: =Supuestos!$E$65 -> 0 | J36: =Supuestos!$E$65 -> 0 | K36: =Supuestos!$E$65 -> 0 | ... AM36: =Supuestos!$E$65 -> 0
B37: Mantenimiento y reposición | D37: =Inversion!E21*Supuestos!$E$66/12 -> 658.41648 | E37: =Inversion!E21*Supuestos!$E$66/12 -> 658.41648 | F37: =Inversion!E21*Supuestos!$E$66/12 -> 658.41648 | G37: =Inversion!E21*Supuestos!$E$66/12 -> 658.41648 | H37: =Inversion!E21*Supuestos!$E$66/12 -> 658.41648 | I37: =Inversion!E21*Supuestos!$E$66/12 -> 658.41648 | J37: =Inversion!E21*Supuestos!$E$66/12 -> 658.41648 | K37: =Inversion!E21*Supuestos!$E$66/12 -> 658.41648 | L37: =Inversion!E21*Supuestos!$E$66/12 -> 658.41648 | M37: =Inversion!E21*Supuestos!$E$66/12 -> 658.41648 | N37: =Inversion!E21*Supuestos!$E$66/12 -> 658.41648 | O37: =Inversion!E21*Supuestos!$E$66/12 -> 658.41648 | P37: =Inversion!E21*Supuestos!$E$66/12 -> 658.41648 | Q37: =Inversion!E21*Supuestos!$E$66/12 -> 658.41648 | R37: =Inversion!E21*Supuestos!$E$66/12 -> 658.41648 | S37: =Inversion!E21*Supuestos!$E$66/12 -> 658.41648 | T37: =Inversion!E21*Supuestos!$E$66/12 -> 658.41648 | U37: =Inversion!E21*Supuestos!$E$66/12 -> 658.41648 | V37: =Inversion!E21*Supuestos!$E$66/12 -> 658.41648 | W37: =Inversion!E21*Supuestos!$E$66/12 -> 658.41648 | X37: =Inversion!E21*Supuestos!$E$66/12 -> 658.41648 | Y37: =Inversion!E21*Supuestos!$E$66/12 -> 658.41648 | Z37: =Inversion!E21*Supuestos!$E$66/12 -> 658.41648 | AA37: =Inversion!E21*Supuestos!$E$66/12 -> 658.41648 | AB37: =Inversion!E21*Supuestos!$E$66/12 -> 658.41648 | AC37: =Inversion!E21*Supuestos!$E$66/12 -> 658.41648 | AD37: =Inversion!E21*Supuestos!$E$66/12 -> 658.41648 | AE37: =Inversion!E21*Supuestos!$E$66/12 -> 658.41648 | AF37: =Inversion!E21*Supuestos!$E$66/12 -> 658.41648 | AG37: =Inversion!E21*Supuestos!$E$66/12 -> 658.41648 | AH37: =Inversion!E21*Supuestos!$E$66/12 -> 658.41648 | AI37: =Inversion!E21*Supuestos!$E$66/12 -> 658.41648 | AJ37: =Inversion!E21*Supuestos!$E$66/12 -> 658.41648 | AK37: =Inversion!E21*Supuestos!$E$66/12 -> 658.41648 | AL37: =Inversion!E21*Supuestos!$E$66/12 -> 658.41648 | AM37: =Inversion!E21*Supuestos!$E$66/12 -> 658.41648
B38: Publicidad y comunidad (eventos, desayunos) | D38: =Supuestos!$E$67+Supuestos!$E$68 -> 550 | E38: =Supuestos!$E$67+Supuestos!$E$68 -> 550 | F38: =Supuestos!$E$67+Supuestos!$E$68 -> 550 | G38: =Supuestos!$E$67+Supuestos!$E$68 -> 550 | H38: =Supuestos!$E$67+Supuestos!$E$68 -> 550 | I38: =Supuestos!$E$67+Supuestos!$E$68 -> 550 | J38: =Supuestos!$E$67+Supuestos!$E$68 -> 550 | K38: =Supuestos!$E$67+Supuestos!$E$68 -> 550 | ... AM38: =Supuestos!$E$67+Supuestos!$E$68 -> 550
B39: Otros e imprevistos | D39: =SUM(D30:D38)*Supuestos!$E$69 -> 178.33082 | E39: =SUM(E30:E38)*Supuestos!$E$69 -> 178.33082 | F39: =SUM(F30:F38)*Supuestos!$E$69 -> 178.33082 | G39: =SUM(G30:G38)*Supuestos!$E$69 -> 178.33082 | H39: =SUM(H30:H38)*Supuestos!$E$69 -> 178.33082 | I39: =SUM(I30:I38)*Supuestos!$E$69 -> 178.33082 | J39: =SUM(J30:J38)*Supuestos!$E$69 -> 178.33082 | K39: =SUM(K30:K38)*Supuestos!$E$69 -> 178.33082 | ... AM39: =SUM(AM30:AM38)*Supuestos!$E$69 -> 178.33082
B40: Total costos fijos | D40: =SUM(D30:D39) -> 3744.9473 | E40: =SUM(E30:E39) -> 3744.9473 | F40: =SUM(F30:F39) -> 3744.9473 | G40: =SUM(G30:G39) -> 3744.9473 | H40: =SUM(H30:H39) -> 3744.9473 | I40: =SUM(I30:I39) -> 3744.9473 | J40: =SUM(J30:J39) -> 3744.9473 | K40: =SUM(K30:K39) -> 3744.9473 | ... AM40: =SUM(AM30:AM39) -> 3744.9473
B41: RESULTADO Y CAJA
B42: RESULTADO OPERATIVO (antes de Ganancias) | D42: =D28-D40 -> -3329.8681 | E42: =E28-E40 -> -3097.6199 | F42: =F28-F40 -> -2872.2361 | G42: =G28-G40 -> -2653.3349 | H42: =H28-H40 -> -2440.5567 | I42: =I28-I40 -> -2233.5621 | J42: =J28-J40 -> -2098.9013 | K42: =K28-K40 -> -1990.6461 | ... AM42: =AM28-AM40 -> -1603.6953
B43: Inversión inicial | C43: =-Inversion!E21 -> -197524.94 | D43: 0 | E43: 0 | F43: 0 | G43: 0 | H43: 0 | I43: 0 | J43: 0 | K43: 0 | L43: 0 | M43: 0 | N43: 0 | O43: 0 | P43: 0 | Q43: 0 | R43: 0 | S43: 0 | T43: 0 | U43: 0 | V43: 0 | W43: 0 | X43: 0 | Y43: 0 | Z43: 0 | AA43: 0 | AB43: 0 | AC43: 0 | AD43: 0 | AE43: 0 | AF43: 0 | AG43: 0 | AH43: 0 | AI43: 0 | AJ43: 0 | AK43: 0 | AL43: 0 | AM43: 0
B44: Flujo de caja del proyecto (casa propia, sin alquiler pagado) | C44: =C43 -> -197524.94 | D44: =D42+D43 -> -3329.8681 | E44: =E42+E43 -> -3097.6199 | F44: =F42+F43 -> -2872.2361 | G44: =G42+G43 -> -2653.3349 | H44: =H42+H43 -> -2440.5567 | I44: =I42+I43 -> -2233.5621 | J44: =J42+J43 -> -2098.9013 | K44: =K42+K43 -> -1990.6461 | ... AM44: =AM42+AM43 -> -1603.6953
B45: Flujo acumulado | C45: =C44 -> -197524.94 | D45: =C45+D44 -> -200854.81 | E45: =D45+E44 -> -203952.43 | F45: =E45+F44 -> -206824.67 | G45: =F45+G44 -> -209478 | H45: =G45+H44 -> -211918.56 | I45: =H45+I44 -> -214152.12 | J45: =I45+J44 -> -216251.02 | K45: =J45+K44 -> -218241.67 | ... AM45: =AL45+AM44 -> -265076
B46: Alquiler de la casa que se deja de cobrar (costo de oportunidad) | C46: =-Supuestos!$E$91*Supuestos!$E$10 -> 0 | D46: =-Supuestos!$E$91 -> 0 | E46: =-Supuestos!$E$91 -> 0 | F46: =-Supuestos!$E$91 -> 0 | G46: =-Supuestos!$E$91 -> 0 | H46: =-Supuestos!$E$91 -> 0 | I46: =-Supuestos!$E$91 -> 0 | J46: =-Supuestos!$E$91 -> 0 | K46: =-Supuestos!$E$91 -> 0 | ... AM46: =-Supuestos!$E$91 -> 0
B47: Resultado económico frente a alquilar la casa | C47: =C44+C46 -> -197524.94 | D47: =D44+D46 -> -3329.8681 | E47: =E44+E46 -> -3097.6199 | F47: =F44+F46 -> -2872.2361 | G47: =G44+G46 -> -2653.3349 | H47: =H44+H46 -> -2440.5567 | I47: =I44+I46 -> -2233.5621 | J47: =J44+J46 -> -2098.9013 | ... AM47: =AM44+AM46 -> -1603.6953
B48: Resultado económico acumulado | C48: =C47 -> -197524.94 | D48: =C48+D47 -> -200854.81 | E48: =D48+E47 -> -203952.43 | F48: =E48+F47 -> -206824.67 | G48: =F48+G47 -> -209478 | H48: =G48+H47 -> -211918.56 | I48: =H48+I47 -> -214152.12 | J48: =I48+J47 -> -216251.02 | K48: =J48+K47 -> -218241.67 | ... AM48: =AL48+AM47 -> -265076

Sheet Modelo_Favorable
A1: Modelo mensual a 36 meses · escenario Favorable (USD constantes)
A2: Miembros = fin de mes. Ingresos sin IVA. Flujo de caja con la casa propia (sin alquiler pagado); abajo, el resultado económico restando el alquiler que se deja de cobrar.
B3: Mes | C3: 0 | D3: 1 | E3: 2 | F3: 3 | G3: 4 | H3: 5 | I3: 6 | J3: 7 | K3: 8 | L3: 9 | M3: 10 | N3: 11 | O3: 12 | P3: 13 | Q3: 14 | R3: 15 | S3: 16 | T3: 17 | U3: 18 | V3: 19 | W3: 20 | X3: 21 | Y3: 22 | Z3: 23 | AA3: 24 | AB3: 25 | AC3: 26 | AD3: 27 | AE3: 28 | AF3: 29 | AG3: 30 | AH3: 31 | AI3: 32 | AJ3: 33 | AK3: 34 | AL3: 35 | AM3: 36
B4: MIEMBROS Y OCUPACIÓN
B5: Tope de miembros flex que entran en los puestos (pico) | D5: =(Supuestos!$F$12*Supuestos!$F$9/((Supuestos!$F$29*Supuestos!$F$21+Supuestos!$F$30*Supuestos!$F$22+Supuestos!$F$31*Supuestos!$F$23+Supuestos!$F$32*Supuestos!$F$24)*Supuestos!$F$17*Supuestos!$F$18)) -> 78.074689 | E5: =(Supuestos!$F$12*Supuestos!$F$9/((Supuestos!$F$29*Supuestos!$F$21+Supuestos!$F$30*Supuestos!$F$22+Supuestos!$F$31*Supuestos!$F$23+Supuestos!$F$32*Supuestos!$F$24)*Supuestos!$F$17*Supuestos!$F$18)) -> 78.074689 | F5: =(Supuestos!$F$12*Supuestos!$F$9/((Supuestos!$F$29*Supuestos!$F$21+Supuestos!$F$30*Supuestos!$F$22+Supuestos!$F$31*Supuestos!$F$23+Supuestos!$F$32*Supuestos!$F$24)*Supuestos!$F$17*Supuestos!$F$18)) -> 78.074689 | G5: =(Supuestos!$F$12*Supuestos!$F$9/((Supuestos!$F$29*Supuestos!$F$21+Supuestos!$F$30*Supuestos!$F$22+Supuestos!$F$31*Supuestos!$F$23+Supuestos!$F$32*Supuestos!$F$24)*Supuestos!$F$17*Supuestos!$F$18)) -> 78.074689 | H5: =(Supuestos!$F$12*Supuestos!$F$9/((Supuestos!$F$29*Supuestos!$F$21+Supuestos!$F$30*Supuestos!$F$22+Supuestos!$F$31*Supuestos!$F$23+Supuestos!$F$32*Supuestos!$F$24)*Supuestos!$F$17*Supuestos!$F$18)) -> 78.074689 | I5: =(Supuestos!$F$12*Supuestos!$F$9/((Supuestos!$F$29*Supuestos!$F$21+Supuestos!$F$30*Supuestos!$F$22+Supuestos!$F$31*Supuestos!$F$23+Supuestos!$F$32*Supuestos!$F$24)*Supuestos!$F$17*Supuestos!$F$18)) -> 78.074689 | J5: =(Supuestos!$F$12*Supuestos!$F$9/((Supuestos!$F$29*Supuestos!$F$21+Supuestos!$F$30*Supuestos!$F$22+Supuestos!$F$31*Supuestos!$F$23+Supuestos!$F$32*Supuestos!$F$24)*Supuestos!$F$17*Supuestos!$F$18)) -> 78.074689 | K5: =(Supuestos!$F$12*Supuestos!$F$9/((Supuestos!$F$29*Supuestos!$F$21+Supuestos!$F$30*Supuestos!$F$22+Supuestos!$F$31*Supuestos!$F$23+Supuestos!$F$32*Supuestos!$F$24)*Supuestos!$F$17*Supuestos!$F$18)) -> 78.074689 | ... AM5: =(Supuestos!$F$12*Supuestos!$F$9/((Supuestos!$F$29*Supuestos!$F$21+Supuestos!$F$30*Supuestos!$F$22+Supuestos!$F$31*Supuestos!$F$23+Supuestos!$F$32*Supuestos!$F$24)*Supuestos!$F$17*Supuestos!$F$18)) -> 78.074689
B6: Altas de miembros flex en el mes | D6: =IF(D$3<=6,Supuestos!$F$46,IF(D$3<=12,Supuestos!$F$47,Supuestos!$F$48)) -> 5 | E6: =IF(E$3<=6,Supuestos!$F$46,IF(E$3<=12,Supuestos!$F$47,Supuestos!$F$48)) -> 5 | F6: =IF(F$3<=6,Supuestos!$F$46,IF(F$3<=12,Supuestos!$F$47,Supuestos!$F$48)) -> 5 | G6: =IF(G$3<=6,Supuestos!$F$46,IF(G$3<=12,Supuestos!$F$47,Supuestos!$F$48)) -> 5 | H6: =IF(H$3<=6,Supuestos!$F$46,IF(H$3<=12,Supuestos!$F$47,Supuestos!$F$48)) -> 5 | I6: =IF(I$3<=6,Supuestos!$F$46,IF(I$3<=12,Supuestos!$F$47,Supuestos!$F$48)) -> 5 | J6: =IF(J$3<=6,Supuestos!$F$46,IF(J$3<=12,Supuestos!$F$47,Supuestos!$F$48)) -> 4 | K6: =IF(K$3<=6,Supuestos!$F$46,IF(K$3<=12,Supuestos!$F$47,Supuestos!$F$48)) -> 4 | ... AM6: =IF(AM$3<=6,Supuestos!$F$46,IF(AM$3<=12,Supuestos!$F$47,Supuestos!$F$48)) -> 3
B7: Miembros flex (fin de mes) | D7: =MIN(D5,Supuestos!$F$45*(1-Supuestos!$F$49)+D6) -> 14.5 | E7: =MIN(E5,D7*(1-Supuestos!$F$49)+E6) -> 18.775 | F7: =MIN(F5,E7*(1-Supuestos!$F$49)+F6) -> 22.83625 | G7: =MIN(G5,F7*(1-Supuestos!$F$49)+G6) -> 26.694437 | H7: =MIN(H5,G7*(1-Supuestos!$F$49)+H6) -> 30.359716 | I7: =MIN(I5,H7*(1-Supuestos!$F$49)+I6) -> 33.84173 | J7: =MIN(J5,I7*(1-Supuestos!$F$49)+J6) -> 36.149643 | K7: =MIN(K5,J7*(1-Supuestos!$F$49)+K6) -> 38.342161 | L7: =MIN(L5,K7*(1-Supuestos!$F$49)+L6) -> 40.425053 | ... AM7: =MIN(AM5,AL7*(1-Supuestos!$F$49)+AM6) -> 55.932426
B8: Bajas estimadas de flex en el mes | D8: =Supuestos!$F$45*Supuestos!$F$49 -> 0.5 | E8: =D7*Supuestos!$F$49 -> 0.725 | F8: =E7*Supuestos!$F$49 -> 0.93875 | G8: =F7*Supuestos!$F$49 -> 1.1418125 | H8: =G7*Supuestos!$F$49 -> 1.3347219 | I8: =H7*Supuestos!$F$49 -> 1.5179858 | J8: =I7*Supuestos!$F$49 -> 1.6920865 | K8: =J7*Supuestos!$F$49 -> 1.8074822 | L8: =K7*Supuestos!$F$49 -> 1.9171081 | ... AM8: =AL7*Supuestos!$F$49 -> 2.7859172
B9: Puestos fijos ocupados | D9: =MIN(Supuestos!$F$13,Supuestos!$F$50) -> 1.5 | E9: =MIN(Supuestos!$F$13,D9*(1-Supuestos!$F$51)+Supuestos!$F$50) -> 2.955 | F9: =MIN(Supuestos!$F$13,E9*(1-Supuestos!$F$51)+Supuestos!$F$50) -> 4.36635 | G9: =MIN(Supuestos!$F$13,F9*(1-Supuestos!$F$51)+Supuestos!$F$50) -> 5.7353595 | H9: =MIN(Supuestos!$F$13,G9*(1-Supuestos!$F$51)+Supuestos!$F$50) -> 7.0632987 | I9: =MIN(Supuestos!$F$13,H9*(1-Supuestos!$F$51)+Supuestos!$F$50) -> 8 | J9: =MIN(Supuestos!$F$13,I9*(1-Supuestos!$F$51)+Supuestos!$F$50) -> 8 | K9: =MIN(Supuestos!$F$13,J9*(1-Supuestos!$F$51)+Supuestos!$F$50) -> 8 | L9: =MIN(Supuestos!$F$13,K9*(1-Supuestos!$F$51)+Supuestos!$F$50) -> 8 | ... AM9: =MIN(Supuestos!$F$13,AL9*(1-Supuestos!$F$51)+Supuestos!$F$50) -> 8
B10: Oficinas privadas ocupadas | D10: =Supuestos!$F$14*MIN(1,D$3/Supuestos!$F$43) -> 0.75 | E10: =Supuestos!$F$14*MIN(1,E$3/Supuestos!$F$43) -> 1.5 | F10: =Supuestos!$F$14*MIN(1,F$3/Supuestos!$F$43) -> 2.25 | G10: =Supuestos!$F$14*MIN(1,G$3/Supuestos!$F$43) -> 3 | H10: =Supuestos!$F$14*MIN(1,H$3/Supuestos!$F$43) -> 3 | I10: =Supuestos!$F$14*MIN(1,I$3/Supuestos!$F$43) -> 3 | J10: =Supuestos!$F$14*MIN(1,J$3/Supuestos!$F$43) -> 3 | K10: =Supuestos!$F$14*MIN(1,K$3/Supuestos!$F$43) -> 3 | ... AM10: =Supuestos!$F$14*MIN(1,AM$3/Supuestos!$F$43) -> 3
B11: Puestos-día usados por miembros flex | D11: =D7*(Supuestos!$F$29*Supuestos!$F$21+Supuestos!$F$30*Supuestos!$F$22+Supuestos!$F$31*Supuestos!$F$23+Supuestos!$F$32*Supuestos!$F$24)*Supuestos!$F$17 -> 131.04375 | E11: =E7*(Supuestos!$F$29*Supuestos!$F$21+Supuestos!$F$30*Supuestos!$F$22+Supuestos!$F$31*Supuestos!$F$23+Supuestos!$F$32*Supuestos!$F$24)*Supuestos!$F$17 -> 169.67906 | F11: =F7*(Supuestos!$F$29*Supuestos!$F$21+Supuestos!$F$30*Supuestos!$F$22+Supuestos!$F$31*Supuestos!$F$23+Supuestos!$F$32*Supuestos!$F$24)*Supuestos!$F$17 -> 206.38261 | G11: =G7*(Supuestos!$F$29*Supuestos!$F$21+Supuestos!$F$30*Supuestos!$F$22+Supuestos!$F$31*Supuestos!$F$23+Supuestos!$F$32*Supuestos!$F$24)*Supuestos!$F$17 -> 241.25098 | H11: =H7*(Supuestos!$F$29*Supuestos!$F$21+Supuestos!$F$30*Supuestos!$F$22+Supuestos!$F$31*Supuestos!$F$23+Supuestos!$F$32*Supuestos!$F$24)*Supuestos!$F$17 -> 274.37593 | I11: =I7*(Supuestos!$F$29*Supuestos!$F$21+Supuestos!$F$30*Supuestos!$F$22+Supuestos!$F$31*Supuestos!$F$23+Supuestos!$F$32*Supuestos!$F$24)*Supuestos!$F$17 -> 305.84463 | J11: =J7*(Supuestos!$F$29*Supuestos!$F$21+Supuestos!$F$30*Supuestos!$F$22+Supuestos!$F$31*Supuestos!$F$23+Supuestos!$F$32*Supuestos!$F$24)*Supuestos!$F$17 -> 326.7024 | K11: =K7*(Supuestos!$F$29*Supuestos!$F$21+Supuestos!$F$30*Supuestos!$F$22+Supuestos!$F$31*Supuestos!$F$23+Supuestos!$F$32*Supuestos!$F$24)*Supuestos!$F$17 -> 346.51728 | ... AM11: =AM7*(Supuestos!$F$29*Supuestos!$F$21+Supuestos!$F$30*Supuestos!$F$22+Supuestos!$F$31*Supuestos!$F$23+Supuestos!$F$32*Supuestos!$F$24)*Supuestos!$F$17 -> 505.4893
B12: Ocupación promedio de puestos flex (días hábiles) | D12: =D11/(Supuestos!$F$12*Supuestos!$F$9) -> 0.14857568 | E12: =E11/(Supuestos!$F$12*Supuestos!$F$9) -> 0.19237989 | F12: =F11/(Supuestos!$F$12*Supuestos!$F$9) -> 0.23399389 | G12: =G11/(Supuestos!$F$12*Supuestos!$F$9) -> 0.27352719 | H12: =H11/(Supuestos!$F$12*Supuestos!$F$9) -> 0.31108382 | I12: =I11/(Supuestos!$F$12*Supuestos!$F$9) -> 0.34676262 | J12: =J11/(Supuestos!$F$12*Supuestos!$F$9) -> 0.37041089 | K12: =K11/(Supuestos!$F$12*Supuestos!$F$9) -> 0.39287674 | ... AM12: =AM11/(Supuestos!$F$12*Supuestos!$F$9) -> 0.57311712
B13: Puestos flex simultáneos en el pico (estimado) | D13: =D11/Supuestos!$F$9*Supuestos!$F$18 -> 7.8002232 | E13: =E11/Supuestos!$F$9*Supuestos!$F$18 -> 10.099944 | F13: =F11/Supuestos!$F$9*Supuestos!$F$18 -> 12.284679 | G13: =G11/Supuestos!$F$9*Supuestos!$F$18 -> 14.360177 | H13: =H11/Supuestos!$F$9*Supuestos!$F$18 -> 16.331901 | I13: =I11/Supuestos!$F$9*Supuestos!$F$18 -> 18.205038 | J13: =J11/Supuestos!$F$9*Supuestos!$F$18 -> 19.446572 | K13: =K11/Supuestos!$F$9*Supuestos!$F$18 -> 20.626029 | ... AM13: =AM11/Supuestos!$F$9*Supuestos!$F$18 -> 30.088649
B14: INGRESOS (USD sin IVA)
B15: Membresías flex (días por mes / ilimitado) | D15: =D7*((Supuestos!$F$29*Supuestos!$F$25+Supuestos!$F$30*Supuestos!$F$26+Supuestos!$F$31*Supuestos!$F$27+Supuestos!$F$32*Supuestos!$F$28)*Supuestos!$F$37)*(1-Supuestos!$F$38)/(1+Supuestos!$F$7*Supuestos!$F$8)/Supuestos!$F$6 -> 730.54351 | E15: =E7*((Supuestos!$F$29*Supuestos!$F$25+Supuestos!$F$30*Supuestos!$F$26+Supuestos!$F$31*Supuestos!$F$27+Supuestos!$F$32*Supuestos!$F$28)*Supuestos!$F$37)*(1-Supuestos!$F$38)/(1+Supuestos!$F$7*Supuestos!$F$8)/Supuestos!$F$6 -> 945.92789 | F15: =F7*((Supuestos!$F$29*Supuestos!$F$25+Supuestos!$F$30*Supuestos!$F$26+Supuestos!$F$31*Supuestos!$F$27+Supuestos!$F$32*Supuestos!$F$28)*Supuestos!$F$37)*(1-Supuestos!$F$38)/(1+Supuestos!$F$7*Supuestos!$F$8)/Supuestos!$F$6 -> 1150.543 | G15: =G7*((Supuestos!$F$29*Supuestos!$F$25+Supuestos!$F$30*Supuestos!$F$26+Supuestos!$F$31*Supuestos!$F$27+Supuestos!$F$32*Supuestos!$F$28)*Supuestos!$F$37)*(1-Supuestos!$F$38)/(1+Supuestos!$F$7*Supuestos!$F$8)/Supuestos!$F$6 -> 1344.9274 | H15: =H7*((Supuestos!$F$29*Supuestos!$F$25+Supuestos!$F$30*Supuestos!$F$26+Supuestos!$F$31*Supuestos!$F$27+Supuestos!$F$32*Supuestos!$F$28)*Supuestos!$F$37)*(1-Supuestos!$F$38)/(1+Supuestos!$F$7*Supuestos!$F$8)/Supuestos!$F$6 -> 1529.5926 | I15: =I7*((Supuestos!$F$29*Supuestos!$F$25+Supuestos!$F$30*Supuestos!$F$26+Supuestos!$F$31*Supuestos!$F$27+Supuestos!$F$32*Supuestos!$F$28)*Supuestos!$F$37)*(1-Supuestos!$F$38)/(1+Supuestos!$F$7*Supuestos!$F$8)/Supuestos!$F$6 -> 1705.0246 | J15: =J7*((Supuestos!$F$29*Supuestos!$F$25+Supuestos!$F$30*Supuestos!$F$26+Supuestos!$F$31*Supuestos!$F$27+Supuestos!$F$32*Supuestos!$F$28)*Supuestos!$F$37)*(1-Supuestos!$F$38)/(1+Supuestos!$F$7*Supuestos!$F$8)/Supuestos!$F$6 -> 1821.3026 | K15: =K7*((Supuestos!$F$29*Supuestos!$F$25+Supuestos!$F$30*Supuestos!$F$26+Supuestos!$F$31*Supuestos!$F$27+Supuestos!$F$32*Supuestos!$F$28)*Supuestos!$F$37)*(1-Supuestos!$F$38)/(1+Supuestos!$F$7*Supuestos!$F$8)/Supuestos!$F$6 -> 1931.7667 | ... AM15: =AM7*((Supuestos!$F$29*Supuestos!$F$25+Supuestos!$F$30*Supuestos!$F$26+Supuestos!$F$31*Supuestos!$F$27+Supuestos!$F$32*Supuestos!$F$28)*Supuestos!$F$37)*(1-Supuestos!$F$38)/(1+Supuestos!$F$7*Supuestos!$F$8)/Supuestos!$F$6 -> 2818.0049
B16: Puestos fijos | D16: =D9*Supuestos!$F$33*Supuestos!$F$37*(1-Supuestos!$F$38)/(1+Supuestos!$F$7*Supuestos!$F$8)/Supuestos!$F$6 -> 93.535442 | E16: =E9*Supuestos!$F$33*Supuestos!$F$37*(1-Supuestos!$F$38)/(1+Supuestos!$F$7*Supuestos!$F$8)/Supuestos!$F$6 -> 184.26482 | F16: =F9*Supuestos!$F$33*Supuestos!$F$37*(1-Supuestos!$F$38)/(1+Supuestos!$F$7*Supuestos!$F$8)/Supuestos!$F$6 -> 272.27232 | G16: =G9*Supuestos!$F$33*Supuestos!$F$37*(1-Supuestos!$F$38)/(1+Supuestos!$F$7*Supuestos!$F$8)/Supuestos!$F$6 -> 357.63959 | H16: =H9*Supuestos!$F$33*Supuestos!$F$37*(1-Supuestos!$F$38)/(1+Supuestos!$F$7*Supuestos!$F$8)/Supuestos!$F$6 -> 440.44584 | I16: =I9*Supuestos!$F$33*Supuestos!$F$37*(1-Supuestos!$F$38)/(1+Supuestos!$F$7*Supuestos!$F$8)/Supuestos!$F$6 -> 498.85569 | J16: =J9*Supuestos!$F$33*Supuestos!$F$37*(1-Supuestos!$F$38)/(1+Supuestos!$F$7*Supuestos!$F$8)/Supuestos!$F$6 -> 498.85569 | K16: =K9*Supuestos!$F$33*Supuestos!$F$37*(1-Supuestos!$F$38)/(1+Supuestos!$F$7*Supuestos!$F$8)/Supuestos!$F$6 -> 498.85569 | ... AM16: =AM9*Supuestos!$F$33*Supuestos!$F$37*(1-Supuestos!$F$38)/(1+Supuestos!$F$7*Supuestos!$F$8)/Supuestos!$F$6 -> 498.85569
B17: Oficinas privadas (complemento) | D17: =D10*Supuestos!$F$34*Supuestos!$F$37*(1-Supuestos!$F$38)/(1+Supuestos!$F$7*Supuestos!$F$8)/Supuestos!$F$6 -> 190.24158 | E17: =E10*Supuestos!$F$34*Supuestos!$F$37*(1-Supuestos!$F$38)/(1+Supuestos!$F$7*Supuestos!$F$8)/Supuestos!$F$6 -> 380.48315 | F17: =F10*Supuestos!$F$34*Supuestos!$F$37*(1-Supuestos!$F$38)/(1+Supuestos!$F$7*Supuestos!$F$8)/Supuestos!$F$6 -> 570.72473 | G17: =G10*Supuestos!$F$34*Supuestos!$F$37*(1-Supuestos!$F$38)/(1+Supuestos!$F$7*Supuestos!$F$8)/Supuestos!$F$6 -> 760.96631 | H17: =H10*Supuestos!$F$34*Supuestos!$F$37*(1-Supuestos!$F$38)/(1+Supuestos!$F$7*Supuestos!$F$8)/Supuestos!$F$6 -> 760.96631 | I17: =I10*Supuestos!$F$34*Supuestos!$F$37*(1-Supuestos!$F$38)/(1+Supuestos!$F$7*Supuestos!$F$8)/Supuestos!$F$6 -> 760.96631 | J17: =J10*Supuestos!$F$34*Supuestos!$F$37*(1-Supuestos!$F$38)/(1+Supuestos!$F$7*Supuestos!$F$8)/Supuestos!$F$6 -> 760.96631 | K17: =K10*Supuestos!$F$34*Supuestos!$F$37*(1-Supuestos!$F$38)/(1+Supuestos!$F$7*Supuestos!$F$8)/Supuestos!$F$6 -> 760.96631 | ... AM17: =AM10*Supuestos!$F$34*Supuestos!$F$37*(1-Supuestos!$F$38)/(1+Supuestos!$F$7*Supuestos!$F$8)/Supuestos!$F$6 -> 760.96631
B18: Pases diarios | D18: =Supuestos!$F$39*MIN(1,D$3/Supuestos!$F$42)*Supuestos!$F$35*Supuestos!$F$37/(1+Supuestos!$F$7*Supuestos!$F$8)/Supuestos!$F$6 -> 63.506569 | E18: =Supuestos!$F$39*MIN(1,E$3/Supuestos!$F$42)*Supuestos!$F$35*Supuestos!$F$37/(1+Supuestos!$F$7*Supuestos!$F$8)/Supuestos!$F$6 -> 127.01314 | F18: =Supuestos!$F$39*MIN(1,F$3/Supuestos!$F$42)*Supuestos!$F$35*Supuestos!$F$37/(1+Supuestos!$F$7*Supuestos!$F$8)/Supuestos!$F$6 -> 190.51971 | G18: =Supuestos!$F$39*MIN(1,G$3/Supuestos!$F$42)*Supuestos!$F$35*Supuestos!$F$37/(1+Supuestos!$F$7*Supuestos!$F$8)/Supuestos!$F$6 -> 254.02628 | H18: =Supuestos!$F$39*MIN(1,H$3/Supuestos!$F$42)*Supuestos!$F$35*Supuestos!$F$37/(1+Supuestos!$F$7*Supuestos!$F$8)/Supuestos!$F$6 -> 317.53285 | I18: =Supuestos!$F$39*MIN(1,I$3/Supuestos!$F$42)*Supuestos!$F$35*Supuestos!$F$37/(1+Supuestos!$F$7*Supuestos!$F$8)/Supuestos!$F$6 -> 381.03942 | J18: =Supuestos!$F$39*MIN(1,J$3/Supuestos!$F$42)*Supuestos!$F$35*Supuestos!$F$37/(1+Supuestos!$F$7*Supuestos!$F$8)/Supuestos!$F$6 -> 381.03942 | K18: =Supuestos!$F$39*MIN(1,K$3/Supuestos!$F$42)*Supuestos!$F$35*Supuestos!$F$37/(1+Supuestos!$F$7*Supuestos!$F$8)/Supuestos!$F$6 -> 381.03942 | ... AM18: =Supuestos!$F$39*MIN(1,AM$3/Supuestos!$F$42)*Supuestos!$F$35*Supuestos!$F$37/(1+Supuestos!$F$7*Supuestos!$F$8)/Supuestos!$F$6 -> 381.03942
B19: Salas por hora a externos | D19: =Supuestos!$F$40*MIN(1,D$3/Supuestos!$F$42)*Supuestos!$F$36*Supuestos!$F$37/(1+Supuestos!$F$7*Supuestos!$F$8)/Supuestos!$F$6 -> 36.157025 | E19: =Supuestos!$F$40*MIN(1,E$3/Supuestos!$F$42)*Supuestos!$F$36*Supuestos!$F$37/(1+Supuestos!$F$7*Supuestos!$F$8)/Supuestos!$F$6 -> 72.31405 | F19: =Supuestos!$F$40*MIN(1,F$3/Supuestos!$F$42)*Supuestos!$F$36*Supuestos!$F$37/(1+Supuestos!$F$7*Supuestos!$F$8)/Supuestos!$F$6 -> 108.47107 | G19: =Supuestos!$F$40*MIN(1,G$3/Supuestos!$F$42)*Supuestos!$F$36*Supuestos!$F$37/(1+Supuestos!$F$7*Supuestos!$F$8)/Supuestos!$F$6 -> 144.6281 | H19: =Supuestos!$F$40*MIN(1,H$3/Supuestos!$F$42)*Supuestos!$F$36*Supuestos!$F$37/(1+Supuestos!$F$7*Supuestos!$F$8)/Supuestos!$F$6 -> 180.78512 | I19: =Supuestos!$F$40*MIN(1,I$3/Supuestos!$F$42)*Supuestos!$F$36*Supuestos!$F$37/(1+Supuestos!$F$7*Supuestos!$F$8)/Supuestos!$F$6 -> 216.94215 | J19: =Supuestos!$F$40*MIN(1,J$3/Supuestos!$F$42)*Supuestos!$F$36*Supuestos!$F$37/(1+Supuestos!$F$7*Supuestos!$F$8)/Supuestos!$F$6 -> 216.94215 | K19: =Supuestos!$F$40*MIN(1,K$3/Supuestos!$F$42)*Supuestos!$F$36*Supuestos!$F$37/(1+Supuestos!$F$7*Supuestos!$F$8)/Supuestos!$F$6 -> 216.94215 | ... AM19: =Supuestos!$F$40*MIN(1,AM$3/Supuestos!$F$42)*Supuestos!$F$36*Supuestos!$F$37/(1+Supuestos!$F$7*Supuestos!$F$8)/Supuestos!$F$6 -> 216.94215
B20: Otros (domicilio comercial, eventos) | D20: =Supuestos!$F$41*MIN(1,D$3/Supuestos!$F$42) -> 33.333333 | E20: =Supuestos!$F$41*MIN(1,E$3/Supuestos!$F$42) -> 66.666667 | F20: =Supuestos!$F$41*MIN(1,F$3/Supuestos!$F$42) -> 100 | G20: =Supuestos!$F$41*MIN(1,G$3/Supuestos!$F$42) -> 133.33333 | H20: =Supuestos!$F$41*MIN(1,H$3/Supuestos!$F$42) -> 166.66667 | I20: =Supuestos!$F$41*MIN(1,I$3/Supuestos!$F$42) -> 200 | J20: =Supuestos!$F$41*MIN(1,J$3/Supuestos!$F$42) -> 200 | K20: =Supuestos!$F$41*MIN(1,K$3/Supuestos!$F$42) -> 200 | ... AM20: =Supuestos!$F$41*MIN(1,AM$3/Supuestos!$F$42) -> 200
B21: INGRESOS TOTALES | D21: =SUM(D15:D20) -> 1147.3175 | E21: =SUM(E15:E20) -> 1776.6697 | F21: =SUM(F15:F20) -> 2392.5309 | G21: =SUM(G15:G20) -> 2995.5211 | H21: =SUM(H15:H20) -> 3395.9894 | I21: =SUM(I15:I20) -> 3762.8281 | J21: =SUM(J15:J20) -> 3879.1061 | K21: =SUM(K15:K20) -> 3989.5702 | ... AM21: =SUM(AM15:AM20) -> 4875.8085
B22: COSTOS VARIABLES
B23: Café, té, agua y consumibles | D23: =(D11+D9*Supuestos!$F$9*Supuestos!$F$19+(D10*Supuestos!$F$15*Supuestos!$F$9*Supuestos!$F$19)+Supuestos!$F$39*MIN(1,D$3/Supuestos!$F$42))*Supuestos!$F$53 -> 82.974604 | E23: =(E11+E9*Supuestos!$F$9*Supuestos!$F$19+(E10*Supuestos!$F$15*Supuestos!$F$9*Supuestos!$F$19)+Supuestos!$F$39*MIN(1,E$3/Supuestos!$F$42))*Supuestos!$F$53 -> 127.75179 | F23: =(F11+F9*Supuestos!$F$9*Supuestos!$F$19+(F10*Supuestos!$F$15*Supuestos!$F$9*Supuestos!$F$19)+Supuestos!$F$39*MIN(1,F$3/Supuestos!$F$42))*Supuestos!$F$53 -> 171.43629 | G23: =(G11+G9*Supuestos!$F$9*Supuestos!$F$19+(G10*Supuestos!$F$15*Supuestos!$F$9*Supuestos!$F$19)+Supuestos!$F$39*MIN(1,G$3/Supuestos!$F$42))*Supuestos!$F$53 -> 214.07672 | H23: =(H11+H9*Supuestos!$F$9*Supuestos!$F$19+(H10*Supuestos!$F$15*Supuestos!$F$9*Supuestos!$F$19)+Supuestos!$F$39*MIN(1,H$3/Supuestos!$F$42))*Supuestos!$F$53 -> 240.22147 | I23: =(I11+I9*Supuestos!$F$9*Supuestos!$F$19+(I10*Supuestos!$F$15*Supuestos!$F$9*Supuestos!$F$19)+Supuestos!$F$39*MIN(1,I$3/Supuestos!$F$42))*Supuestos!$F$53 -> 262.9923 | J23: =(J11+J9*Supuestos!$F$9*Supuestos!$F$19+(J10*Supuestos!$F$15*Supuestos!$F$9*Supuestos!$F$19)+Supuestos!$F$39*MIN(1,J$3/Supuestos!$F$42))*Supuestos!$F$53 -> 271.54398 | K23: =(K11+K9*Supuestos!$F$9*Supuestos!$F$19+(K10*Supuestos!$F$15*Supuestos!$F$9*Supuestos!$F$19)+Supuestos!$F$39*MIN(1,K$3/Supuestos!$F$42))*Supuestos!$F$53 -> 279.66809 | ... AM23: =(AM11+AM9*Supuestos!$F$9*Supuestos!$F$19+(AM10*Supuestos!$F$15*Supuestos!$F$9*Supuestos!$F$19)+Supuestos!$F$39*MIN(1,AM$3/Supuestos!$F$42))*Supuestos!$F$53 -> 344.84661
B24: Comisiones de cobro | D24: =D21*(1+Supuestos!$F$7*Supuestos!$F$8)*Supuestos!$F$54 -> 8.3295247 | E24: =E21*(1+Supuestos!$F$7*Supuestos!$F$8)*Supuestos!$F$54 -> 12.898622 | F24: =F21*(1+Supuestos!$F$7*Supuestos!$F$8)*Supuestos!$F$54 -> 17.369774 | G24: =G21*(1+Supuestos!$F$7*Supuestos!$F$8)*Supuestos!$F$54 -> 21.747483 | H24: =H21*(1+Supuestos!$F$7*Supuestos!$F$8)*Supuestos!$F$54 -> 24.654883 | I24: =I21*(1+Supuestos!$F$7*Supuestos!$F$8)*Supuestos!$F$54 -> 27.318132 | J24: =J21*(1+Supuestos!$F$7*Supuestos!$F$8)*Supuestos!$F$54 -> 28.16231 | K24: =K21*(1+Supuestos!$F$7*Supuestos!$F$8)*Supuestos!$F$54 -> 28.96428 | ... AM24: =AM21*(1+Supuestos!$F$7*Supuestos!$F$8)*Supuestos!$F$54 -> 35.398369
B25: Ingresos Brutos | D25: =D21*Supuestos!$F$55 -> 34.419524 | E25: =E21*Supuestos!$F$55 -> 53.300091 | F25: =F21*Supuestos!$F$55 -> 71.775926 | G25: =G21*Supuestos!$F$55 -> 89.865632 | H25: =H21*Supuestos!$F$55 -> 101.87968 | I25: =I21*Supuestos!$F$55 -> 112.88484 | J25: =J21*Supuestos!$F$55 -> 116.37318 | K25: =K21*Supuestos!$F$55 -> 119.68711 | ... AM25: =AM21*Supuestos!$F$55 -> 146.27425
B26: Impuesto a los débitos y créditos (aprox.) | D26: =D21*(1+Supuestos!$F$7*Supuestos!$F$8)*Supuestos!$F$56 -> 16.659049 | E26: =E21*(1+Supuestos!$F$7*Supuestos!$F$8)*Supuestos!$F$56 -> 25.797244 | F26: =F21*(1+Supuestos!$F$7*Supuestos!$F$8)*Supuestos!$F$56 -> 34.739548 | G26: =G21*(1+Supuestos!$F$7*Supuestos!$F$8)*Supuestos!$F$56 -> 43.494966 | H26: =H21*(1+Supuestos!$F$7*Supuestos!$F$8)*Supuestos!$F$56 -> 49.309766 | I26: =I21*(1+Supuestos!$F$7*Supuestos!$F$8)*Supuestos!$F$56 -> 54.636264 | J26: =J21*(1+Supuestos!$F$7*Supuestos!$F$8)*Supuestos!$F$56 -> 56.324621 | K26: =K21*(1+Supuestos!$F$7*Supuestos!$F$8)*Supuestos!$F$56 -> 57.92856 | ... AM26: =AM21*(1+Supuestos!$F$7*Supuestos!$F$8)*Supuestos!$F$56 -> 70.796739
B27: Total costos variables | D27: =SUM(D23:D26) -> 142.3827 | E27: =SUM(E23:E26) -> 219.74775 | F27: =SUM(F23:F26) -> 295.32154 | G27: =SUM(G23:G26) -> 369.1848 | H27: =SUM(H23:H26) -> 416.0658 | I27: =SUM(I23:I26) -> 457.83154 | J27: =SUM(J23:J26) -> 472.4041 | K27: =SUM(K23:K26) -> 486.24803 | ... AM27: =SUM(AM23:AM26) -> 597.31598
B28: MARGEN DE CONTRIBUCIÓN | D28: =D21-D27 -> 1004.9348 | E28: =E21-E27 -> 1556.922 | F28: =F21-F27 -> 2097.2093 | G28: =G21-G27 -> 2626.3362 | H28: =H21-H27 -> 2979.9236 | I28: =I21-I27 -> 3304.9966 | J28: =J21-J27 -> 3406.702 | K28: =K21-K27 -> 3503.3222 | ... AM28: =AM21-AM27 -> 4278.4925
B29: COSTOS FIJOS MENSUALES
B30: Personal (recepción / comunidad), con cargas | D30: =Supuestos!$F$58*Supuestos!$F$59 -> 1574.85 | E30: =Supuestos!$F$58*Supuestos!$F$59 -> 1574.85 | F30: =Supuestos!$F$58*Supuestos!$F$59 -> 1574.85 | G30: =Supuestos!$F$58*Supuestos!$F$59 -> 1574.85 | H30: =Supuestos!$F$58*Supuestos!$F$59 -> 1574.85 | I30: =Supuestos!$F$58*Supuestos!$F$59 -> 1574.85 | J30: =Supuestos!$F$58*Supuestos!$F$59 -> 1574.85 | K30: =Supuestos!$F$58*Supuestos!$F$59 -> 1574.85 | ... AM30: =Supuestos!$F$58*Supuestos!$F$59 -> 1574.85
B31: Limpieza | D31: =Supuestos!$F$60 -> 269.2 | E31: =Supuestos!$F$60 -> 269.2 | F31: =Supuestos!$F$60 -> 269.2 | G31: =Supuestos!$F$60 -> 269.2 | H31: =Supuestos!$F$60 -> 269.2 | I31: =Supuestos!$F$60 -> 269.2 | J31: =Supuestos!$F$60 -> 269.2 | K31: =Supuestos!$F$60 -> 269.2 | ... AM31: =Supuestos!$F$60 -> 269.2
B32: Internet principal + respaldo | D32: =Supuestos!$F$61 -> 43 | E32: =Supuestos!$F$61 -> 43 | F32: =Supuestos!$F$61 -> 43 | G32: =Supuestos!$F$61 -> 43 | H32: =Supuestos!$F$61 -> 43 | I32: =Supuestos!$F$61 -> 43 | J32: =Supuestos!$F$61 -> 43 | K32: =Supuestos!$F$61 -> 43 | ... AM32: =Supuestos!$F$61 -> 43
B33: Electricidad, gas y agua | D33: =Supuestos!$F$62 -> 27.1 | E33: =Supuestos!$F$62 -> 27.1 | F33: =Supuestos!$F$62 -> 27.1 | G33: =Supuestos!$F$62 -> 27.1 | H33: =Supuestos!$F$62 -> 27.1 | I33: =Supuestos!$F$62 -> 27.1 | J33: =Supuestos!$F$62 -> 27.1 | K33: =Supuestos!$F$62 -> 27.1 | ... AM33: =Supuestos!$F$62 -> 27.1
B34: Seguros | D34: =Supuestos!$F$63 -> 32.1 | E34: =Supuestos!$F$63 -> 32.1 | F34: =Supuestos!$F$63 -> 32.1 | G34: =Supuestos!$F$63 -> 32.1 | H34: =Supuestos!$F$63 -> 32.1 | I34: =Supuestos!$F$63 -> 32.1 | J34: =Supuestos!$F$63 -> 32.1 | K34: =Supuestos!$F$63 -> 32.1 | ... AM34: =Supuestos!$F$63 -> 32.1
B35: Software de gestión y reservas | D35: =Supuestos!$F$64 -> 99 | E35: =Supuestos!$F$64 -> 99 | F35: =Supuestos!$F$64 -> 99 | G35: =Supuestos!$F$64 -> 99 | H35: =Supuestos!$F$64 -> 99 | I35: =Supuestos!$F$64 -> 99 | J35: =Supuestos!$F$64 -> 99 | K35: =Supuestos!$F$64 -> 99 | ... AM35: =Supuestos!$F$64 -> 99
B36: Contador y administración | D36: =Supuestos!$F$65 -> 0 | E36: =Supuestos!$F$65 -> 0 | F36: =Supuestos!$F$65 -> 0 | G36: =Supuestos!$F$65 -> 0 | H36: =Supuestos!$F$65 -> 0 | I36: =Supuestos!$F$65 -> 0 | J36: =Supuestos!$F$65 -> 0 | K36: =Supuestos!$F$65 -> 0 | ... AM36: =Supuestos!$F$65 -> 0
B37: Mantenimiento y reposición | D37: =Inversion!F21*Supuestos!$F$66/12 -> 452.28468 | E37: =Inversion!F21*Supuestos!$F$66/12 -> 452.28468 | F37: =Inversion!F21*Supuestos!$F$66/12 -> 452.28468 | G37: =Inversion!F21*Supuestos!$F$66/12 -> 452.28468 | H37: =Inversion!F21*Supuestos!$F$66/12 -> 452.28468 | I37: =Inversion!F21*Supuestos!$F$66/12 -> 452.28468 | J37: =Inversion!F21*Supuestos!$F$66/12 -> 452.28468 | K37: =Inversion!F21*Supuestos!$F$66/12 -> 452.28468 | L37: =Inversion!F21*Supuestos!$F$66/12 -> 452.28468 | M37: =Inversion!F21*Supuestos!$F$66/12 -> 452.28468 | N37: =Inversion!F21*Supuestos!$F$66/12 -> 452.28468 | O37: =Inversion!F21*Supuestos!$F$66/12 -> 452.28468 | P37: =Inversion!F21*Supuestos!$F$66/12 -> 452.28468 | Q37: =Inversion!F21*Supuestos!$F$66/12 -> 452.28468 | R37: =Inversion!F21*Supuestos!$F$66/12 -> 452.28468 | S37: =Inversion!F21*Supuestos!$F$66/12 -> 452.28468 | T37: =Inversion!F21*Supuestos!$F$66/12 -> 452.28468 | U37: =Inversion!F21*Supuestos!$F$66/12 -> 452.28468 | V37: =Inversion!F21*Supuestos!$F$66/12 -> 452.28468 | W37: =Inversion!F21*Supuestos!$F$66/12 -> 452.28468 | X37: =Inversion!F21*Supuestos!$F$66/12 -> 452.28468 | Y37: =Inversion!F21*Supuestos!$F$66/12 -> 452.28468 | Z37: =Inversion!F21*Supuestos!$F$66/12 -> 452.28468 | AA37: =Inversion!F21*Supuestos!$F$66/12 -> 452.28468 | AB37: =Inversion!F21*Supuestos!$F$66/12 -> 452.28468 | AC37: =Inversion!F21*Supuestos!$F$66/12 -> 452.28468 | AD37: =Inversion!F21*Supuestos!$F$66/12 -> 452.28468 | AE37: =Inversion!F21*Supuestos!$F$66/12 -> 452.28468 | AF37: =Inversion!F21*Supuestos!$F$66/12 -> 452.28468 | AG37: =Inversion!F21*Supuestos!$F$66/12 -> 452.28468 | AH37: =Inversion!F21*Supuestos!$F$66/12 -> 452.28468 | AI37: =Inversion!F21*Supuestos!$F$66/12 -> 452.28468 | AJ37: =Inversion!F21*Supuestos!$F$66/12 -> 452.28468 | AK37: =Inversion!F21*Supuestos!$F$66/12 -> 452.28468 | AL37: =Inversion!F21*Supuestos!$F$66/12 -> 452.28468 | AM37: =Inversion!F21*Supuestos!$F$66/12 -> 452.28468
B38: Publicidad y comunidad (eventos, desayunos) | D38: =Supuestos!$F$67+Supuestos!$F$68 -> 550 | E38: =Supuestos!$F$67+Supuestos!$F$68 -> 550 | F38: =Supuestos!$F$67+Supuestos!$F$68 -> 550 | G38: =Supuestos!$F$67+Supuestos!$F$68 -> 550 | H38: =Supuestos!$F$67+Supuestos!$F$68 -> 550 | I38: =Supuestos!$F$67+Supuestos!$F$68 -> 550 | J38: =Supuestos!$F$67+Supuestos!$F$68 -> 550 | K38: =Supuestos!$F$67+Supuestos!$F$68 -> 550 | ... AM38: =Supuestos!$F$67+Supuestos!$F$68 -> 550
B39: Otros e imprevistos | D39: =SUM(D30:D38)*Supuestos!$F$69 -> 152.37673 | E39: =SUM(E30:E38)*Supuestos!$F$69 -> 152.37673 | F39: =SUM(F30:F38)*Supuestos!$F$69 -> 152.37673 | G39: =SUM(G30:G38)*Supuestos!$F$69 -> 152.37673 | H39: =SUM(H30:H38)*Supuestos!$F$69 -> 152.37673 | I39: =SUM(I30:I38)*Supuestos!$F$69 -> 152.37673 | J39: =SUM(J30:J38)*Supuestos!$F$69 -> 152.37673 | K39: =SUM(K30:K38)*Supuestos!$F$69 -> 152.37673 | ... AM39: =SUM(AM30:AM38)*Supuestos!$F$69 -> 152.37673
B40: Total costos fijos | D40: =SUM(D30:D39) -> 3199.9114 | E40: =SUM(E30:E39) -> 3199.9114 | F40: =SUM(F30:F39) -> 3199.9114 | G40: =SUM(G30:G39) -> 3199.9114 | H40: =SUM(H30:H39) -> 3199.9114 | I40: =SUM(I30:I39) -> 3199.9114 | J40: =SUM(J30:J39) -> 3199.9114 | K40: =SUM(K30:K39) -> 3199.9114 | ... AM40: =SUM(AM30:AM39) -> 3199.9114
B41: RESULTADO Y CAJA
B42: RESULTADO OPERATIVO (antes de Ganancias) | D42: =D28-D40 -> -2194.9767 | E42: =E28-E40 -> -1642.9894 | F42: =F28-F40 -> -1102.7021 | G42: =G28-G40 -> -573.57517 | H42: =H28-H40 -> -219.9878 | I42: =I28-I40 -> 105.08516 | J42: =J28-J40 -> 206.79061 | K42: =K28-K40 -> 303.41079 | ... AM42: =AM28-AM40 -> 1078.5811
B43: Inversión inicial | C43: =-Inversion!F21 -> -135685.4 | D43: 0 | E43: 0 | F43: 0 | G43: 0 | H43: 0 | I43: 0 | J43: 0 | K43: 0 | L43: 0 | M43: 0 | N43: 0 | O43: 0 | P43: 0 | Q43: 0 | R43: 0 | S43: 0 | T43: 0 | U43: 0 | V43: 0 | W43: 0 | X43: 0 | Y43: 0 | Z43: 0 | AA43: 0 | AB43: 0 | AC43: 0 | AD43: 0 | AE43: 0 | AF43: 0 | AG43: 0 | AH43: 0 | AI43: 0 | AJ43: 0 | AK43: 0 | AL43: 0 | AM43: 0
B44: Flujo de caja del proyecto (casa propia, sin alquiler pagado) | C44: =C43 -> -135685.4 | D44: =D42+D43 -> -2194.9767 | E44: =E42+E43 -> -1642.9894 | F44: =F42+F43 -> -1102.7021 | G44: =G42+G43 -> -573.57517 | H44: =H42+H43 -> -219.9878 | I44: =I42+I43 -> 105.08516 | J44: =J42+J43 -> 206.79061 | K44: =K42+K43 -> 303.41079 | ... AM44: =AM42+AM43 -> 1078.5811
B45: Flujo acumulado | C45: =C44 -> -135685.4 | D45: =C45+D44 -> -137880.38 | E45: =D45+E44 -> -139523.37 | F45: =E45+F44 -> -140626.07 | G45: =F45+G44 -> -141199.65 | H45: =G45+H44 -> -141419.64 | I45: =H45+I44 -> -141314.55 | J45: =I45+J44 -> -141107.76 | K45: =J45+K44 -> -140804.35 | ... AM45: =AL45+AM44 -> -116787.85
B46: Alquiler de la casa que se deja de cobrar (costo de oportunidad) | C46: =-Supuestos!$F$91*Supuestos!$F$10 -> 0 | D46: =-Supuestos!$F$91 -> 0 | E46: =-Supuestos!$F$91 -> 0 | F46: =-Supuestos!$F$91 -> 0 | G46: =-Supuestos!$F$91 -> 0 | H46: =-Supuestos!$F$91 -> 0 | I46: =-Supuestos!$F$91 -> 0 | J46: =-Supuestos!$F$91 -> 0 | K46: =-Supuestos!$F$91 -> 0 | ... AM46: =-Supuestos!$F$91 -> 0
B47: Resultado económico frente a alquilar la casa | C47: =C44+C46 -> -135685.4 | D47: =D44+D46 -> -2194.9767 | E47: =E44+E46 -> -1642.9894 | F47: =F44+F46 -> -1102.7021 | G47: =G44+G46 -> -573.57517 | H47: =H44+H46 -> -219.9878 | I47: =I44+I46 -> 105.08516 | J47: =J44+J46 -> 206.79061 | ... AM47: =AM44+AM46 -> 1078.5811
B48: Resultado económico acumulado | C48: =C47 -> -135685.4 | D48: =C48+D47 -> -137880.38 | E48: =D48+E47 -> -139523.37 | F48: =E48+F47 -> -140626.07 | G48: =F48+G47 -> -141199.65 | H48: =G48+H47 -> -141419.64 | I48: =H48+I47 -> -141314.55 | J48: =I48+J47 -> -141107.76 | K48: =J48+K47 -> -140804.35 | ... AM48: =AL48+AM47 -> -116787.85

Sheet Mercado_verificado
A1: Precios del mercado: solo fichas VERIFICADAS (ARS por mes, con IVA)
A2: USD pasados a pesos con el TC de Supuestos; precios 'IVA excluido' llevados a con IVA. Una cadena con varias sedes cuenta una vez. No se usan precios históricos.
A4: Zona | B4: Concepto | C4: Planes únicos | D4: Marcas | E4: Mínimo | F4: Mediana | G4: Máximo | H4: Vigencia del precio | I4: Moneda publicada | J4: IVA publicado
A5: A · Cercana (Com. 9, 10, 11, 12, 15) | B5: 12-13 días por mes | C5: 1 | D5: Ambrela | E5: 103000 | F5: 103000 | G5: 103000 | H5: publicado_sin_vigencia | I5: ARS | J5: sin aclarar
A6: A · Cercana (Com. 9, 10, 11, 12, 15) | B6: 8-10 días por mes | C6: 1 | D6: Ambrela | E6: 89000 | F6: 89000 | G6: 89000 | H6: publicado_sin_vigencia | I6: ARS | J6: sin aclarar
A7: A · Cercana (Com. 9, 10, 11, 12, 15) | B7: Puesto fijo (por mes) | C7: 1 | D7: Ambrela | E7: 118000 | F7: 118000 | G7: 118000 | H7: publicado_sin_vigencia | I7: ARS | J7: sin aclarar
A8: A · Cercana (Com. 9, 10, 11, 12, 15) | B8: Sala (por hora) | C8: 2 | D8: Ambrela | E8: 13000 | F8: 19500 | G8: 26000 | H8: publicado_sin_vigencia | I8: ARS | J8: sin aclarar
A9: C · Centro y Palermo (Com. 1, 14 y otras) | B9: 12-13 días por mes | C9: 1 | D9: HUERTA Coworking | E9: 302500 | F9: 302500 | G9: 302500 | H9: vigente_comprobado | I9: ARS | J9: excluido
A10: C · Centro y Palermo (Com. 1, 14 y otras) | B10: 2 días fijos por semana (L y V) | C10: 1 | D10: HUERTA Coworking | E10: 108900 | F10: 108900 | G10: 108900 | H10: vigente_comprobado | I10: ARS | J10: excluido
A11: C · Centro y Palermo (Com. 1, 14 y otras) | B11: 4-5 días por mes | C11: 7 | D11: HUERTA Coworking, Regus (IWG) | E11: 101400 | F11: 132600 | G11: 163350 | H11: vigente_comprobado | I11: ARS, USD | J11: excluido, sin aclarar
A12: C · Centro y Palermo (Com. 1, 14 y otras) | B12: 8-10 días por mes | C12: 7 | D12: HUERTA Coworking, Regus (IWG) | E12: 154440 | F12: 201240 | G12: 264990 | H12: vigente_comprobado | I12: ARS, USD | J12: excluido, sin aclarar
A13: C · Centro y Palermo (Com. 1, 14 y otras) | B13: Ilimitado flex (por mes) | C13: 11 | D13: HUERTA Coworking, Regus (IWG), WeWork | E13: 248040 | F13: 341640 | G13: 639896 | H13: vigente_comprobado | I13: ARS, USD | J13: excluido, sin aclarar
A14: C · Centro y Palermo (Com. 1, 14 y otras) | B14: Pase diario | C14: 2 | D14: Regus (IWG) | E14: 76440 | F14: 81120 | G14: 85800 | H14: vigente_comprobado | I14: USD | J14: sin aclarar
A15: C · Centro y Palermo (Com. 1, 14 y otras) | B15: Puesto fijo (por mes) | C15: 1 | D15: HUERTA Coworking | E15: 387200 | F15: 387200 | G15: 387200 | H15: vigente_comprobado | I15: ARS | J15: excluido
A16: C · Centro y Palermo (Com. 1, 14 y otras) | B16: Sala (por hora) | C16: 6 | D16: HUERTA Coworking, Regus (IWG) | E16: 70200 | F16: 103001 | G16: 153065 | H16: vigente_comprobado | I16: ARS, USD | J16: excluido, sin aclarar

Sheet Mercado_no_verificado
A1: Precios de fichas PROBABLES o INCIERTAS: aparte, no alimentan el modelo
A2: Misma conversión que la hoja verificada. Sin confirmar que la sede exista, siga abierta o que el precio esté vigente.
A4: Zona | B4: Concepto | C4: Planes únicos | D4: Marcas | E4: Mínimo | F4: Mediana | G4: Máximo | H4: Vigencia del precio | I4: Moneda publicada | J4: IVA publicado
A5: A · Cercana (Com. 9, 10, 11, 12, 15) | B5: Puesto fijo (por mes) | C5: 2 | D5: elburó | E5: 257000 | F5: 278500 | G5: 300000 | H5: publicado_sin_vigencia | I5: ARS | J5: sin aclarar
A6: C · Centro y Palermo (Com. 1, 14 y otras) | B6: 4-5 días por mes | C6: 6 | D6: Spaces (IWG) | E6: 101400 | F6: 124800 | G6: 154440 | H6: vigente_comprobado | I6: USD | J6: sin aclarar
A7: C · Centro y Palermo (Com. 1, 14 y otras) | B7: 8-10 días por mes | C7: 6 | D7: Spaces (IWG) | E7: 154440 | F7: 193440 | G7: 248040 | H7: vigente_comprobado | I7: USD | J7: sin aclarar
A8: C · Centro y Palermo (Com. 1, 14 y otras) | B8: Ilimitado flex (por mes) | C8: 6 | D8: Spaces (IWG) | E8: 248040 | F8: 310440 | G8: 372840 | H8: vigente_comprobado | I8: USD | J8: sin aclarar
A9: C · Centro y Palermo (Com. 1, 14 y otras) | B9: Pase diario | C9: 1 | D9: Spaces (IWG) | E9: 85800 | F9: 85800 | G9: 85800 | H9: vigente_comprobado | I9: USD | J9: sin aclarar
A10: C · Centro y Palermo (Com. 1, 14 y otras) | B10: Sala (por hora) | C10: 1 | D10: Spaces (IWG) | E10: 60840 | F10: 60840 | G10: 60840 | H10: vigente_comprobado | I10: USD | J10: sin aclarar

Sheet Censo
A1: Qué hay en el censo de sedes (98 fichas) y cuánto está confirmado
A2: Solo las fichas 'verificado' + 'principal' alimentan los precios. Probable e incierto van aparte. Cerradas, GBA y próximas aperturas están excluidas.
A4: Zona | B4: Estado de la ficha | C4: Categoría | D4: Fichas
A5: A · Cercana (Com. 9, 10, 11, 12, 15) | B5: cerrado | C5: excluida | D5: 2
A6: A · Cercana (Com. 9, 10, 11, 12, 15) | B6: incierto | C6: candidata_pendiente | D6: 10
A7: A · Cercana (Com. 9, 10, 11, 12, 15) | B7: incierto | C7: excluida | D7: 1
A8: A · Cercana (Com. 9, 10, 11, 12, 15) | B8: incierto | C8: sustituto | D8: 1
A9: A · Cercana (Com. 9, 10, 11, 12, 15) | B9: probable | C9: candidata_pendiente | D9: 10
A10: A · Cercana (Com. 9, 10, 11, 12, 15) | B10: probable | C10: excluida | D10: 1
A11: A · Cercana (Com. 9, 10, 11, 12, 15) | B11: probable | C11: principal | D11: 1
A12: A · Cercana (Com. 9, 10, 11, 12, 15) | B12: probable | C12: secundaria | D12: 4
A13: A · Cercana (Com. 9, 10, 11, 12, 15) | B13: verificado | C13: principal | D13: 2
A14: B · Norte (Com. 13: Belgrano, Núñez) | B14: probable | C14: candidata_pendiente | D14: 12
A15: B · Norte (Com. 13: Belgrano, Núñez) | B15: probable | C15: principal | D15: 4
A16: B · Norte (Com. 13: Belgrano, Núñez) | B16: proxima_apertura | C16: excluida | D16: 2
... A31: D · Fuera de CABA o sin zona | B31: verificado | C31: excluida | D31: 8
A32: TOTAL | D32: 98

Sheet Datos_faltantes
A1: Datos que faltan (ninguno se buscó en la web: se pregunta primero)
A2: Lo que no tiene dato entra en 0 o en un piso con fuente, así que el resultado del modelo es una COTA OPTIMISTA: lo real es peor o igual.
A4: N° | B4: Qué falta | C4: Por qué importa | D4: Cómo está cargado hoy | E4: Quién lo puede dar
A5: 1 | B5: Valor de alquiler (y de venta) de la casa de 450 m² | C5: Es el costo de oportunidad: lo que se deja de cobrar. Sin él no se puede decir si conviene más alquilar la casa. | D5: alquiler_casa_usd = 0. El Resumen y la hoja Lectura muestran cuánto resultado operativo queda para pagarlo. | E5: Cris (o avisos de casas de 300 a 600 m² en Villa del Parque, Devoto, Santa Rita y Agronomía)
A6: 2 | B6: Facturas de luz, gas y agua de la casa (12 meses) o consumo estimado | C6: Hoy solo hay tarifas, no consumo. Con 40 a 60 personas y aire acondicionado puede ser un costo grande. | D6: servicios_usd = solo cargos fijos (USD 27 por mes). | E6: Cris (facturas) o un profesional de instalaciones
A7: 3 | B7: Honorarios de contador (Responsable Inscripto) | C7: Es un costo fijo seguro. | D7: admin_usd = 0. | E7: Cris / contador
A8: 4 | B8: Plano de la casa y m² reales por piso | C8: Define cuántos puestos entran, el techado del patio y la superficie de la unidad de uso (500 m² cambia el trámite). | D8: Capacidad supuesta: 7,5 a 11 m² por puesto; patio de 60 m² supuesto. | E8: Cris (planos) / arquitecto
A9: 5 | B9: Demanda local: cuántos interesados hay en el barrio | C9: Todo el ritmo de altas es supuesto. No hay un solo dato de usuarios potenciales ni de disposición a pagar. | D9: Altas por mes supuestas (1 a 5). | E9: Cris (preventa o lista de espera)
A10: 6 | B10: Precio de relleno de pileta | C10: No hay precio en las fuentes. | D10: pileta_usd = 0. | E10: Presupuesto de albañilería
A11: 7 | B11: Precio de cabinas acústicas | C11: No hay precio argentino. | D11: cabina_usd = 0. | E11: Proveedor
A12: 8 | B12: Precio de baño accesible | C12: El rango usado es de reforma de baño común. | D12: Proxy: reforma 'media' de ARS 5 a 9 millones. | E12: Presupuesto
A13: 9 | B13: Mesa de reuniones, sillas de sala, espresso comercial, vajilla, switch PoE y cableado | C13: Equipamiento sin precio. | D13: No incluidos. | E13: Proveedores
A14: 10 | B14: Cotización de internet empresarial simétrica | C14: Hoy hay precios de planes residenciales. | D14: Fibra de combo + respaldo Starlink. | E14: Operadores
A15: 11 | B15: Certificado urbanístico y de uso conforme; regularización de planos (catastro 2008 no muestra subsuelo ni planta alta) | C15: El Código dice que el uso está permitido, pero no hay certificado. Puede haber multas y obra de regularización. | D15: No cuantificado. | E15: Gestor / arquitecto (entorno_y_normativa.md, 2.6)
A16: 12 | B16: Si techar el patio se puede; estacionamiento exigible (2 módulos); accesibilidad en una casa de 3 niveles | C16: Pueden sumar obra o frenar el proyecto. | D16: No cuantificado; el techado de 60 m² está incluido como si se pudiera. | E16: Arquitecto / DGIUR
... A20: 16 | B20: Secciones 5 a 9 de entorno_y_normativa.md (escala de Comuna, estado de las leyes) | C20: El archivo anuncia secciones que nunca se escribieron. | D20: — | E20: Siguiente tramo
